Workbook

Sheet 0. README
A1: SkinBB HLHP — Scenario Library v3.4 (Evidence-Base enrichment) -> adds 4 evidence-backed concerns (Premature Aging/Sun Damage, Fungal, Heat Rash, Dark Marks/PIH), Nutrition & Lifestyle modifier layers, and a Did-You-Know education layer. Built on v3.3.1 (SFI recalibration). Architecture, schema and tone unchanged. -> v3.6 adds sheet 17 (Routine Change Rules) for the 'What's Different Today' card
A3: What this is
A4: A synthesis layer between the published evidence (1,800+ PubMed-cited findings) and the HLHP/SFI
A5: user-facing engine. Every cell maps a specific environmental scenario × skin type × concern to:
A6: • Risk score (0–5)
A7: • Confidence tier (HIGH / MODERATE / INFERRED) with cite count
A8: • Three alert levels (L0 compact / L1 personalised / L2 explainer) — all product-free
A9: • PMID anchors for traceability
A10: • Indian climatic zone applicability
A12: How it works
A13: 1. SINGLE-FACTOR cells (750): Factor × Band × Skin Type × Concern.
A14: For each cell, the system queries the evidence base for rows whose trigger band and user filter
... A128: 'Time Overlay' sheet's why-it-matters column + a real citation, and get dermatologist sign-off before shipping.

Sheet System Map
A1: SYSTEM MAP — SkinBB HLHP Scenario Library
A2: Read-only overview of every sheet, its role, and how the scenario counts multiply out. Nothing here changes the model — it's a mirror to think from.
A3: ="Generated "&TEXT(TODAY(),"dd-mmm-yyyy")&" · "&COUNTA(A6:A39)&" sheets inventoried below"
A5: # | B5: Sheet | C5: Category | D5: Lang | E5: Purpose | F5: Rows | G5: Flag
A6: 1 | B6: 0. README | C6: Meta / Docs | D6: EN | E6: Master changelog, architecture, locked principles, sheet map | F6: =COUNTA('0. README'!A:A)
A7: 2 | B7: 1. India Climatic Zones | C7: Reference | D7: EN | E7: 6 zones, 62 cities, seasonal band profiles | F7: =COUNTA('1. India Climatic Zones'!A:A)
A8: 3 | B8: 2. Bands Reference | C8: Reference | D8: EN | E8: Locked band thresholds (mirrors live engine) | F8: =COUNTA('2. Bands Reference'!A:A)
A9: 4 | B9: 3. Confidence Framework | C9: Reference | D9: EN | E9: HIGH / MODERATE / INFERRED rules + evidence audit | F9: =COUNTA('3. Confidence Framework'!A:A)
A10: 5 | B10: Time-of-Day Logic | C10: Reference | D10: EN | E10: Time-of-day modifier logic | F10: =COUNTA('Time-of-Day Logic'!A:A)
A11: 6 | B11: Time Overlay | C11: Reference | D11: EN | E11: Time overlay matrix | F11: =COUNTA('Time Overlay'!A:A)
A12: 7 | B12: Gap Analysis | C12: Reference / Meta | D12: EN | E12: Coverage gaps & conflicts (the roadmap) | F12: =COUNTA('Gap Analysis'!A:A)
A13: 8 | B13: 4. Temperature Cells | C13: Production · Single-factor | D13: EN | E13: Temperature × band × skin type × concern | F13: =COUNTA('4. Temperature Cells'!A:A)
A14: 9 | B14: 5. AQI Cells | C14: Production · Single-factor | D14: EN | E14: AQI × band × skin type × concern | F14: =COUNTA('5. AQI Cells'!A:A)
A15: 10 | B15: 6. UV Cells | C15: Production · Single-factor | D15: EN | E15: UV × band × skin type × concern | F15: =COUNTA('6. UV Cells'!A:A)
A16: 11 | B16: 7. Humidity Cells | C16: Production · Single-factor | D16: EN | E16: Humidity × band × skin type × concern | F16: =COUNTA('7. Humidity Cells'!A:A)
A17: 12 | B17: 8. Compound Scenarios Index | C17: Production · Compound | D17: EN | E17: 21 named India scenarios (C01–C21) w/ bands, zones, seasons | F17: =COUNTA('8. Compound Scenarios Index'!A:A)
A18: 13 | B18: 9. Compound Cell Library | C18: Production · Compound | D18: EN | E18: Compound cells: scenario × skin × concern, L0/L1/L2 | F18: =COUNTA('9. Compound Cell Library'!A:A)
A19: 14 | B19: 10. Master Library | C19: Production · Master | D19: EN | E19: All single-factor cells, flat-queryable (union of 4–7) | F19: =COUNTA('10. Master Library'!A:A)
A20: 15 | B20: 11. Guest Mode | C20: Production · Guest | D20: EN | E20: Guest-mode variant (no personalisation) | F20: =COUNTA('11. Guest Mode'!A:A)
A21: 16 | B21: 12. Age Modifiers | C21: Modifier layer | D21: EN | E21: Age-based nudges | F21: =COUNTA('12. Age Modifiers'!A:A)
A22: 17 | B22: 13. Gender + Life-Stage | C22: Modifier layer | D22: EN | E22: Gender & life-stage nudges | F22: =COUNTA('13. Gender + Life-Stage'!A:A)
A23: 18 | B23: 14. Nutrition Modifiers | C23: Modifier layer | D23: EN | E23: 7 evidence-backed nutrition nudges | F23: =COUNTA('14. Nutrition Modifiers'!A:A)
A24: 19 | B24: 15. Lifestyle Modifiers | C24: Modifier layer | D24: EN | E24: 7 lifestyle nudges | F24: =COUNTA('15. Lifestyle Modifiers'!A:A)
A25: 20 | B25: 16. Did-You-Know Nuggets | C25: Education layer | D25: EN | E25: Cited education micro-cards | F25: =COUNTA('16. Did-You-Know Nuggets'!A:A)
A26: 21 | B26: 17. Routine Change Rules | C26: Modifier layer | D26: EN | E26: What's Different Today' card logic | F26: =COUNTA('17. Routine Change Rules'!A:A)
A27: 22 | B27: Glossary | C27: Meta / Docs | D27: EN | E27: Term definitions | F27: =COUNTA(Glossary!A:A)
A28: 23 | B28: Hindi (Devanagari) | C28: Translation | D28: HI | E28: Master Hindi string table | F28: =COUNTA('Hindi (Devanagari)'!A:A)
A29: 24 | B29: Guest Mode Hindi | C29: Translation | D29: HI | E29: Mirror of 11. Guest Mode | F29: =COUNTA('Guest Mode Hindi'!A:A)
A30: 25 | B30: Time Overlay Hindi | C30: Translation | D30: HI | E30: Mirror of Time Overlay | F30: =COUNTA('Time Overlay Hindi'!A:A)
A31: 26 | B31: Did-You-Know Nuggets Hindi | C31: Translation | D31: HI | E31: Mirror of 16. Nuggets | F31: =COUNTA('Did-You-Know Nuggets Hindi'!A:A)
A32: 27 | B32: Temperature Cells Hindi | C32: Translation | D32: HI | E32: Mirror of 4. Temperature Cells | F32: =COUNTA('Temperature Cells Hindi'!A:A)
A33: 28 | B33: AQI Cells Hindi | C33: Translation | D33: HI | E33: Mirror of 5. AQI Cells | F33: =COUNTA('AQI Cells Hindi'!A:A)
A34: 29 | B34: UV Cells Hindi | C34: Translation | D34: HI | E34: Mirror of 6. UV Cells | F34: =COUNTA('UV Cells Hindi'!A:A)
A35: 30 | B35: Humidity Cells Hindi | C35: Translation | D35: HI | E35: Mirror of 7. Humidity Cells | F35: =COUNTA('Humidity Cells Hindi'!A:A)
A36: 31 | B36: Compound Cell Library Hindi | C36: Translation | D36: HI | E36: Mirror of 9. Compound Cell Library | F36: =COUNTA('Compound Cell Library Hindi'!A:A)
A37: 32 | B37: Master Library Hindi | C37: Translation | D37: HI | E37: Mirror of 10. Master Library | F37: =COUNTA('Master Library Hindi'!A:A)
A38: 33 | B38: 6. UV Cells (backup v3.6) | C38: ⚠ BACKUP | D38: EN | E38: Stray backup living in production file | F38: =COUNTA('6. UV Cells (backup v3.6)'!A:A) | G38: Move out / delete
A39: 34 | B39: Temp Cells backup v3.6 | C39: ⚠ BACKUP | D39: EN | E39: Stray backup living in production file | F39: =COUNTA('Temp Cells backup v3.6'!A:A) | G39: Move out / delete
A42: THE COMBINATORICS — where the scenario count comes from
A44: Dimension | B44: Count | C44: Values
A45: Factors | B45: 4 | C45: Temperature, AQI, UV, Humidity
A46: Bands (across all factors) | B46: 24 | C46: Temp 7 · AQI 6 · UV 5 · Humidity 6
A47: Skin types | B47: 5 | C47: Normal, Dry, Oily, Combination, Sensitive
A48: Concerns | B48: 14 | C48: Dryness, Eczema, Acne, Melasma, PIH, Aging, Fungal, Heat Rash, Dark Circles, Keloid, Vitiligo, Hair/Scalp, Tan, Oily
A49: Climatic zones | B49: 6 | C49: CN, HD, TP, HH, TN, CH
A50: Languages | B50: 2 | C50: English + Hindi (full mirror)
A51: Compound scenarios | B51: 21 | C51: Named India presets C01–C21
A53: Layer | B53: How it multiplies | C53: Theoretical | D53: Built (live) | E53: Coverage
A54: Single-factor cells | B54: 24 bands × 5 skin × 14 concerns | C54: =B46*B47*B48 | D54: =COUNTA('10. Master Library'!A:A)-1 | E54: =D54/C54
A55: Compound cells | B55: 21 scenarios × 5 skin × concerns (varies) | C55: — | D55: =COUNTA('9. Compound Cell Library'!A:A)-1 | E55: =ROUND(D55/(B51*B47),1)&" concerns/scn"
A56: English content total | C56: — | D56: =D54+D55
A57: Plus Hindi mirror (×2) | D57: =D56*2
A59: Reading: you've built ~2 of every 3 theoretically-possible single-factor cells. The 'missing third' is mostly concern×band pairs with no evidence — that's the INFERRED frontier, not an error.
A61: WHAT THE MAP REVEALS
A63: Sheets by role | B63: # | D63: Observations & flags
A64: Production content (EN) | B64: =COUNTIF(C6:C39,"Production*") | D64: 1. 30% of all sheets (10 of 34) are Hindi mirrors. Every English edit must be mirrored — that's a doubling tax on every change. Worth a single 'source → translation' status tracker.
A65: Reference / framework | B65: =COUNTIF(C6:C39,"Reference*") | D65: 2. 2 stray backup sheets live inside the production file (rows 33–34). These drift and get edited by accident — move to a separate archive file or delete.
A66: Modifier / education layers | B66: =COUNTIF(C6:C39,"Modifier*")+COUNTIF(C6:C39,"Education*") | D66: 3. Single-factor coverage is 68% (1,140 of 1,680 possible). The missing third = concern×band pairs with no evidence. This is your INFERRED frontier / roadmap, not a defect.
A67: Translation (Hindi mirrors) | B67: =COUNTIF(C6:C39,"Translation") | D67: 4. Compound library carries ~9 concerns per scenario (940 cells), deeper than the single-factor sheets. Confirm that's intended and not accidental duplication.
A68: Meta / docs | B68: =COUNTIF(C6:C39,"Meta*") | D68: 5. Version drift: file is v3.5 (name) / v3.6 (backup tabs) / README changelog to v3.4. No single source-of-truth version cell. One 'current version + date' anchor would fix it.
A69: ⚠ Backups in production file | B69: =COUNTIF(C6:C39,"*BACKUP*") | D69: 6. Master Library (1,140) = exact union of the 4 factor sheets. Good — it's a true flattened view, not a separate hand-maintained copy. Keep it formula/rule-derived if possible.
A70: TOTAL | B70: =COUNTA(B6:B39)

Sheet 1. India Climatic Zones
A1: Zone Code | B1: Zone Name | C1: Description | D1: Dominant Skin Stressors | E1: Cities (sample) | F1: # Cities
A2: HD | B2: Hot & Dry | C2: NW deserts and adjoining plains. Extreme summer heat, severe winter dryness, low humidity year-round, occasional dust storms. | D2: Critical low humidity · Extreme heat · Very high UV · Dust irritation | E2: Jodhpur, Bikaner, Jaisalmer, Jaipur, Ahmedabad, Bhuj ... | F2: 10
A3: HH | B3: Warm & Humid Coastal | C3: All Indian coastlines (Arabian Sea and Bay of Bengal). High humidity year-round, moderate temperature range, salt air, intense monsoon. | D3: Very high humidity · Sweat-sebum pore-clogging · Heat + humidity combination · Reflected UV at beaches | E3: Mumbai, Chennai, Kolkata, Goa, Mangalore, Kochi ... | F3: 29
A4: CN | B4: Composite North Plains | C4: Indo-Gangetic Plain. Extreme summer, cold dry winters, monsoon rains, severe AQI in winter from inversion + stubble burning. | D4: Severe winter AQI (inversion + stubble) · Cold + dry winter combination · Extreme summer heat · Pre-monsoon dust | E4: Delhi, Gurgaon, Noida, Faridabad, Lucknow, Kanpur ... | F4: 22
A5: TP | B5: Temperate Plateau | C5: Deccan Plateau. Mild year-round temperatures, predictable monsoon, moderate humidity, generally optimal for skin. | D5: Pre-monsoon UV spike · Mild humidity swings · Localized city AQI (Bengaluru, Hyderabad) | E5: Bengaluru, Pune, Hyderabad, Mysore, Nashik, Coimbatore ... | F5: 14
A6: CH | B6: Cold Himalayan | C6: Himalayan belt — high altitude. Cold winters, mild summers, intense UV at altitude, snow reflection, low humidity in winter. | D6: Altitude UV intensification (+10–12% per 1000m) · Snow-reflected UV (up to 80%) · Extreme cold + dry winter · Wind chill barrier compromise | E6: Shimla, Manali, Srinagar, Leh, Darjeeling, Gangtok ... | F6: 13
A7: TN | B7: Tropical Northeast | C7: Northeast India — high rainfall, very high humidity year-round, mild temperature range, moderate UV with frequent cloud cover. | D7: Year-round high humidity (fungal risk) · Heavy monsoon saturation · Sweat-trapping in folds | E7: Guwahati, Shillong, Imphal, Agartala, Aizawl, Itanagar ... | F7: 9
A10: Zone × Season Typical Band Profile
A11: Zone | B11: Season | C11: Temperature | D11: Humidity | E11: UV | F11: AQI
A12: HD | B12: Summer (Apr–Jun) | C12: Hot to Extreme Heat | D12: Critical Low to Low | E12: Very High to Extreme | F12: 10
A13: HD | B13: Monsoon (Jul–Sep) | C13: Warm to Hot | D13: Low to High | E13: High | F13: 10
A14: HD | B14: Winter (Dec–Jan) | C14: Cool to Cold | D14: Very Low to Low | E14: Moderate | F14: 10
A15: HD | B15: Post-monsoon (Oct–Nov) | C15: Warm | D15: Low | E15: High | F15: 10
A16: HH | B16: Summer (Mar–May) | C16: Warm to Hot | D16: High to Very High | E16: Very High | F16: 29
A17: HH | B17: Monsoon (Jun–Sep) | C17: Warm | D17: Very High to Extreme | E17: Moderate (cloudy) | F17: 29
A18: HH | B18: Post-monsoon (Oct–Nov) | C18: Warm | D18: High | E18: High | F18: 29
A19: HH | B19: Winter (Dec–Feb) | C19: Cool to Warm | D19: High | E19: Moderate | F19: 29
A20: CN | B20: Summer (Apr–Jun) | C20: Hot to Extreme Heat | D20: Low | E20: Very High | F20: 22
A21: CN | B21: Monsoon (Jul–Sep) | C21: Warm to Hot | D21: High to Very High | E21: High | F21: 22
A22: CN | B22: Post-monsoon (Oct–Nov) | C22: Warm to Cool | D22: Low to Moderate | E22: Moderate to High | F22: 22
A23: CN | B23: Winter (Dec–Feb) | C23: Cold to Cool | D23: Very Low to Low | E23: Moderate | F23: 22
... A34: TN | B34: Winter (Dec–Feb) | C34: Cool to Warm | D34: High | E34: Moderate | F34: 9
A37: City → Zone Lookup
A38: City | B38: Zone Code | C38: Zone Name
A39: Agartala | B39: TN | C39: Tropical Northeast
A40: Agra | B40: CN | C40: Composite North Plains
A41: Ahilyanagar | B41: TP | C41: Temperate Plateau
A42: Ahmedabad | B42: HD | C42: Hot & Dry
A43: Aizawl | B43: TN | C43: Tropical Northeast
A44: Ajmer | B44: HD | C44: Hot & Dry
A45: Allahabad | B45: CN | C45: Composite North Plains
A46: Amritsar | B46: CN | C46: Composite North Plains
A47: Bengaluru | B47: TP | C47: Temperate Plateau
A48: Bhopal | B48: CN | C48: Composite North Plains
A49: Bhubaneswar | B49: HH | C49: Warm & Humid Coastal
... A135: Visakhapatnam | B135: HH | C135: Warm & Humid Coastal

Sheet 2. Bands Reference
A1: Factor | B1: Band Label | C1: Range | D1: Points (of 25) | E1: Band Key
A2: Temperature
B3: Extreme Cold | C3: <5°C | D3: 0 | E3: extreme_cold
B4: Cold | C4: 5–14°C | D4: 5 | E4: cold
B5: Cool | C5: 15–19°C | D5: 12 | E5: cool
B6: Optimal | C6: 20–27°C | D6: 25 | E6: optimal
B7: Warm | C7: 28–34°C | D7: 12 | E7: warm
B8: Hot | C8: 35–42°C | D8: 5 | E8: hot
B9: Extreme Heat | C9: >42°C | D9: 0 | E9: extreme_heat
A10: AQI
B11: Good | C11: 0–50 | D11: 25 | E11: good
B12: Satisfactory | C12: 51–100 | D12: 18 | E12: satisfactory
B13: Moderate | C13: 101–200 | D13: 10 | E13: moderate
B14: Poor | C14: 201–300 | D14: 5 | E14: poor
B15: Very Poor | C15: 301–400 | D15: 2 | E15: very_poor
B16: Severe | C16: >400 | D16: 0 | E16: severe
A17: UV
B18: Low | C18: 0–2 | D18: 25 | E18: low
B19: Moderate | C19: 3–5 | D19: 18 | E19: moderate
B20: High | C20: 6–7 | D20: 11 | E20: high
B21: Very High | C21: 8–10 | D21: 5 | E21: very_high
B22: Extreme | C22: 11+ | D22: 0 | E22: extreme
A23: Humidity
B24: Critical Low | C24: <10% | D24: 0 | E24: critical_low
B25: Very Low | C25: 10–19% | D25: 5 | E25: very_low
B26: Low | C26: 20–39% | D26: 12 | E26: low
B27: Optimal | C27: 40–60% | D27: 25 | E27: optimal
B28: High | C28: 61–79% | D28: 15 | E28: high
B29: Very High | C29: 80–89% | D29: 9 | E29: very_high
B30: Extreme | C30: >90% | D30: 5 | E30: extreme

Sheet 3. Confidence Framework
A1: Tier | B1: Criteria | C1: Color | D1: Operational meaning | E1: 60% problem signal
A2: HIGH | B2: ≥2 PMID-cited findings AND ≥1 India/Fitzpatrick III–V relevant | C2: HIGH | D2: Engine can surface confidently; minimal editorial caveat needed. | E2: Not a gap.
A3: MODERATE | B3: ≥2 PMID-cited findings OR (≥1 PMID + ≥1 book citation) | C3: MODERATE | D3: Engine surfaces with standard caveat; flag for editorial review. | E3: Partial gap — India-specific research needed.
A4: INFERRED | B4: Mechanism-consistent extrapolation only (no direct PMID for the cell) | C4: INFERRED | D4: Engine surfaces with explicit hedge; treat as roadmap item. | E4: Direct 60% problem signal — research priority.

Sheet Time-of-Day Logic
A1: Time-of-Day Logic — engine specification (v3.5, 3-window model)
A2: PURPOSE: scenario cells describe CURRENT environmental bands (UV/AQI/temperature/humidity). They are time-blind — the same cell shows the same alert at 7am and 9pm. This sheet specifies how the engine reshapes the ACTION half of each alert by the user's LOCAL clock. The science (the condition-describing first sentence) does not change — only the action / framing does. No cells are pre-generated; this is an implementation spec.
A4: 1. The three time windows (user's local time)
A5: Window | B5: Local time | C5: Framing | D5: What the alert should do
A6: MORNING | B6: before ~09:00 | C6: CURRENT + ANTICIPATORY | D6: State what conditions are RIGHT NOW, then — only if a band change is forecast today — add the 'later it will…' note so the user can prep before going out.
A7: DAYTIME | B7: 09:00–16:00 | C7: CURRENT (peak / present-tense) | D7: Describe what is happening now and the protective action. This is exactly what the existing v3.5 cell text already does.
A8: EVENING→NIGHT | B8: after ~16:00 | C8: CURRENT → repair | D8: Describe current conditions (the peak is behind, so little left to anticipate today). As evening sets in, pivot the action from 'protect' to 'cleanse off the day + overnight repair'.
A10: WHY THREE, NOT FOUR: an earlier draft used a pure-anticipatory morning that hid the present ('UV climbs to extreme by midday') and an anticipatory evening. Both were wrong. Morning must be honest about NOW (a 7am walker needs to know UV is low right now) AND flag the coming peak. After ~4pm the day's peak has passed, so there is nothing left to anticipate — the alert is simply current conditions easing into the evening repair story. Anticipating at 6pm would mean forecasting tomorrow, which is a different feature.
A12: 2. When to add the anticipatory 'coming change' note — the band-change rule
A13: RULE: in the MORNING window, add the anticipatory note for ANY factor — UV, AQI, Temperature OR Humidity — IF AND ONLY IF today's forecast shows that factor crossing into a DIFFERENT BAND later today. The trigger is a forecast band change, not which factor it is. This is data-driven, not factor-stereotyped: if UV stays 'Low' all day, do NOT promise a peak; if Temperature jumps Warm→Extreme Heat by afternoon, DO warn — even though temperature is normally a 'current' factor.
A15: Factor | B15: Typical morning behaviour | C15: Anticipatory note fires when… | D15: Example morning line
A16: UV | B16: Almost always climbs from ~0 to a midday peak → usually crosses bands. | C16: Forecast peak band > current band (the common case). | D16: 'UV is low now but climbs to Very High by midday — sun protection on before you head out.'
A17: AQI | B17: Often worsens through the morning commute / evening inversion in cities. | C17: Forecast AQI band worsens later (e.g. Moderate→Poor). | D17: 'Air is moderate now but worsens through the commute — cleanse off grime when you get in.'
A18: Temperature | B18: Usually stable band; occasionally crosses on heatwave / cold-snap days. | C18: Forecast crosses a band (e.g. Warm→Extreme Heat, or Cool→Cold tonight). | D18: 'Pleasant now, but it climbs into a heatwave by afternoon — plan shade and water.'
A19: Humidity | B19: Usually stable; can cross around monsoon onset or a weather front. | C19: Forecast crosses a band (e.g. Optimal→Very High as rain sets in). | D19: 'Comfortable now, but it turns very humid later — keep skin and folds dry through the day.'
A21: If the factor's band is forecast to stay the SAME all day, the morning alert is just current-conditions (no anticipatory clause). If only the current value is available (no forecast), omit the anticipatory note entirely — never invent a peak.
A23: 3. Worked examples — same sensor reading, six open-times (3-window model)
A24: Example A — UV forecast to cross Low→Extreme today (band change → anticipatory note fires in the morning):
A25: Opens at | B25: UV now | C25: Window | D25: L0 the guest should see
A26: 7:00 am | B26: Low (~1) | C26: MORNING | D26: UV is low right now but climbs to extreme by midday. Easy outdoors now; sun protection on before you're out later.
A27: 9:00 am | B27: High (~6) | C27: MORNING→DAYTIME | D27: UV is strong now and still climbing. Cover up and use daily broad-spectrum sun protection.
A28: 12:00 noon | B28: Extreme (~11) | C28: DAYTIME | D28: UV is at danger levels — skin can burn in minutes. Limit midday sun; cover up and reapply often.
A29: 4:00 pm | B29: Moderate (~5) | C29: EVENING | D29: UV is easing but still real. Keep protection on if you're out — the worst is behind you.
A30: 6:00 pm | B30: Low (~1) | C30: EVENING→NIGHT | D30: The day's strong sun is over. Cleanse off sweat and sunscreen when you settle in.
A31: 9:00 pm | B31: 0 | C31: NIGHT | D31: Sun load for the day is done. Cleanse off the day, moisturise, and let skin repair overnight.
A33: Example B — Temperature forecast Warm→Extreme Heat (a 'current' factor that DOES get an anticipatory note because the band changes):
A34: Opens at | B34: Window | C34: L0 the guest should see
A35: 7:00 am | B35: MORNING | C35: Warm and comfortable now, but a heatwave builds by afternoon. Plan shade and water before it peaks.
A36: 12:00 noon | B36: DAYTIME | C36: Heatwave conditions now — your body and skin are dehydrating. Drink water, stay shaded, rinse off sweat.
A37: 6:00 pm | B37: EVENING→NIGHT | C37: The peak heat is easing. Rehydrate, rinse off the day's sweat, and keep skin lightly moisturised.
A38: 9:00 pm | B38: NIGHT | C38: Cooler now. A gentle cleanse and a light moisturiser before bed help skin recover from the hot day.
A40: Example C — Humidity Very High and forecast to STAY Very High all day (no band change → NO anticipatory note; current-conditions throughout):
A41: Opens at | B41: Window | C41: L0 the guest should see
A42: 7:00 am | B42: MORNING | C42: Very humid, sweaty air today. Keep skin and folds dry; use a light, water-based moisturiser.
A43: 12:00 noon | B43: DAYTIME | C43: Very humid — sweat and oil sit on skin. Cleanse off sweat and keep folds dry.
A44: 9:00 pm | B44: NIGHT | C44: Still humid tonight. A gentle cleanse before bed clears sweat and oil; keep moisturiser light.
A46: 4. How each window reshapes the three alert levels
A47: Level | B47: Morning (current + anticipatory) | C47: Daytime (current peak) | D47: Evening→Night (current → repair)
A48: L0 (≤20w) | B48: Current state + 'prep before you go out'; add coming-band note only if forecast to change. | C48: Current condition + present protective action. = existing cell. | D48: Current easing → 'cleanse off the day'; by night, repair line only (no 'protect/shield').
A49: L1 (≤40w) | B49: Current personalised action + anticipatory prep; keep 'if outdoor time today is long' frame. | C49: Current personalised action (existing cell). | D49: Protect-if-still-out early; by night: cleanse off the day, moisturise, note overnight repair.
A50: L2 (60–90w) | B50: Science + current state + coming-peak prep close. | C50: Existing explainer (existing cell). | D50: Science + 'peak behind you, move to cleanse/repair' close. Drop daytime directives at night.
A52: 5. Engine rules & edge cases
A53: # | B53: Rule
A54: R1 | B54: Window is derived from the USER'S LOCAL TIME (device clock / zone), not server time.
A55: R2 | B55: Anticipatory note fires ONLY on a forecast BAND CHANGE for that factor today (any of the 4 factors). No forecast available → no anticipatory note; never invent a peak.
A56: R3 | B56: After ~16:00 do NOT anticipate later-today peaks (the peak has passed). Only describe current conditions easing into evening repair. (Forecasting tomorrow is a separate feature.)
A57: R4 | B57: NIGHT must not use daytime protection verbs ('cover up','seek shade','reapply sunscreen'). Validation should hard-block these after ~20:00 for UV/AQI.
A58: R5 | B58: Risk SCORE and confidence tier do NOT change with time of day — only the wording changes.
A59: R6 | B59: Window boundaries (≈09:00 and ≈16:00) are defaults; expose as config. Sunrise/sunset-aware boundaries are a v-next nicety (esp. the Himalayan zone where daylight shifts seasonally).
A60: R7 | B60: Compound scenarios follow the same overlay; the dominant-driver action gets the window reshape (e.g. Beach Day UV at 9pm → 'cleanse off salt, sand and sunscreen; rehydrate skin').
A61: R8 | B61: The overlay applies to BOTH guest and personalised alerts; guest simply lacks the concern-specific clause.
A62: R9 | B62: Daytime window text = the existing v3.5 cell text as-is. So only the morning anticipatory clause and the evening/night repair clause are new per cell.
A64: 6. Build shortcut + recommended implementation
A65: REUSE: the Evidence Base (HLHP_Evidence_Base.xlsx) already has Time_of_Day_Phase, Alert_L1_Evening_Personalised and Alert_L1_Evening_Guest columns (never imported here) — use them to seed the EVENING/NIGHT wording. IMPLEMENTATION: build a TIME OVERLAY — a small rule-set per factor that rewrites only the action clause by window — rather than multiplying every cell. The cell stays the single source of the science + daytime text; the overlay supplies the morning anticipatory clause (gated on a forecast band change) and the evening/night repair clause. Estimated content: a morning + an evening/night clause per factor and per compound scenario — a few dozen strings, not thousands of new cells.

Sheet Time Overlay
A1: Time Overlay — morning + evening/night action clauses (v3.5)
A2: HOW THE ENGINE USES THIS: MORNING (before ~09:00): if the forecast moves a factor into a WORSE band, append a morning add-on — rotate D and E; use F instead when the jump is 2+ bands; if the band IMPROVES into a better band, use the good-news note (G); otherwise show current conditions only. EARLY EVENING (~16:00–20:00): use column H (protection wording allowed until ~20:00). NIGHT (after ~20:00): rotate I / J / K — no daytime protection verbs (QA check in column N). Column L adds a rotating 'why it matters' insight (DYK refs → sheet 16). Column M records keying/context flags; column O tracks max words per row. All clauses are product-free (category words only), plain, and short.
A4: Single-factor overlays (by band)
A5: Type | B5: Factor / Scenario | C5: Band / Key | D5: Morning add-on (use only if the band worsens today) | E5: Morning add-on — variant B (rotate with D) | F5: Morning add-on — big-jump variant (band worsens 2+ steps) | G5: Morning good-news note (use only if the band improves today) | H5: Early-evening action (~4–8pm) | I5: Night action (after ~8pm) | J5: Night action — variant B (rotate with I) | K5: Night action — variant C (rotate with I) | L5: Why it matters (micro-insight; DYK ref where noted) | M5: Keying & context flags | N5: QA: banned night verbs | O5: QA: max words (D:K)
A6: UV | B6: UV | C6: Low | D6: — (UV low and staying low; no prep note needed) | G6: UV eases right down today — a lighter routine works; enjoy the gentler sun. | H6: UV is low and fading with the light — nothing extra needed if you're out. | I6: UV is done for the day — cleanse off the day and moisturise before bed. | J6: No sun to undo tonight — a simple cleanse and moisturiser will do. | K6: Quiet sun day — tonight is just cleanse, moisturise, sleep. | L6: Even darker-toned skin, which filters most UVB, still tans and spots — low UV just means less urgency. (DYK #1) | M6: Keyed to FORECAST band (add-on describes the band the day rises into) | N6: {=IF(SUMPRODUCT(--ISNUMBER(SEARCH({"cover up","seek shade","reapply","sun protection","protection on","protect "},I6&" "&J6&" "&K6)))>0,"⚠ banned night verb","OK")} | O6: {=MAX(IF(LEN(TRIM(D6:K6))=0,0,LEN(TRIM(D6:K6))-LEN(SUBSTITUTE(TRIM(D6:K6)," ",""))+1))}
A7: UV | B7: UV | C7: Moderate | D7: It climbs higher by midday — sun protection on before you head out. | E7: Heading out? The sun strengthens by midday — protection on first. | H7: UV is easing but still around — keep protection on if you're still out. | I7: Sun is down — cleanse off sunscreen and the day, then moisturise. | J7: Day's sun done — wash it off and give skin its overnight drink. | K7: Sun's off duty — your cleanse takes over from your sunscreen. | L7: At UV 8 skin reaches damage thresholds within minutes — moderate isn't harmless. (DYK #2) | M7: Keyed to FORECAST band | N7: {=IF(SUMPRODUCT(--ISNUMBER(SEARCH({"cover up","seek shade","reapply","sun protection","protection on","protect "},I7&" "&J7&" "&K7)))>0,"⚠ banned night verb","OK")} | O7: {=MAX(IF(LEN(TRIM(D7:K7))=0,0,LEN(TRIM(D7:K7))-LEN(SUBSTITUTE(TRIM(D7:K7)," ",""))+1))}
A8: UV | B8: UV | C8: High | D8: It turns strong by midday — cover up and put on sun protection before you're out. | E8: Midday sun turns harsh today — sort your sun protection before you leave. | F8: A two-band UV jump today — from gentle morning to harsh midday; protection before you leave. | H8: Sun is weakening but not done — keep protection on till sundown. | I8: The day's sun is over — cleanse off sunscreen and sweat, then moisturise. | J8: Sunscreen and sweat come off tonight — then moisturise and rest. | K8: Trade sunscreen for moisturiser tonight — skin repairs while you sleep. | L8: Sweat strips up to ~40% of your protection — the midday reapply is what keeps strong sun in check. (DYK #5) | M8: Keyed to FORECAST band | N8: {=IF(SUMPRODUCT(--ISNUMBER(SEARCH({"cover up","seek shade","reapply","sun protection","protection on","protect "},I8&" "&J8&" "&K8)))>0,"⚠ banned night verb","OK")} | O8: {=MAX(IF(LEN(TRIM(D8:K8))=0,0,LEN(TRIM(D8:K8))-LEN(SUBSTITUTE(TRIM(D8:K8)," ",""))+1))}
A9: UV | B9: UV | C9: Very High | D9: It peaks very high by midday — sun protection and shade planned before you go. | E9: Big sun today — pack shade plans and protection before stepping out. | F9: UV jumps several bands to very high today — full protection and shade before you're out. | H9: Still strong for a while yet — protection stays on if you're outdoors. | I9: Sun load is done — cleanse off the day well and let skin repair overnight. | J9: The sun took its toll today — cleanse gently and let repair begin. | K9: Skin worked hard in that sun — clean slate tonight, repair by morning. | L9: Shade, hat and cover-up each add real protection beyond any cream on a very-high day. (DYK #27) | M9: Keyed to FORECAST band | N9: {=IF(SUMPRODUCT(--ISNUMBER(SEARCH({"cover up","seek shade","reapply","sun protection","protection on","protect "},I9&" "&J9&" "&K9)))>0,"⚠ banned night verb","OK")} | O9: {=MAX(IF(LEN(TRIM(D9:K9))=0,0,LEN(TRIM(D9:K9))-LEN(SUBSTITUTE(TRIM(D9:K9)," ",""))+1))}
A10: UV | B10: UV | C10: Extreme | D10: It hits extreme by midday — limit midday sun and cover up before you head out. | E10: Today's sun peaks at extreme — plan around midday and cover up early. | F10: UV rockets to extreme from a mild start — plan the whole day around avoiding midday sun. | H10: Easing from extreme, but the sun still bites — protection and shade till sunset. | I10: No more sun today — cleanse off thoroughly and moisturise for overnight repair. | J10: Big-sun day over — a thorough cleanse tonight sets up overnight repair. | K10: Extreme-UV day behind you — tonight's cleanse and moisturiser do the repair work. | L10: Reapplying ~20 min after heading out cuts your sun dose more than waiting two hours. (DYK #24) | M10: Keyed to FORECAST band | N10: {=IF(SUMPRODUCT(--ISNUMBER(SEARCH({"cover up","seek shade","reapply","sun protection","protection on","protect "},I10&" "&J10&" "&K10)))>0,"⚠ banned night verb","OK")} | O10: {=MAX(IF(LEN(TRIM(D10:K10))=0,0,LEN(TRIM(D10:K10))-LEN(SUBSTITUTE(TRIM(D10:K10)," ",""))+1))}
A11: AQI | B11: AQI | C11: Good | D11: — (air clean and staying clean) | G11: Air clears to clean today — a good day for time outdoors. | H11: Air is clean this evening — enjoy the time out. | I11: Clean-air day — a simple evening cleanse is plenty before bed. | J11: Clean air all day — keep tonight simple: cleanse, then bed. | K11: Nothing clinging to skin today — one gentle wash and lights out. | L11: Clean-air days let skin's own antioxidant oils recover — no cleansing overload needed. (DYK #8) | M11: Keyed to FORECAST band | N11: {=IF(SUMPRODUCT(--ISNUMBER(SEARCH({"cover up","seek shade","reapply","sun protection","protection on","protect "},I11&" "&J11&" "&K11)))>0,"⚠ banned night verb","OK")} | O11: {=MAX(IF(LEN(TRIM(D11:K11))=0,0,LEN(TRIM(D11:K11))-LEN(SUBSTITUTE(TRIM(D11:K11)," ",""))+1))}
A12: AQI | B12: AQI | C12: Satisfactory | D12: — (only a small rise expected; deliberate exception — spec Rule R2 would fire on any band change) | G12: Air improves today — outdoor plans are back on. | H12: Air is fine for an evening outdoors. | I12: Mostly clean today — a gentle evening cleanse is enough. | J12: An easy air day — a light evening cleanse is all it takes. | K12: Air stayed kind — keep tonight to a quick, gentle cleanse. | L12: A small AQI rise barely moves skin load — why this row stays product-free. | M12: Keyed to FORECAST band · deliberate exception to Rule R2 | N12: {=IF(SUMPRODUCT(--ISNUMBER(SEARCH({"cover up","seek shade","reapply","sun protection","protection on","protect "},I12&" "&J12&" "&K12)))>0,"⚠ banned night verb","OK")} | O12: {=MAX(IF(LEN(TRIM(D12:K12))=0,0,LEN(TRIM(D12:K12))-LEN(SUBSTITUTE(TRIM(D12:K12)," ",""))+1))}
A13: AQI | B13: AQI | C13: Moderate | D13: Air worsens through the commute — plan to cleanse off grime later. | E13: Grime builds in the air today — a good cleanse tonight will matter. | H13: Evening air still carries grime — keep outdoor time easy. | I13: Cleanse off the day's settled grime tonight; moisturise after. | J13: The day's grime is sitting on your skin — wash it off before bed. | K13: A light film of city grime — one proper wash clears it. | L13: Polluted air halves skin's protective oils — the evening cleanse restores the reset. (DYK #8) | M13: Keyed to FORECAST band · CONTEXT: assumes weekday commute — use neutral fallback at weekends | N13: {=IF(SUMPRODUCT(--ISNUMBER(SEARCH({"cover up","seek shade","reapply","sun protection","protection on","protect "},I13&" "&J13&" "&K13)))>0,"⚠ banned night verb","OK")} | O13: {=MAX(IF(LEN(TRIM(D13:K13))=0,0,LEN(TRIM(D13:K13))-LEN(SUBSTITUTE(TRIM(D13:K13)," ",""))+1))}
A14: AQI | B14: AQI | C14: Poor | D14: Air gets worse through the day — cleanse well when you're back in. | E14: The air thickens as the day goes on — plan a proper cleanse later. | F14: Air slides two bands today — a good cleanse tonight is essential. | H14: Air stays poor into the evening — keep outdoor spells short. | I14: Wash off the day's pollution tonight and layer a little moisturiser. | J14: Pollution clung to you today — a good cleanse now, moisturiser after. | K14: Tonight's wash undoes the day's pollution — don't skip the moisturiser. | L14: Every +10 fine pollution particles raises pigment-spot scores ~9% — grime is a provable skin-ager. (DYK #14) | M14: Keyed to FORECAST band | N14: {=IF(SUMPRODUCT(--ISNUMBER(SEARCH({"cover up","seek shade","reapply","sun protection","protection on","protect "},I14&" "&J14&" "&K14)))>0,"⚠ banned night verb","OK")} | O14: {=MAX(IF(LEN(TRIM(D14:K14))=0,0,LEN(TRIM(D14:K14))-LEN(SUBSTITUTE(TRIM(D14:K14)," ",""))+1))}
A15: AQI | B15: AQI | C15: Very Poor | D15: Heavy pollution builds today — limit long outdoor spells and cleanse off later. | E15: A heavy-pollution day ahead — keep outdoor spells short and cleanse well after. | F15: Air quality collapses today — minimise time outside and cleanse well after. | H15: The evening smog-trapping weather keeps pollution high — better indoors tonight. | I15: Cleanse off the heavy grime tonight; moisturise to support the barrier. | J15: Heavy grime today — tonight's cleanse is the day's most useful step. | K15: Heavy air today — cleanse thoroughly, then feed the barrier. | L15: Pollution reaches skin from the surface and through blood — nightly cleanse plus antioxidants both help. (DYK #29) | M15: Keyed to FORECAST band | N15: {=IF(SUMPRODUCT(--ISNUMBER(SEARCH({"cover up","seek shade","reapply","sun protection","protection on","protect "},I15&" "&J15&" "&K15)))>0,"⚠ banned night verb","OK")} | O15: {=MAX(IF(LEN(TRIM(D15:K15))=0,0,LEN(TRIM(D15:K15))-LEN(SUBSTITUTE(TRIM(D15:K15)," ",""))+1))}
A16: AQI | B16: AQI | C16: Severe | D16: Hazardous air ahead — stay in where you can and cleanse off after any time out. | E16: The air turns hazardous today — indoors where possible; cleanse after any time out. | F16: A sharp crash to hazardous air today — stay in where you can; cleanse after any time out. | H16: Hazardous air into the night — stay in where you can. | I16: Wash the day's pollution off thoroughly tonight and moisturise well. | J16: The worst air does its damage overnight if it stays on — cleanse thoroughly. | K16: The grime is the day's real damage — a thorough wash, then rich support. | L16: Months in high pollution and skin makes less of its own moisturiser protein. (DYK #13) | M16: Keyed to FORECAST band | N16: {=IF(SUMPRODUCT(--ISNUMBER(SEARCH({"cover up","seek shade","reapply","sun protection","protection on","protect "},I16&" "&J16&" "&K16)))>0,"⚠ banned night verb","OK")} | O16: {=MAX(IF(LEN(TRIM(D16:K16))=0,0,LEN(TRIM(D16:K16))-LEN(SUBSTITUTE(TRIM(D16:K16)," ",""))+1))}
A17: Temperature | B17: Temperature | C17: Extreme Cold | D17: — (already extreme cold) | H17: Bitter cold deepens after sunset — layer up well if you step out. | I17: Bitter cold tonight — moisturise richly before bed to hold water in. | J17: Deep-freeze night — seal water in with a rich layer before bed. | K17: The coldest hours are ahead — the rich layer goes on before bed, not after. | L17: Cold nights spike water loss; skin loses most moisture in the coldest hours. (DYK #7) | M17: ⚠ Keyed to CURRENT band (inconsistent with UV/AQI rows) — engine must reconcile | N17: {=IF(SUMPRODUCT(--ISNUMBER(SEARCH({"cover up","seek shade","reapply","sun protection","protection on","protect "},I17&" "&J17&" "&K17)))>0,"⚠ banned night verb","OK")} | O17: {=MAX(IF(LEN(TRIM(D17:K17))=0,0,LEN(TRIM(D17:K17))-LEN(SUBSTITUTE(TRIM(D17:K17)," ",""))+1))}
A18: Temperature | B18: Temperature | C18: Cold | D18: It dips colder through the day — moisturise before you head out. | E18: A colder snap moves in today — moisturise before stepping out. | H18: The chill sharpens this evening — wrap up for time outside. | I18: Cold evening — a richer moisturiser before bed keeps skin from drying out. | J18: Cold nights pull water from skin — a richer layer before bed helps. | K18: Skin loses most water on cold nights — lock it in before sleep. | L18: Stepping from warm to cold air can spike water-loss six-fold. (DYK #7) | M18: ⚠ Keyed to CURRENT band (inconsistent with UV/AQI rows) — engine must reconcile | N18: {=IF(SUMPRODUCT(--ISNUMBER(SEARCH({"cover up","seek shade","reapply","sun protection","protection on","protect "},I18&" "&J18&" "&K18)))>0,"⚠ banned night verb","OK")} | O18: {=MAX(IF(LEN(TRIM(D18:K18))=0,0,LEN(TRIM(D18:K18))-LEN(SUBSTITUTE(TRIM(D18:K18)," ",""))+1))}
A19: Temperature | B19: Temperature | C19: Cool | D19: — (mild; usually no prep note) | G19: The cold lets up today — a milder day; ease back the heavy layering. | H19: A cool, easy evening — nothing extra needed. | I19: Cool evening — a light moisturiser before bed is enough. | J19: Cool night — a light moisturiser and you're done. | K19: An easy night — a light layer and you're done. | L19: Mild temperatures keep the barrier stable — no special step earns its place. | M19: ⚠ Keyed to CURRENT band (inconsistent with UV/AQI rows) — engine must reconcile | N19: {=IF(SUMPRODUCT(--ISNUMBER(SEARCH({"cover up","seek shade","reapply","sun protection","protection on","protect "},I19&" "&J19&" "&K19)))>0,"⚠ banned night verb","OK")} | O19: {=MAX(IF(LEN(TRIM(D19:K19))=0,0,LEN(TRIM(D19:K19))-LEN(SUBSTITUTE(TRIM(D19:K19)," ",""))+1))}
A20: Temperature | B20: Temperature | C20: Optimal | D20: A heatwave builds by afternoon — plan shade and water before it peaks. | E20: Heat builds to a peak this afternoon — shade and water will earn their keep. | F20: A rare jump straight into severe heat today — clear your midday plans; water and shade throughout. | G20: Temperature turns pleasant today — skin gets an easy day; enjoy it. | H20: A pleasant evening — enjoy it. | I20: An easy evening — keep up your usual routine. | J20: Nothing special needed tonight — your usual routine is right. | K20: Skin had a good day — just keep the routine steady. | L20: A comfortable day is a rare no-stress day for skin — keep it simple. | M20: ⚠ Keyed to CURRENT band (inconsistent with UV/AQI rows) — engine must reconcile | N20: {=IF(SUMPRODUCT(--ISNUMBER(SEARCH({"cover up","seek shade","reapply","sun protection","protection on","protect "},I20&" "&J20&" "&K20)))>0,"⚠ banned night verb","OK")} | O20: {=MAX(IF(LEN(TRIM(D20:K20))=0,0,LEN(TRIM(D20:K20))-LEN(SUBSTITUTE(TRIM(D20:K20)," ",""))+1))}
A21: Temperature | B21: Temperature | C21: Warm | D21: It heats up into the afternoon — plan a sweat rinse and stay shaded. | E21: The afternoon turns hot — a sweat rinse later will feel earned. | F21: Heat surges two bands today — treat midday like a heatwave: water, shade, cool rinses. | H21: Still warm out — water and light clothing if you're staying out. | I21: Warm evening — rinse off the day's sweat and keep moisturiser light. | J21: Warm night — rinse the day's sweat off and keep layers light. | K21: Sweat off, something light on — that's the whole night. | L21: Warm skin makes measurably more oil within an hour of the heat rising. (DYK #15) | M21: ⚠ Keyed to CURRENT band (inconsistent with UV/AQI rows) — engine must reconcile | N21: {=IF(SUMPRODUCT(--ISNUMBER(SEARCH({"cover up","seek shade","reapply","sun protection","protection on","protect "},I21&" "&J21&" "&K21)))>0,"⚠ banned night verb","OK")} | O21: {=MAX(IF(LEN(TRIM(D21:K21))=0,0,LEN(TRIM(D21:K21))-LEN(SUBSTITUTE(TRIM(D21:K21)," ",""))+1))}
A22: Temperature | B22: Temperature | C22: Hot | D22: It gets hotter by afternoon — plan water, shade and a sweat rinse. | E22: A hot afternoon ahead — line up water, shade and a rinse. | H22: Heat lingers into the evening — keep water handy if you're out. | I22: Heat easing tonight — rehydrate, rinse off sweat, moisturise lightly. | J22: The heat is finally easing — water, a rinse, and a light finish. | K22: Drink, rinse, keep it light — heat recovery in three steps. | L22: Heat plus sweat is prickly-heat territory — staying cool and rinsing settles it. (DYK #33) | M22: ⚠ Keyed to CURRENT band (inconsistent with UV/AQI rows) — engine must reconcile | N22: {=IF(SUMPRODUCT(--ISNUMBER(SEARCH({"cover up","seek shade","reapply","sun protection","protection on","protect "},I22&" "&J22&" "&K22)))>0,"⚠ banned night verb","OK")} | O22: {=MAX(IF(LEN(TRIM(D22:K22))=0,0,LEN(TRIM(D22:K22))-LEN(SUBSTITUTE(TRIM(D22:K22)," ",""))+1))}
A23: Temperature | B23: Temperature | C23: Extreme Heat | D23: A heatwave peaks today — plan water, shade and cool rinses before it does. | E23: Today peaks in a heatwave — get water, shade and cool rinses ready now. | H23: Still dangerously hot — stay shaded and keep drinking water. | I23: Peak heat easing — rehydrate well, rinse off sweat, keep moisturiser light. | J23: After a scorcher, rehydrate well — inside and out, kept light. | K23: Heatwave night — water first, a cool rinse, and the lightest finish. | L23: In a heatwave, rehydrating inside and out matters as much as anything topical. (DYK #15) | M23: ⚠ Keyed to CURRENT band (inconsistent with UV/AQI rows) — engine must reconcile | N23: {=IF(SUMPRODUCT(--ISNUMBER(SEARCH({"cover up","seek shade","reapply","sun protection","protection on","protect "},I23&" "&J23&" "&K23)))>0,"⚠ banned night verb","OK")} | O23: {=MAX(IF(LEN(TRIM(D23:K23))=0,0,LEN(TRIM(D23:K23))-LEN(SUBSTITUTE(TRIM(D23:K23)," ",""))+1))}
A24: Humidity | B24: Humidity | C24: Critical Low | D24: — (already bone-dry) | H24: Bone-dry evening air — skin may feel tight; a moisturiser helps. | I24: Bone-dry tonight — moisturise on slightly damp skin before bed. | J24: Desert-dry night — moisturise onto slightly damp skin and it holds. | K24: Bone-dry air works all night — give it a rich barrier to fight. | L24: Skin's natural moisturiser only forms well near 80–95% humidity — bone-dry air stalls it. (DYK #6) | M24: ⚠ Keyed to CURRENT band (inconsistent with UV/AQI rows) — engine must reconcile | N24: {=IF(SUMPRODUCT(--ISNUMBER(SEARCH({"cover up","seek shade","reapply","sun protection","protection on","protect "},I24&" "&J24&" "&K24)))>0,"⚠ banned night verb","OK")} | O24: {=MAX(IF(LEN(TRIM(D24:K24))=0,0,LEN(TRIM(D24:K24))-LEN(SUBSTITUTE(TRIM(D24:K24)," ",""))+1))}
A25: Humidity | B25: Humidity | C25: Very Low | D25: It dries out further today — carry a moisturiser to reapply. | E25: The air gets thirstier today — keep a moisturiser within reach. | H25: A dry evening — light moisturiser if skin starts to feel tight. | I25: Very dry evening — moisturise well before bed to hold water in. | J25: Very dry night air — a good layer before bed stops the tight-skin morning. | K25: Tight, flaky mornings start tonight — head them off with a good layer. | L25: Very dry air keeps pulling water out all night — a richer layer fights back. (DYK #6) | M25: ⚠ Keyed to CURRENT band (inconsistent with UV/AQI rows) — engine must reconcile | N25: {=IF(SUMPRODUCT(--ISNUMBER(SEARCH({"cover up","seek shade","reapply","sun protection","protection on","protect "},I25&" "&J25&" "&K25)))>0,"⚠ banned night verb","OK")} | O25: {=MAX(IF(LEN(TRIM(D25:K25))=0,0,LEN(TRIM(D25:K25))-LEN(SUBSTITUTE(TRIM(D25:K25)," ",""))+1))}
A26: Humidity | B26: Humidity | C26: Low | D26: Air dries out more today — moisturise after washing. | E26: Drier air moves in today — moisturise after every wash. | H26: Slightly dry evening air — nothing urgent. | I26: Drier evening — a moisturiser before bed keeps the barrier supported. | J26: Drier night — moisturiser before bed keeps the barrier topped up. | K26: A little extra moisturiser tonight saves dry patches tomorrow. | L26: Drier air slows the skin's moisture-making — topping up keeps the barrier even. (DYK #6) | M26: ⚠ Keyed to CURRENT band (inconsistent with UV/AQI rows) — engine must reconcile | N26: {=IF(SUMPRODUCT(--ISNUMBER(SEARCH({"cover up","seek shade","reapply","sun protection","protection on","protect "},I26&" "&J26&" "&K26)))>0,"⚠ banned night verb","OK")} | O26: {=MAX(IF(LEN(TRIM(D26:K26))=0,0,LEN(TRIM(D26:K26))-LEN(SUBSTITUTE(TRIM(D26:K26)," ",""))+1))}
A27: Humidity | B27: Humidity | C27: Optimal | D27: It turns humid later today — plan to keep skin and creases dry. | E27: Humidity climbs later — plan to keep skin and creases dry. | F27: Humidity surges from comfortable to soaking today — dry creases and a sweat rinse will matter. | G27: Humidity settles into the comfort zone today — skin can breathe easy. | H27: A comfortable evening — carry on as usual. | I27: An easy evening — keep up your usual routine. | J27: A kind night for skin — stick to your usual routine. | K27: Comfortable air, comfortable night — your usual routine is plenty. | L27: Comfortable humidity is where skin works best — nothing to correct. | M27: ⚠ Keyed to CURRENT band (inconsistent with UV/AQI rows) — engine must reconcile | N27: {=IF(SUMPRODUCT(--ISNUMBER(SEARCH({"cover up","seek shade","reapply","sun protection","protection on","protect "},I27&" "&J27&" "&K27)))>0,"⚠ banned night verb","OK")} | O27: {=MAX(IF(LEN(TRIM(D27:K27))=0,0,LEN(TRIM(D27:K27))-LEN(SUBSTITUTE(TRIM(D27:K27)," ",""))+1))}
A28: Humidity | B28: Humidity | C28: High | D28: It turns more humid today — plan a sweat rinse and keep skin creases dry. | E28: A muggier day ahead — a sweat rinse and dry creases will help. | F28: Humidity spikes to saturation today — cleanse often and keep creases dry. | H28: A sticky evening — light clothing helps sweat evaporate. | I28: Humid evening — a gentle cleanse clears sweat and oil before bed. | J28: Muggy night — a gentle cleanse clears the sweat film before bed. | K28: Sweat and oil built up today — clear them gently before sleep. | L28: Humid heat traps sweat in creases — prickly heat and irritation start there. (DYK #33) | M28: ⚠ Keyed to CURRENT band (inconsistent with UV/AQI rows) — engine must reconcile | N28: {=IF(SUMPRODUCT(--ISNUMBER(SEARCH({"cover up","seek shade","reapply","sun protection","protection on","protect "},I28&" "&J28&" "&K28)))>0,"⚠ banned night verb","OK")} | O28: {=MAX(IF(LEN(TRIM(D28:K28))=0,0,LEN(TRIM(D28:K28))-LEN(SUBSTITUTE(TRIM(D28:K28)," ",""))+1))}
A29: Humidity | B29: Humidity | C29: Very High | D29: Air saturates later today — plan to keep skin creases dry and cleanse off sweat. | E29: The air heads for saturation — keep creases dry and rinse off sweat. | H29: Humid evening — sweat sits on skin; take it easy out there. | I29: Still humid tonight — a gentle cleanse before bed; keep moisturiser light. | J29: Humidity hasn't let up — cleanse gently, moisturise sparingly. | K29: Still steamy — light cleanse, light moisturiser, nothing heavy. | L29: In sticky weather the scalp and creases stay damp for hours — a rinse keeps them fresh. (DYK #23) | M29: ⚠ Keyed to CURRENT band (inconsistent with UV/AQI rows) — engine must reconcile | N29: {=IF(SUMPRODUCT(--ISNUMBER(SEARCH({"cover up","seek shade","reapply","sun protection","protection on","protect "},I29&" "&J29&" "&K29)))>0,"⚠ banned night verb","OK")} | O29: {=MAX(IF(LEN(TRIM(D29:K29))=0,0,LEN(TRIM(D29:K29))-LEN(SUBSTITUTE(TRIM(D29:K29)," ",""))+1))}
A30: Humidity | B30: Humidity | C30: Extreme | D30: — (already saturated) | H30: Saturated evening air — keep time out light and easy. | I30: Saturated air tonight — cleanse off sweat, keep skin creases dry and moisturiser light. | J30: Saturated night — cleanse off sweat, dry the creases, keep it light. | K30: Air's fully saturated — cleanse, dry the creases, sleep light. | L30: Saturated air stops sweat evaporating — gentle, frequent cleansing beats heavy creams. (DYK #33) | M30: ⚠ Keyed to CURRENT band (inconsistent with UV/AQI rows) — engine must reconcile | N30: {=IF(SUMPRODUCT(--ISNUMBER(SEARCH({"cover up","seek shade","reapply","sun protection","protection on","protect "},I30&" "&J30&" "&K30)))>0,"⚠ banned night verb","OK")} | O30: {=MAX(IF(LEN(TRIM(D30:K30))=0,0,LEN(TRIM(D30:K30))-LEN(SUBSTITUTE(TRIM(D30:K30)," ",""))+1))}
A32: Compound-scenario overlays (21 named scenarios)
A33: Type | B33: Factor / Scenario | C33: Band / Key | D33: Morning add-on (use only if the band worsens today) | E33: Morning add-on — variant B (rotate with D) | F33: Morning add-on — big-jump variant (band worsens 2+ steps) | G33: Morning good-news note (use only if the band improves today) | H33: Early-evening action (~4–8pm) | I33: Night action (after ~8pm) | J33: Night action — variant B (rotate with I) | K33: Night action — variant C (rotate with I) | L33: Why it matters (micro-insight; DYK ref where noted) | M33: Keying & context flags | N33: QA: banned night verbs | O33: QA: max words (D:K)
A34: Compound | B34: Pre-Monsoon Sun & Heat | C34: C01 | D34: Strong sun and heat build by midday — put on sun protection and plan a sweat rinse before you go. | E34: Sun and heat gang up by midday — protection on and a rinse planned. | H34: Sun and heat are easing — keep protection on till sundown if you're still out. | I34: Sun and heat easing — rinse off sweat and sunscreen, then moisturise lightly. | J34: Sun and sweat both come off tonight — rinse well, then a light moisturiser. | K34: Today asked a lot of skin — sun and sweat off, a light drink on, sleep. | L34: Strong sun plus heat means more oil and more UV load at once — protect and rinse. (DYK #5, #15) | M34: Keyed to FORECAST band ("build today" phrasing) | N34: {=IF(SUMPRODUCT(--ISNUMBER(SEARCH({"cover up","seek shade","reapply","sun protection","protection on","protect "},I34&" "&J34&" "&K34)))>0,"⚠ banned night verb","OK")} | O34: {=MAX(IF(LEN(TRIM(D34:K34))=0,0,LEN(TRIM(D34:K34))-LEN(SUBSTITUTE(TRIM(D34:K34)," ",""))+1))}
A35: Compound | B35: Heatwave Crisis | C35: C02 | D35: A heatwave peaks today — water, shade and cool rinses before it does. | E35: Today is a heatwave day — stock water and plan cool rinses before the peak. | H35: Heat is still dangerous this evening — shade, water and minimal exertion. | I35: Peak heat easing — rehydrate well, rinse off sweat, keep moisturiser light overnight. | J35: After a scorching day, water first — then a rinse and the lightest layer. | K35: The heat did its worst; tonight is repair — water, rinse, light finish. | L35: Heatwave days need inside-out rehydration — topical care alone won't hold. (DYK #15) | M35: Keyed to FORECAST band | N35: {=IF(SUMPRODUCT(--ISNUMBER(SEARCH({"cover up","seek shade","reapply","sun protection","protection on","protect "},I35&" "&J35&" "&K35)))>0,"⚠ banned night verb","OK")} | O35: {=MAX(IF(LEN(TRIM(D35:K35))=0,0,LEN(TRIM(D35:K35))-LEN(SUBSTITUTE(TRIM(D35:K35)," ",""))+1))}
A36: Compound | B36: Dry-Heat Desert Day | C36: C03 | D36: Dry heat and strong sun build today — moisturise and put on sun protection before heading out. | E36: Desert-dry heat and strong sun today — moisturise, then protect before out. | H36: The heat fades but the dryness stays — moisturiser if skin feels tight. | I36: Dry, hot day done — moisturise on damp skin and cleanse off sunscreen. | J36: Wash off the sunscreen, then moisturise damp skin to win back lost water. | K36: Desert day done — damp-skin moisturising beats dry-skin moisturising tonight. | L36: Dry heat plus sun stalls moisture-making while UV bites — moisturise, then protect. (DYK #6) | M36: Keyed to FORECAST band | N36: {=IF(SUMPRODUCT(--ISNUMBER(SEARCH({"cover up","seek shade","reapply","sun protection","protection on","protect "},I36&" "&J36&" "&K36)))>0,"⚠ banned night verb","OK")} | O36: {=MAX(IF(LEN(TRIM(D36:K36))=0,0,LEN(TRIM(D36:K36))-LEN(SUBSTITUTE(TRIM(D36:K36)," ",""))+1))}
A37: Compound | B37: Beach Day UV | C37: C04 | D37: Glare-boosted UV peaks midday — sun protection, shade and cover-ups before you're out. | E37: Water and sand bounce extra UV today — protect and plan shade before you go. | H37: Late-beach glare still burns — keep protection on till the sun is down. | I37: Beach day over — cleanse off salt, sand and sunscreen; rehydrate skin. | J37: Salt, sand and sunscreen all come off tonight — then let skin drink. | K37: Beach glow now, beach residue later — wash it all off before bed. | L37: Water and sand bounce 25–50% extra UV up at you — glare burns from below too. (DYK #2) | M37: Keyed to FORECAST band · CONTEXT: assumes beach/waterside outing | N37: {=IF(SUMPRODUCT(--ISNUMBER(SEARCH({"cover up","seek shade","reapply","sun protection","protection on","protect "},I37&" "&J37&" "&K37)))>0,"⚠ banned night verb","OK")} | O37: {=MAX(IF(LEN(TRIM(D37:K37))=0,0,LEN(TRIM(D37:K37))-LEN(SUBSTITUTE(TRIM(D37:K37)," ",""))+1))}
A38: Compound | B38: Hot-Humid Coastal Summer | C38: C05 | D38: Heat and humidity build today — plan a sweat rinse and keep skin creases dry. | E38: A hot, sticky one today — plan a rinse and keep creases dry. | H38: A sticky evening — light clothes and an easy pace. | I38: Sticky day easing — a gentle cleanse clears sweat and oil before bed. | J38: A day of sweat needs a gentle wash tonight — keep the finish light. | K38: Sticky day, simple night: gentle wash, light layer, dry creases. | L38: Humid heat traps sweat in creases — the classic prickly-heat setup. (DYK #33) | M38: Keyed to FORECAST band | N38: {=IF(SUMPRODUCT(--ISNUMBER(SEARCH({"cover up","seek shade","reapply","sun protection","protection on","protect "},I38&" "&J38&" "&K38)))>0,"⚠ banned night verb","OK")} | O38: {=MAX(IF(LEN(TRIM(D38:K38))=0,0,LEN(TRIM(D38:K38))-LEN(SUBSTITUTE(TRIM(D38:K38)," ",""))+1))}
A39: Compound | B39: Monsoon Acne Trifecta | C39: C06 | D39: Humid, polluted heat builds today — plan to keep skin dry and cleanse off sweat and grime. | E39: Heat, humidity and grime all day — tonight's cleanse will matter. | H39: Humid, grimy evening air — keep outdoor time easy. | I39: Cleanse off the day's sweat and grime tonight; keep moisturiser light and skin dry. | J39: Sweat and grime clog overnight if they stay — cleanse gently, finish light and dry. | K39: Breakout weather peaks overnight if grime stays — cleanse gently before bed. | L39: Humidity plus pollution: grime sticks to damp skin — the nightly cleanse earns its keep. (DYK #29) | M39: Keyed to FORECAST band | N39: {=IF(SUMPRODUCT(--ISNUMBER(SEARCH({"cover up","seek shade","reapply","sun protection","protection on","protect "},I39&" "&J39&" "&K39)))>0,"⚠ banned night verb","OK")} | O39: {=MAX(IF(LEN(TRIM(D39:K39))=0,0,LEN(TRIM(D39:K39))-LEN(SUBSTITUTE(TRIM(D39:K39)," ",""))+1))}
A40: Compound | B40: Coastal Monsoon Standard | C40: C07 | D40: Humid air holds all day — plan a sweat rinse to keep skin fresh. | E40: Humid air parks over the day — a sweat rinse keeps skin fresh. | H40: A humid evening — take it easy; cleanse when you're back in. | I40: Humid day done — a gentle cleanse before bed clears sweat and oil. | J40: Rinse the muggy day away — light cleanse, light layer, done. | K40: Muggy day over — one gentle wash keeps pores clear tonight. | L40: Damp skin all day invites irritation — a sweat rinse keeps it fresh. (DYK #23) | M40: Keyed to FORECAST band | N40: {=IF(SUMPRODUCT(--ISNUMBER(SEARCH({"cover up","seek shade","reapply","sun protection","protection on","protect "},I40&" "&J40&" "&K40)))>0,"⚠ banned night verb","OK")} | O40: {=MAX(IF(LEN(TRIM(D40:K40))=0,0,LEN(TRIM(D40:K40))-LEN(SUBSTITUTE(TRIM(D40:K40)," ",""))+1))}
A41: Compound | B41: Tropical NE Saturated | C41: C08 | D41: Saturated air all day — plan to keep skin creases dry and cleanse often. | E41: Saturation all day — dry creases and frequent cleansing win today. | H41: Air stays saturated this evening — keep exertion light. | I41: Still saturated tonight — cleanse off sweat and keep skin creases dry before bed. | J41: Before bed: sweat off, creases dry, moisturiser minimal. | K41: Saturation day: the win is dry creases and a feather-light finish. | L41: Saturated air stops sweat drying — frequent gentle cleansing wins. (DYK #33) | M41: Keyed to FORECAST band | N41: {=IF(SUMPRODUCT(--ISNUMBER(SEARCH({"cover up","seek shade","reapply","sun protection","protection on","protect "},I41&" "&J41&" "&K41)))>0,"⚠ banned night verb","OK")} | O41: {=MAX(IF(LEN(TRIM(D41:K41))=0,0,LEN(TRIM(D41:K41))-LEN(SUBSTITUTE(TRIM(D41:K41)," ",""))+1))}
A42: Compound | B42: Pre-Monsoon Humidity Surge | C42: C09 | D42: Humid heat and strong sun build today — sweat rinse, light moisturiser and sun protection planned. | E42: Humid heat plus strong sun today — rinse, light moisturiser, protection. | H42: Humid heat lingers — water and shade if you're still out. | I42: Humid heat easing — cleanse off sweat and sunscreen, keep moisturiser light. | J42: Sweat and sunscreen come off together tonight — keep what follows light. | K42: Three stressors today — one calm night: rinse, dry, light layer. | L42: Heat, humidity and sun stack every stressor — rinse, light moisturiser, protection. (DYK #15) | M42: Keyed to FORECAST band | N42: {=IF(SUMPRODUCT(--ISNUMBER(SEARCH({"cover up","seek shade","reapply","sun protection","protection on","protect "},I42&" "&J42&" "&K42)))>0,"⚠ banned night verb","OK")} | O42: {=MAX(IF(LEN(TRIM(D42:K42))=0,0,LEN(TRIM(D42:K42))-LEN(SUBSTITUTE(TRIM(D42:K42)," ",""))+1))}
A43: Compound | B43: North-Plains Winter Smog | C43: C10 | D43: Cold, dry, smoggy air today — moisturise before you go and plan to cleanse off grime. | E43: Cold smog sits over the day — moisturise first, cleanse off grime later. | H43: Smog thickens after sunset — better indoors this evening. | I43: Cleanse off the day's pollution tonight and moisturise the dry barrier. | J43: Smog washes off; dryness gets a moisturiser — tonight covers both. | K43: Winter smog day — wash off the city, then feed the dry barrier. | L43: Cold, dry, smoggy air hits the barrier from three sides — moisturise first, cleanse later. (DYK #7, #8) | M43: Keyed to FORECAST band | N43: {=IF(SUMPRODUCT(--ISNUMBER(SEARCH({"cover up","seek shade","reapply","sun protection","protection on","protect "},I43&" "&J43&" "&K43)))>0,"⚠ banned night verb","OK")} | O43: {=MAX(IF(LEN(TRIM(D43:K43))=0,0,LEN(TRIM(D43:K43))-LEN(SUBSTITUTE(TRIM(D43:K43)," ",""))+1))}
A44: Compound | B44: Post-Diwali AQI Spike | C44: C11 | D44: Severe pollution spikes today — limit time out and plan to cleanse off grime. | E44: A severe pollution spike today — minimise time out and cleanse well after. | H44: Pollution peaks tonight — stay in where you can. | I44: Wash off the day's heavy grime tonight; an antioxidant product (such as Vitamin C) supports repair. | J44: Tonight's wash matters most this week — clear the grime, then support repair. | K44: The spike ends at your sink — a thorough wash, then overnight support. | L44: A severe pollution spike ages skin fast — limit exposure, cleanse thoroughly. (DYK #14) | M44: Keyed to FORECAST band | N44: {=IF(SUMPRODUCT(--ISNUMBER(SEARCH({"cover up","seek shade","reapply","sun protection","protection on","protect "},I44&" "&J44&" "&K44)))>0,"⚠ banned night verb","OK")} | O44: {=MAX(IF(LEN(TRIM(D44:K44))=0,0,LEN(TRIM(D44:K44))-LEN(SUBSTITUTE(TRIM(D44:K44)," ",""))+1))}
A45: Compound | B45: Stubble-Burning Season | C45: C12 | D45: Smoke-heavy air builds today — limit long spells out and cleanse off after. | E45: Smoke in the air all day — short outdoor spells, thorough cleanse after. | H45: Smoke hangs in the evening air — keep outdoor spells short. | I45: Cleanse off the smoke and grime tonight; moisturise to support the barrier. | J45: Smoke settles on skin all day — wash it off well and moisturise after. | K45: Smoke lingers on skin longer than in air — wash it off tonight. | L45: Smoke particles settle and penetrate — short spells out, proper cleanse after. (DYK #29) | M45: Keyed to FORECAST band | N45: {=IF(SUMPRODUCT(--ISNUMBER(SEARCH({"cover up","seek shade","reapply","sun protection","protection on","protect "},I45&" "&J45&" "&K45)))>0,"⚠ banned night verb","OK")} | O45: {=MAX(IF(LEN(TRIM(D45:K45))=0,0,LEN(TRIM(D45:K45))-LEN(SUBSTITUTE(TRIM(D45:K45)," ",""))+1))}
... A54: Compound | B54: Indoor AC Office Hours | C54: C21 | D54: A full day of dry AC air ahead — keep a moisturiser at your desk to reapply. | E54: A long AC day ahead — desk moisturiser on standby. | H54: The AC day is done — skin can start recovering this evening. | I54: Dry AC day done — a richer moisturiser before bed restores lost water. | J54: The AC kept taking all day — give it back tonight with a good layer. | K54: Office-dry skin recovers overnight — help it with a proper layer. | L54: A full AC day stalls the skin's moisture-making — reapply to keep pace. (DYK #6) | M54: CONTEXT: assumes indoor AC exposure — not weather-forecast keyed | N54: {=IF(SUMPRODUCT(--ISNUMBER(SEARCH({"cover up","seek shade","reapply","sun protection","protection on","protect "},I54&" "&J54&" "&K54)))>0,"⚠ banned night verb","OK")} | O54: {=MAX(IF(LEN(TRIM(D54:K54))=0,0,LEN(TRIM(D54:K54))-LEN(SUBSTITUTE(TRIM(D54:K54)," ",""))+1))}

Sheet Gap Analysis
A1: Gap Analysis — Evidence Base coverage vs Scenario Library v3.5
A2: Every concern in the Evidence Base Coverage_Matrix, checked against what the Scenario Library now builds. STATUS: ✓ in v3.5 = scenario cells exist · NEW in v3.5 = added this release · Modifier/Education = supported as a nudge, not weather cells · Roadmap = evidence too thin or non-environmental.
A4: Concern (Evidence Base) | B4: Total cited rows | C4: India-relevant | D4: Top factor sheets | E4: In Scenario Library? | F4: How it's covered | G4: Best confidence achievable | H4: Notes / what's still missing
A5: barrier | B5: 501 | C5: 312 | D5: Humidity(151), Pollution(101), Lifestyle(97) | E5: ✓ in v3.5 | F5: Underlies Dryness + Eczema cells across all 4 factors | G5: HIGH | H5: Fully covered as the core of the library.
A6: sensitivity | B6: 471 | C6: 338 | D6: Lifestyle(124), UV(111), Humidity(91) | E6: ✓ in v3.5 | F6: Sensitive skin type runs through every cell + Stress/Sleep modifiers | G6: HIGH | H6: Covered as a skin-type lens on all concerns.
A7: pigmentation | B7: 425 | C7: 326 | D7: UV(232), Lifestyle(62), Nutrition(59) | E7: ✓ in v3.5 | F7: Uneven Skin Tone / Tan + Melasma cells | G7: HIGH | H7: Fully covered.
A8: uv_sun_protection | B8: 386 | C8: 275 | D8: UV(294), Pollution(33), Lifestyle(25) | E8: ✓ in v3.5 | F8: Whole UV factor + Premature Aging cells | G8: HIGH | H8: Fully covered.
A9: nutritional | B9: 327 | C9: 237 | D9: UV(119), Nutrition(115), Lifestyle(31) | E9: ✓ in v3.5 | F9: Nutrition Modifiers sheet (7 nudges) | G9: MODERATE | H9: Covered as personalisation nudges, not weather cells (correct — diet isn't an environmental trigger).
A10: acne | B10: 288 | C10: 224 | D10: Lifestyle(91), UV(80), Temperature(39) | E10: ✓ in v3.5 | F10: Acne cells across all 4 factors | G10: HIGH | H10: Fully covered.
A11: aging | B11: 242 | C11: 120 | D11: UV(92), Nutrition(76), Pollution(26) | E11: ✓ in v3.5 | F11: Premature Aging / Sun Damage cells (UV, AQI, Temp) | G11: HIGH | H11: Added in v3.4; retained.
A12: eczema | B12: 226 | C12: 150 | D12: Humidity(63), Lifestyle(56), Nutrition(30) | E12: ✓ in v3.5 | F12: Eczema cells across all 4 factors | G12: HIGH | H12: Fully covered.
A13: melasma | B13: 163 | C13: 102 | D13: UV(96), Nutrition(29), Lifestyle(21) | E13: ✓ in v3.5 | F13: Melasma cells across all 4 factors | G13: MODERATE | H13: Fully covered.
A14: pollution_specific | B14: 153 | C14: 106 | D14: Pollution(100), UV(27), Lifestyle(10) | E14: ✓ in v3.5 | F14: Whole AQI factor | G14: HIGH | H14: Fully covered.
A15: hair_loss | B15: 109 | C15: 90 | D15: Lifestyle(63), UV(11), Humidity(11) | E15: NEW in v3.5 | F15: Hair & Scalp (Shedding): 90 single-factor + 85 compound cells | G15: MODERATE | H15: Environmental triggers (scalp UV, grime, sweat) covered across single-factor AND named scenarios. Hormonal/genetic hair loss stays a dermatologist topic.
A16: fungal_infections | B16: 80 | C16: 76 | D16: Humidity(51), Temperature(14), Pollution(7) | E16: ✓ in v3.5 | F16: Fungal Infection (Sweat & Folds) cells (Humidity, Temp) | G16: HIGH | H16: Added in v3.4; retained.
... A22: miliaria_heat | B22: 12 | C22: 12 | D22: Humidity(8), Temperature(4) | E22: ✓ in v3.5 | F22: Heat Rash (Prickly Heat) cells (Temp, Humidity) | G22: MODERATE | H22: Added in v3.4; retained.

Sheet 4. Temperature Cells
A1: Scenario ID | B1: Band | C1: Range | D1: Skin Type | E1: Concern | F1: Risk | G1: Risk Level | H1: Confidence | I1: Evidence Summary | J1: PMID Anchors | K1: L0 Compact (≤20w) | L1: L1 Personalised (≤40w) | M1: L2 Explainer (60–90w) | N1: Action Cluster | O1: Applicable Zones | P1: Indian Cities/Season
A2: T-EXTR-NOR-DRYN-001 | B2: Extreme Cold | C2: <5°C | D2: Normal | E2: Dryness | F2: 5 | G2: Critical | H2: HIGH | I2: 39 cites · 26 PMID · 8 book · 7 India-relevant | J2: PMID:37953512 | PMID:35053992 | PMID:31029804 | K2: Sub-zero air holds almost no moisture. Lock in moisture to protect your skin now. | L2: Sub-zero air holds almost no moisture. For your skin with dryness, this is as tough as it gets for your skin. Layer a water-binding humectant (like glycerin) on damp skin, then seal with an emollient. Apply within three minutes of any wash. | M2: Sub-zero air holds almost no moisture. Air this cold holds almost no water — your skin is losing moisture every second it's exposed. In Indian context: the Himalayan belt (Dec–Jan); -ve impact in mountain belt. Build moisture from the inside out: water-binding humectants (like glycerin) on damp skin, sealed with an emollient layer that locks moisture in. Apply within three minutes of any wash before water evaporates. A bedroom humidifier helps overnight. | N2: Hydrate | O2: CH | P2: Kashmir, Himachal (Dec–Jan); -ve impact in mountain belt
A3: T-EXTR-NOR-ECZE-002 | B3: Extreme Cold | C3: <5°C | D3: Normal | E3: Eczema | F3: 5 | G3: Critical | H3: MODERATE | I3: 7 cites · 2 PMID · 1 book · 0 India-relevant | J3: PMID:37336870 | PMID:21426384 | 10.1016/j.anai.2023.08.007 | K3: Sub-zero air holds almost no moisture. Soothe and protect eczema-prone skin now. | L3: Sub-zero air holds almost no moisture. For your skin with eczema, this is as tough as it gets for your skin. Layer a water-binding humectant (like glycerin) on damp skin, then seal with an emollient. Apply within three minutes of any wash. | M3: Sub-zero air holds almost no moisture. Cold this severe collapses your skin's natural moisture-binders. Flares are nearly automatic without intervention. In Indian context: the Himalayan belt (Dec–Jan); -ve impact in mountain belt. Build moisture from the inside out: water-binding humectants (like glycerin) on damp skin, sealed with an emollient layer that locks moisture in. Apply within three minutes of any wash before water evaporates. A bedroom humidifier helps overnight. | N3: Hydrate | O3: CH | P3: Kashmir, Himachal (Dec–Jan); -ve impact in mountain belt
A4: T-EXTR-NOR-OILY-003 | B4: Extreme Cold | C4: <5°C | D4: Normal | E4: Oily Skin | F4: 0 | G4: Negligible | H4: MODERATE | I4: 12 cites · 8 PMID · 0 book · 0 India-relevant | J4: PMID:11096379 | PMID:27333493 | PMID:19467097 | K4: Sub-zero air holds almost no moisture. Maintain your usual routine for oily skin. | L4: Sub-zero air holds almost no moisture. Your skin faces no extra pressure from this factor today. Hydrate hard. | M4: Sub-zero air holds almost no moisture. Oil flow slows in sub-zero air. You may feel matte, but the barrier underneath needs more care, not less. In Indian context: the Himalayan belt (Dec–Jan); -ve impact in mountain belt. Build moisture from the inside out: water-binding humectants (like glycerin) on damp skin, sealed with an emollient layer that locks moisture in. Apply within three minutes of any wash before water evaporates. A bedroom humidifier helps overnight. | N4: Hydrate | O4: CH | P4: Kashmir, Himachal (Dec–Jan); -ve impact in mountain belt
A5: T-EXTR-NOR-ACNE-004 | B5: Extreme Cold | C5: <5°C | D5: Normal | E5: Acne | F5: 1 | G5: Low | H5: HIGH | I5: 14 cites · 14 PMID · 0 book · 9 India-relevant | J5: PMID:37336870 | PMID:30238598 | PMID:12227481 | K5: Sub-zero air holds almost no moisture. Take good care of your acne-prone pores. | L5: Sub-zero air holds almost no moisture. Your skin with acne feels this as a manageable environmental hit. Hydrate hard. | M5: Sub-zero air holds almost no moisture. Bacteria slow down, but heated indoor air strips skin — barrier cracks can still drive breakouts. In Indian context: the Himalayan belt (Dec–Jan); -ve impact in mountain belt. Build moisture from the inside out: water-binding humectants (like glycerin) on damp skin, sealed with an emollient layer that locks moisture in. Apply within three minutes of any wash before water evaporates. A bedroom humidifier helps overnight. | N5: Hydrate | O5: CH | P5: Kashmir, Himachal (Dec–Jan); -ve impact in mountain belt
A6: T-EXTR-NOR-UNEV-005 | B6: Extreme Cold | C6: <5°C | D6: Normal | E6: Uneven Skin Tone / Tan | F6: 1 | G6: Low | H6: HIGH | I6: 39 cites · 27 PMID · 5 book · 15 India-relevant | J6: PMID:14764172 | PMID:22374181 | PMID:37855862 | K6: Sub-zero air holds almost no moisture. Daily sun protection keeps tone even. | L6: Sub-zero air holds almost no moisture. Your skin with uneven skin tone / tan feels this as a manageable environmental hit. Routine day. | M6: Sub-zero air holds almost no moisture. Cold itself doesn't darken skin, but snow and ice can reflect up to 80% of UV onto your face. In Indian context: the Himalayan belt (Dec–Jan); -ve impact in mountain belt. Environmental pressure is low today — a good day to be consistent with your basics. Sunscreen still matters regardless of weather; visible light triggers pigment year-round. | N6: Maintain | O6: CH | P6: Kashmir, Himachal (Dec–Jan); -ve impact in mountain belt
A7: T-EXTR-NOR-MELA-006 | B7: Extreme Cold | C7: <5°C | D7: Normal | E7: Melasma | F7: 1 | G7: Low | H7: MODERATE | I7: 3 cites · 0 PMID · 3 book · 1 India-relevant | J7: Melasma and Vitiligo in Brown , p.p13 | Melasma and Vitiligo in Brown , p.p349 | K7: Sub-zero air holds almost no moisture. Daily sun protection keeps melasma calm. | L7: Sub-zero air holds almost no moisture. Your skin with melasma feels this as a manageable environmental hit. Routine day. | M7: Sub-zero air holds almost no moisture. Cold air narrows surface blood vessels — skin looks evener, but heat-cold cycles can trigger pigment surges. In Indian context: the Himalayan belt (Dec–Jan); -ve impact in mountain belt. Environmental pressure is low today — a good day to be consistent with your basics. Sunscreen still matters regardless of weather; visible light triggers pigment year-round. | N7: Maintain | O7: CH | P7: Kashmir, Himachal (Dec–Jan); -ve impact in mountain belt
A8: T-EXTR-DRY-DRYN-007 | B8: Extreme Cold | C8: <5°C | D8: Dry | E8: Dryness | F8: 5 | G8: Critical | H8: HIGH | I8: 44 cites · 26 PMID · 12 book · 11 India-relevant | J8: PMID:37953512 | PMID:35053992 | PMID:31029804 | K8: Sub-zero air holds almost no moisture. Lock in moisture to protect your skin now. | L8: Sub-zero air holds almost no moisture. For your dry skin with dryness, this is as tough as it gets for your skin. Layer a water-binding humectant (like glycerin) on damp skin, then seal with an emollient. Apply within three minutes of any wash. | M8: Sub-zero air holds almost no moisture. Air this cold holds almost no water — your skin is losing moisture every second it's exposed. In Indian context: the Himalayan belt (Dec–Jan); -ve impact in mountain belt. Build moisture from the inside out: water-binding humectants (like glycerin) on damp skin, sealed with an emollient layer that locks moisture in. Apply within three minutes of any wash before water evaporates. A bedroom humidifier helps overnight. | N8: Hydrate | O8: CH | P8: Kashmir, Himachal (Dec–Jan); -ve impact in mountain belt
A9: T-EXTR-DRY-ECZE-008 | B9: Extreme Cold | C9: <5°C | D9: Dry | E9: Eczema | F9: 5 | G9: Critical | H9: MODERATE | I9: 12 cites · 2 PMID · 6 book · 5 India-relevant | J9: PMID:37336870 | PMID:21426384 | 10.1016/j.anai.2023.08.007 | K9: Sub-zero air holds almost no moisture. Soothe and protect eczema-prone skin now. | L9: Sub-zero air holds almost no moisture. For your dry skin with eczema, this is as tough as it gets for your skin. Layer a water-binding humectant (like glycerin) on damp skin, then seal with an emollient. Apply within three minutes of any wash. | M9: Sub-zero air holds almost no moisture. Cold this severe collapses your skin's natural moisture-binders. Flares are nearly automatic without intervention. In Indian context: the Himalayan belt (Dec–Jan); -ve impact in mountain belt. Build moisture from the inside out: water-binding humectants (like glycerin) on damp skin, sealed with an emollient layer that locks moisture in. Apply within three minutes of any wash before water evaporates. A bedroom humidifier helps overnight. | N9: Hydrate | O9: CH | P9: Kashmir, Himachal (Dec–Jan); -ve impact in mountain belt
A10: T-EXTR-DRY-OILY-009 | B10: Extreme Cold | C10: <5°C | D10: Dry | E10: Oily Skin | F10: 1 | G10: Low | H10: MODERATE | I10: 13 cites · 8 PMID · 1 book · 0 India-relevant | J10: PMID:11096379 | PMID:27333493 | PMID:19467097 | K10: Sub-zero air holds almost no moisture. Take good care of your oily skin. | L10: Sub-zero air holds almost no moisture. Your dry skin with oily skin feels this as a manageable environmental hit. Hydrate hard. | M10: Sub-zero air holds almost no moisture. Oil flow slows in sub-zero air. You may feel matte, but the barrier underneath needs more care, not less. In Indian context: the Himalayan belt (Dec–Jan); -ve impact in mountain belt. Build moisture from the inside out: water-binding humectants (like glycerin) on damp skin, sealed with an emollient layer that locks moisture in. Apply within three minutes of any wash before water evaporates. A bedroom humidifier helps overnight. | N10: Hydrate | O10: CH | P10: Kashmir, Himachal (Dec–Jan); -ve impact in mountain belt
A11: T-EXTR-DRY-ACNE-010 | B11: Extreme Cold | C11: <5°C | D11: Dry | E11: Acne | F11: 2 | G11: Moderate | H11: HIGH | I11: 14 cites · 14 PMID · 0 book · 9 India-relevant | J11: PMID:37336870 | PMID:30238598 | PMID:12227481 | K11: Sub-zero air holds almost no moisture. Keep pores clean to prevent breakouts. | L11: Sub-zero air holds almost no moisture. Your dry skin with acne feels this as a moderate environmental hit. Hydrate hard. | M11: Sub-zero air holds almost no moisture. Bacteria slow down, but heated indoor air strips skin — barrier cracks can still drive breakouts. In Indian context: the Himalayan belt (Dec–Jan); -ve impact in mountain belt. Build moisture from the inside out: water-binding humectants (like glycerin) on damp skin, sealed with an emollient layer that locks moisture in. Apply within three minutes of any wash before water evaporates. A bedroom humidifier helps overnight. | N11: Hydrate | O11: CH | P11: Kashmir, Himachal (Dec–Jan); -ve impact in mountain belt
A12: T-EXTR-DRY-UNEV-011 | B12: Extreme Cold | C12: <5°C | D12: Dry | E12: Uneven Skin Tone / Tan | F12: 2 | G12: Moderate | H12: HIGH | I12: 42 cites · 27 PMID · 7 book · 18 India-relevant | J12: PMID:14764172 | PMID:22374181 | PMID:37855862 | K12: Sub-zero air holds almost no moisture. Protect from sun to keep tone even. | L12: Sub-zero air holds almost no moisture. Your dry skin with uneven skin tone / tan feels this as a moderate environmental hit. Routine day. | M12: Sub-zero air holds almost no moisture. Cold itself doesn't darken skin, but snow and ice can reflect up to 80% of UV onto your face. In Indian context: the Himalayan belt (Dec–Jan); -ve impact in mountain belt. Environmental pressure is low today — a good day to be consistent with your basics. Sunscreen still matters regardless of weather; visible light triggers pigment year-round. | N12: Maintain | O12: CH | P12: Kashmir, Himachal (Dec–Jan); -ve impact in mountain belt
A13: T-EXTR-DRY-MELA-012 | B13: Extreme Cold | C13: <5°C | D13: Dry | E13: Melasma | F13: 2 | G13: Moderate | H13: MODERATE | I13: 3 cites · 0 PMID · 3 book · 1 India-relevant | J13: Melasma and Vitiligo in Brown , p.p13 | Melasma and Vitiligo in Brown , p.p349 | K13: Sub-zero air holds almost no moisture. Protect melasma patches from sun today. | L13: Sub-zero air holds almost no moisture. Your dry skin with melasma feels this as a moderate environmental hit. Routine day. | M13: Sub-zero air holds almost no moisture. Cold air narrows surface blood vessels — skin looks evener, but heat-cold cycles can trigger pigment surges. In Indian context: the Himalayan belt (Dec–Jan); -ve impact in mountain belt. Environmental pressure is low today — a good day to be consistent with your basics. Sunscreen still matters regardless of weather; visible light triggers pigment year-round. | N13: Maintain | O13: CH | P13: Kashmir, Himachal (Dec–Jan); -ve impact in mountain belt
... A221: T-HOT-SEN-AGE | B221: Hot | C221: 35–42°C | D221: Sensitive | E221: Premature Aging / Sun Damage | F221: 2 | G221: Moderate | H221: HIGH | I221: 10 cites · 6 PMID · 4 book · 6 India-relevant | J221: 10.1016/j.jphotobiol.2015.12.014 | 10.1111/srt.12951 | 10.1111/srt.70361 | K221: Heat is ramping up your oil and sweat. Protect skin from sun to slow aging. | L221: Hot direct sun — heat speeds collagen breakdown and visible aging. For sensitive skin with sun-related aging, an antioxidant product (such as Vitamin C) and daily sun protection help most. Fragrance-free mineral options suit you. | M221: Hot direct sun — heat speeds collagen breakdown and visible aging. Infrared heat from strong sun penetrates deep and breaks down collagen much like UV, so skin in hot sun ages faster. In Indian context: Plains (Apr–Jun); the north Indian plains peaks. If your day involves direct sun, an antioxidant product (such as Vitamin C) is what helps most, alongside daily sun protection. Shade and cooling down protect skin on the hottest days. | N221: Shield | O221: HD, HH, CN, TP | P221: Plains (Apr–Jun); Delhi, Jaipur, Nagpur peaks
A222: T-WARM-NOR-FUNG | B222: Warm | C222: 28–34°C | D222: Normal | E222: Fungal Infection (Sweat & Folds) | F222: 2 | G222: Moderate | H222: INFERRED | I222: 9 cites · 0 PMID · 8 book · 7 India-relevant | K222: Warm air starts to bump up oil production. Keep skin folds dry to avoid fungus. | L222: Warm, sweaty folds create the damp setting fungus prefers. For normal skin with fungal flare-ups, breathable cotton, staying dry and a gentle clarifying wash help. | M222: Warm, sweaty folds create the damp setting fungus prefers. Heat plus sweat trapped in folds creates the warm, damp setting fungus prefers, raising the risk of ringworm and yeast flare-ups. In Indian context: Most of India (Mar–Apr, Sep–Oct). If your day involves heat and sweat, breathable cotton, staying dry and a gentle clarifying wash help. Changing out of damp clothes quickly makes a real difference. | N222: Balance | O222: HD, HH, CN, TP, CH, TN | P222: Most of India (Mar–Apr, Sep–Oct)
A223: T-WARM-DRY-FUNG | B223: Warm | C223: 28–34°C | D223: Dry | E223: Fungal Infection (Sweat & Folds) | F223: 2 | G223: Moderate | H223: INFERRED | I223: 9 cites · 0 PMID · 8 book · 7 India-relevant | K223: Warm air starts to bump up oil production. Keep skin folds dry to avoid fungus. | L223: Warm, sweaty folds create the damp setting fungus prefers. For dry skin with fungal flare-ups, breathable cotton, staying dry and a gentle clarifying wash help. Damp folds flare even on dry skin. | M223: Warm, sweaty folds create the damp setting fungus prefers. Heat plus sweat trapped in folds creates the warm, damp setting fungus prefers, raising the risk of ringworm and yeast flare-ups. In Indian context: Most of India (Mar–Apr, Sep–Oct). If your day involves heat and sweat, breathable cotton, staying dry and a gentle clarifying wash help. Changing out of damp clothes quickly makes a real difference. | N223: Balance | O223: HD, HH, CN, TP, CH, TN | P223: Most of India (Mar–Apr, Sep–Oct)
A224: T-WARM-OIL-FUNG | B224: Warm | C224: 28–34°C | D224: Oily | E224: Fungal Infection (Sweat & Folds) | F224: 2 | G224: Moderate | H224: INFERRED | I224: 9 cites · 0 PMID · 8 book · 7 India-relevant | K224: Warm air starts to bump up oil production. Keep skin folds dry to avoid fungus. | L224: Warm, sweaty folds create the damp setting fungus prefers. For oily skin with fungal flare-ups, breathable cotton, staying dry and a gentle clarifying wash help. Oily, sweat-prone skin is most at risk. | M224: Warm, sweaty folds create the damp setting fungus prefers. Heat plus sweat trapped in folds creates the warm, damp setting fungus prefers, raising the risk of ringworm and yeast flare-ups. In Indian context: Most of India (Mar–Apr, Sep–Oct). If your day involves heat and sweat, breathable cotton, staying dry and a gentle clarifying wash help. Changing out of damp clothes quickly makes a real difference. | N224: Balance | O224: HD, HH, CN, TP, CH, TN | P224: Most of India (Mar–Apr, Sep–Oct)
A225: T-WARM-COM-FUNG | B225: Warm | C225: 28–34°C | D225: Combination | E225: Fungal Infection (Sweat & Folds) | F225: 2 | G225: Moderate | H225: INFERRED | I225: 9 cites · 0 PMID · 8 book · 7 India-relevant | K225: Warm air starts to bump up oil production. Keep skin folds dry to avoid fungus. | L225: Warm, sweaty folds create the damp setting fungus prefers. For combination skin with fungal flare-ups, breathable cotton, staying dry and a gentle clarifying wash help. Focus on oily zones and folds. | M225: Warm, sweaty folds create the damp setting fungus prefers. Heat plus sweat trapped in folds creates the warm, damp setting fungus prefers, raising the risk of ringworm and yeast flare-ups. In Indian context: Most of India (Mar–Apr, Sep–Oct). If your day involves heat and sweat, breathable cotton, staying dry and a gentle clarifying wash help. Changing out of damp clothes quickly makes a real difference. | N225: Balance | O225: HD, HH, CN, TP, CH, TN | P225: Most of India (Mar–Apr, Sep–Oct)
A226: T-WARM-SEN-FUNG | B226: Warm | C226: 28–34°C | D226: Sensitive | E226: Fungal Infection (Sweat & Folds) | F226: 2 | G226: Moderate | H226: INFERRED | I226: 9 cites · 0 PMID · 8 book · 7 India-relevant | K226: Warm air starts to bump up oil production. Keep skin folds dry to avoid fungus. | L226: Warm, sweaty folds create the damp setting fungus prefers. For sensitive skin with fungal flare-ups, breathable cotton, staying dry and a gentle clarifying wash help. A gentle wash avoids over-stripping. | M226: Warm, sweaty folds create the damp setting fungus prefers. Heat plus sweat trapped in folds creates the warm, damp setting fungus prefers, raising the risk of ringworm and yeast flare-ups. In Indian context: Most of India (Mar–Apr, Sep–Oct). If your day involves heat and sweat, breathable cotton, staying dry and a gentle clarifying wash help. Changing out of damp clothes quickly makes a real difference. | N226: Balance | O226: HD, HH, CN, TP, CH, TN | P226: Most of India (Mar–Apr, Sep–Oct)
A227: T-HOT-NOR-FUNG | B227: Hot | C227: 35–42°C | D227: Normal | E227: Fungal Infection (Sweat & Folds) | F227: 3 | G227: High | H227: INFERRED | I227: 10 cites · 0 PMID · 9 book · 8 India-relevant | K227: Heat is ramping up your oil and sweat. Keep skin dry to stop fungal flare-ups. | L227: Hot weather and trapped sweat raise fungal-infection risk in folds. For normal skin with fungal flare-ups, breathable cotton, staying dry and a gentle clarifying wash help. | M227: Hot weather and trapped sweat raise fungal-infection risk in folds. Heat plus sweat trapped in folds creates the warm, damp setting fungus prefers, raising the risk of ringworm and yeast flare-ups. In Indian context: Plains (Apr–Jun); the north Indian plains peaks. If your day involves heat and sweat, breathable cotton, staying dry and a gentle clarifying wash help. Changing out of damp clothes quickly makes a real difference. | N227: Balance | O227: HD, HH, CN, TP | P227: Plains (Apr–Jun); Delhi, Jaipur, Nagpur peaks
A228: T-HOT-DRY-FUNG | B228: Hot | C228: 35–42°C | D228: Dry | E228: Fungal Infection (Sweat & Folds) | F228: 3 | G228: High | H228: INFERRED | I228: 10 cites · 0 PMID · 9 book · 8 India-relevant | K228: Heat is ramping up your oil and sweat. Keep skin dry to stop fungal flare-ups. | L228: Hot weather and trapped sweat raise fungal-infection risk in folds. For dry skin with fungal flare-ups, breathable cotton, staying dry and a gentle clarifying wash help. Damp folds flare even on dry skin. | M228: Hot weather and trapped sweat raise fungal-infection risk in folds. Heat plus sweat trapped in folds creates the warm, damp setting fungus prefers, raising the risk of ringworm and yeast flare-ups. In Indian context: Plains (Apr–Jun); the north Indian plains peaks. If your day involves heat and sweat, breathable cotton, staying dry and a gentle clarifying wash help. Changing out of damp clothes quickly makes a real difference. | N228: Balance | O228: HD, HH, CN, TP | P228: Plains (Apr–Jun); Delhi, Jaipur, Nagpur peaks
A229: T-HOT-OIL-FUNG | B229: Hot | C229: 35–42°C | D229: Oily | E229: Fungal Infection (Sweat & Folds) | F229: 3 | G229: High | H229: INFERRED | I229: 10 cites · 0 PMID · 9 book · 8 India-relevant | K229: Heat is ramping up your oil and sweat. Keep skin dry to stop fungal flare-ups. | L229: Hot weather and trapped sweat raise fungal-infection risk in folds. For oily skin with fungal flare-ups, breathable cotton, staying dry and a gentle clarifying wash help. Oily, sweat-prone skin is most at risk. | M229: Hot weather and trapped sweat raise fungal-infection risk in folds. Heat plus sweat trapped in folds creates the warm, damp setting fungus prefers, raising the risk of ringworm and yeast flare-ups. In Indian context: Plains (Apr–Jun); the north Indian plains peaks. If your day involves heat and sweat, breathable cotton, staying dry and a gentle clarifying wash help. Changing out of damp clothes quickly makes a real difference. | N229: Balance | O229: HD, HH, CN, TP | P229: Plains (Apr–Jun); Delhi, Jaipur, Nagpur peaks
A230: T-HOT-COM-FUNG | B230: Hot | C230: 35–42°C | D230: Combination | E230: Fungal Infection (Sweat & Folds) | F230: 3 | G230: High | H230: INFERRED | I230: 10 cites · 0 PMID · 9 book · 8 India-relevant | K230: Heat is ramping up your oil and sweat. Keep skin dry to stop fungal flare-ups. | L230: Hot weather and trapped sweat raise fungal-infection risk in folds. For combination skin with fungal flare-ups, breathable cotton, staying dry and a gentle clarifying wash help. Focus on oily zones and folds. | M230: Hot weather and trapped sweat raise fungal-infection risk in folds. Heat plus sweat trapped in folds creates the warm, damp setting fungus prefers, raising the risk of ringworm and yeast flare-ups. In Indian context: Plains (Apr–Jun); the north Indian plains peaks. If your day involves heat and sweat, breathable cotton, staying dry and a gentle clarifying wash help. Changing out of damp clothes quickly makes a real difference. | N230: Balance | O230: HD, HH, CN, TP | P230: Plains (Apr–Jun); Delhi, Jaipur, Nagpur peaks
A231: T-HOT-SEN-FUNG | B231: Hot | C231: 35–42°C | D231: Sensitive | E231: Fungal Infection (Sweat & Folds) | F231: 3 | G231: High | H231: INFERRED | I231: 10 cites · 0 PMID · 9 book · 8 India-relevant | K231: Heat is ramping up your oil and sweat. Keep skin dry to stop fungal flare-ups. | L231: Hot weather and trapped sweat raise fungal-infection risk in folds. For sensitive skin with fungal flare-ups, breathable cotton, staying dry and a gentle clarifying wash help. A gentle wash avoids over-stripping. | M231: Hot weather and trapped sweat raise fungal-infection risk in folds. Heat plus sweat trapped in folds creates the warm, damp setting fungus prefers, raising the risk of ringworm and yeast flare-ups. In Indian context: Plains (Apr–Jun); the north Indian plains peaks. If your day involves heat and sweat, breathable cotton, staying dry and a gentle clarifying wash help. Changing out of damp clothes quickly makes a real difference. | N231: Balance | O231: HD, HH, CN, TP | P231: Plains (Apr–Jun); Delhi, Jaipur, Nagpur peaks
A232: T-HOT-NOR-HEAT | B232: Hot | C232: 35–42°C | D232: Normal | E232: Heat Rash (Prickly Heat) | F232: 3 | G232: High | H232: MODERATE | I232: 3 cites · 1 PMID · 2 book · 3 India-relevant | J232: PMID:36692206 | K232: Heat is ramping up your oil and sweat. Stay cool and dry to prevent heat rash. | L232: Hot weather and heavy sweating can block sweat ducts — prickly heat. For normal skin with prickly heat, loose cotton, staying cool and a light non-greasy moisturiser help most. | M232: Hot weather and heavy sweating can block sweat ducts — prickly heat. In heat your skin sweats hard through tiny ducts; when sweat can't escape it backs up under the surface and causes prickly heat — fine, itchy bumps. In Indian context: Plains (Apr–Jun); the north Indian plains peaks. If your day involves heat and sweat, loose breathable cotton, staying cool and a light non-greasy moisturiser help most, while heavy creams trap heat and make it worse. Cooling the skin clears most prickly heat within days. | N232: Calm | O232: HD, HH, CN, TP | P232: Plains (Apr–Jun); Delhi, Jaipur, Nagpur peaks
A233: T-HOT-DRY-HEAT | B233: Hot | C233: 35–42°C | D233: Dry | E233: Heat Rash (Prickly Heat) | F233: 3 | G233: High | H233: MODERATE | I233: 3 cites · 1 PMID · 2 book · 3 India-relevant | J233: PMID:36692206 | K233: Heat is ramping up your oil and sweat. Stay cool and dry to prevent heat rash. | L233: Hot weather and heavy sweating can block sweat ducts — prickly heat. For dry skin with prickly heat, loose cotton, staying cool and a light non-greasy moisturiser help most. Choose light, not heavy, creams. | M233: Hot weather and heavy sweating can block sweat ducts — prickly heat. In heat your skin sweats hard through tiny ducts; when sweat can't escape it backs up under the surface and causes prickly heat — fine, itchy bumps. In Indian context: Plains (Apr–Jun); the north Indian plains peaks. If your day involves heat and sweat, loose breathable cotton, staying cool and a light non-greasy moisturiser help most, while heavy creams trap heat and make it worse. Cooling the skin clears most prickly heat within days. | N233: Calm | O233: HD, HH, CN, TP | P233: Plains (Apr–Jun); Delhi, Jaipur, Nagpur peaks
A234: T-HOT-OIL-HEAT | B234: Hot | C234: 35–42°C | D234: Oily | E234: Heat Rash (Prickly Heat) | F234: 3 | G234: High | H234: MODERATE | I234: 3 cites · 1 PMID · 2 book · 3 India-relevant | J234: PMID:36692206 | K234: Heat is ramping up your oil and sweat. Stay cool and dry to prevent heat rash. | L234: Hot weather and heavy sweating can block sweat ducts — prickly heat. For oily skin with prickly heat, loose cotton, staying cool and a light non-greasy moisturiser help most. A light gel won't clog ducts. | M234: Hot weather and heavy sweating can block sweat ducts — prickly heat. In heat your skin sweats hard through tiny ducts; when sweat can't escape it backs up under the surface and causes prickly heat — fine, itchy bumps. In Indian context: Plains (Apr–Jun); the north Indian plains peaks. If your day involves heat and sweat, loose breathable cotton, staying cool and a light non-greasy moisturiser help most, while heavy creams trap heat and make it worse. Cooling the skin clears most prickly heat within days. | N234: Calm | O234: HD, HH, CN, TP | P234: Plains (Apr–Jun); Delhi, Jaipur, Nagpur peaks
A235: T-HOT-COM-HEAT | B235: Hot | C235: 35–42°C | D235: Combination | E235: Heat Rash (Prickly Heat) | F235: 3 | G235: High | H235: MODERATE | I235: 3 cites · 1 PMID · 2 book · 3 India-relevant | J235: PMID:36692206 | K235: Heat is ramping up your oil and sweat. Stay cool and dry to prevent heat rash. | L235: Hot weather and heavy sweating can block sweat ducts — prickly heat. For combination skin with prickly heat, loose cotton, staying cool and a light non-greasy moisturiser help most. Keep all zones light. | M235: Hot weather and heavy sweating can block sweat ducts — prickly heat. In heat your skin sweats hard through tiny ducts; when sweat can't escape it backs up under the surface and causes prickly heat — fine, itchy bumps. In Indian context: Plains (Apr–Jun); the north Indian plains peaks. If your day involves heat and sweat, loose breathable cotton, staying cool and a light non-greasy moisturiser help most, while heavy creams trap heat and make it worse. Cooling the skin clears most prickly heat within days. | N235: Calm | O235: HD, HH, CN, TP | P235: Plains (Apr–Jun); Delhi, Jaipur, Nagpur peaks
A236: T-HOT-SEN-HEAT | B236: Hot | C236: 35–42°C | D236: Sensitive | E236: Heat Rash (Prickly Heat) | F236: 3 | G236: High | H236: MODERATE | I236: 3 cites · 1 PMID · 2 book · 3 India-relevant | J236: PMID:36692206 | K236: Heat is ramping up your oil and sweat. Stay cool and dry to prevent heat rash. | L236: Hot weather and heavy sweating can block sweat ducts — prickly heat. For sensitive skin with prickly heat, loose cotton, staying cool and a light non-greasy moisturiser help most. Sensitive skin stings — prioritise cooling. | M236: Hot weather and heavy sweating can block sweat ducts — prickly heat. In heat your skin sweats hard through tiny ducts; when sweat can't escape it backs up under the surface and causes prickly heat — fine, itchy bumps. In Indian context: Plains (Apr–Jun); the north Indian plains peaks. If your day involves heat and sweat, loose breathable cotton, staying cool and a light non-greasy moisturiser help most, while heavy creams trap heat and make it worse. Cooling the skin clears most prickly heat within days. | N236: Calm | O236: HD, HH, CN, TP | P236: Plains (Apr–Jun); Delhi, Jaipur, Nagpur peaks
A237: T-EHEAT-NOR-HEAT | B237: Extreme Heat | C237: >42°C | D237: Normal | E237: Heat Rash (Prickly Heat) | F237: 4 | G237: Severe | H237: MODERATE | I237: 3 cites · 1 PMID · 2 book · 3 India-relevant | J237: PMID:36692206 | K237: Heatwave conditions are dehydrating your body and skin. Cool down and stay dry to stop rash. | L237: Extreme heat — sweat overload and high risk of itchy heat rash. For normal skin with prickly heat, loose cotton, staying cool and a light non-greasy moisturiser help most. | M237: Extreme heat — sweat overload and high risk of itchy heat rash. In heat your skin sweats hard through tiny ducts; when sweat can't escape it backs up under the surface and causes prickly heat — fine, itchy bumps. In Indian context: Heatwave events: the hot interior regions (May). If your day involves heat and sweat, loose breathable cotton, staying cool and a light non-greasy moisturiser help most, while heavy creams trap heat and make it worse. Cooling the skin clears most prickly heat within days. | N237: Calm | O237: HD, CN | P237: Heatwave events: Rajasthan, Vidarbha, Telangana (May)
A238: T-EHEAT-DRY-HEAT | B238: Extreme Heat | C238: >42°C | D238: Dry | E238: Heat Rash (Prickly Heat) | F238: 4 | G238: Severe | H238: MODERATE | I238: 3 cites · 1 PMID · 2 book · 3 India-relevant | J238: PMID:36692206 | K238: Heatwave conditions are dehydrating your body and skin. Cool down and stay dry to stop rash. | L238: Extreme heat — sweat overload and high risk of itchy heat rash. For dry skin with prickly heat, loose cotton, staying cool and a light non-greasy moisturiser help most. Choose light, not heavy, creams. | M238: Extreme heat — sweat overload and high risk of itchy heat rash. In heat your skin sweats hard through tiny ducts; when sweat can't escape it backs up under the surface and causes prickly heat — fine, itchy bumps. In Indian context: Heatwave events: the hot interior regions (May). If your day involves heat and sweat, loose breathable cotton, staying cool and a light non-greasy moisturiser help most, while heavy creams trap heat and make it worse. Cooling the skin clears most prickly heat within days. | N238: Calm | O238: HD, CN | P238: Heatwave events: Rajasthan, Vidarbha, Telangana (May)
A239: T-EHEAT-OIL-HEAT | B239: Extreme Heat | C239: >42°C | D239: Oily | E239: Heat Rash (Prickly Heat) | F239: 4 | G239: Severe | H239: MODERATE | I239: 3 cites · 1 PMID · 2 book · 3 India-relevant | J239: PMID:36692206 | K239: Heatwave conditions are dehydrating your body and skin. Cool down and stay dry to stop rash. | L239: Extreme heat — sweat overload and high risk of itchy heat rash. For oily skin with prickly heat, loose cotton, staying cool and a light non-greasy moisturiser help most. A light gel won't clog ducts. | M239: Extreme heat — sweat overload and high risk of itchy heat rash. In heat your skin sweats hard through tiny ducts; when sweat can't escape it backs up under the surface and causes prickly heat — fine, itchy bumps. In Indian context: Heatwave events: the hot interior regions (May). If your day involves heat and sweat, loose breathable cotton, staying cool and a light non-greasy moisturiser help most, while heavy creams trap heat and make it worse. Cooling the skin clears most prickly heat within days. | N239: Calm | O239: HD, CN | P239: Heatwave events: Rajasthan, Vidarbha, Telangana (May)
A240: T-EHEAT-COM-HEAT | B240: Extreme Heat | C240: >42°C | D240: Combination | E240: Heat Rash (Prickly Heat) | F240: 4 | G240: Severe | H240: MODERATE | I240: 3 cites · 1 PMID · 2 book · 3 India-relevant | J240: PMID:36692206 | K240: Heatwave conditions are dehydrating your body and skin. Cool down and stay dry to stop rash. | L240: Extreme heat — sweat overload and high risk of itchy heat rash. For combination skin with prickly heat, loose cotton, staying cool and a light non-greasy moisturiser help most. Keep all zones light. | M240: Extreme heat — sweat overload and high risk of itchy heat rash. In heat your skin sweats hard through tiny ducts; when sweat can't escape it backs up under the surface and causes prickly heat — fine, itchy bumps. In Indian context: Heatwave events: the hot interior regions (May). If your day involves heat and sweat, loose breathable cotton, staying cool and a light non-greasy moisturiser help most, while heavy creams trap heat and make it worse. Cooling the skin clears most prickly heat within days. | N240: Calm | O240: HD, CN | P240: Heatwave events: Rajasthan, Vidarbha, Telangana (May)
A241: T-EHEAT-SEN-HEAT | B241: Extreme Heat | C241: >42°C | D241: Sensitive | E241: Heat Rash (Prickly Heat) | F241: 4 | G241: Severe | H241: MODERATE | I241: 3 cites · 1 PMID · 2 book · 3 India-relevant | J241: PMID:36692206 | K241: Heatwave conditions are dehydrating your body and skin. Cool down and stay dry to stop rash. | L241: Extreme heat — sweat overload and high risk of itchy heat rash. For sensitive skin with prickly heat, loose cotton, staying cool and a light non-greasy moisturiser help most. Sensitive skin stings — prioritise cooling. | M241: Extreme heat — sweat overload and high risk of itchy heat rash. In heat your skin sweats hard through tiny ducts; when sweat can't escape it backs up under the surface and causes prickly heat — fine, itchy bumps. In Indian context: Heatwave events: the hot interior regions (May). If your day involves heat and sweat, loose breathable cotton, staying cool and a light non-greasy moisturiser help most, while heavy creams trap heat and make it worse. Cooling the skin clears most prickly heat within days. | N241: Calm | O241: HD, CN | P241: Heatwave events: Rajasthan, Vidarbha, Telangana (May)
A242: T-EXTR-NOR-DCIR-001 | B242: Extreme Cold | C242: <5°C | D242: Normal | E242: Dark Circles (Periorbital) | F242: 3 | G242: High | H242: INFERRED | I242: 2 cites · 0 PMID · 0 book · 1 India-relevant | J242: see evidence base (cold periorbital vasoconstriction) | K242: Sub-zero air holds almost no moisture. Sun protection and rest keep under-eye tone steadier. | L242: Cold slows blood flow under the eyes, so the bluish tint looks darker. For normal skin with dark circles, a gentle brightening serum and good sleep help the most; warmth and rest ease the look. | M242: Cold slows blood flow under the eyes, so the bluish tint looks darker. Cold air narrows the tiny blood vessels under your eyes and slows drainage, so pooled blood shows through the thin skin as a darker, bluish shadow. It often eases once you warm up. In Indian context: Most noticeable on cold North Indian and hill-station mornings. A gentle brightening serum and good sleep help the most; warmth and rest ease the look. Gentle daily habits matter more here than any single product. | N242: Brighten | O242: CH, CN | P242: Dec–Feb mornings
A243: T-EXTR-DRY-DCIR-002 | B243: Extreme Cold | C243: <5°C | D243: Dry | E243: Dark Circles (Periorbital) | F243: 3 | G243: High | H243: INFERRED | I243: 2 cites · 0 PMID · 0 book · 1 India-relevant | J243: see evidence base (cold periorbital vasoconstriction) | K243: Sub-zero air holds almost no moisture. Sun protection and rest keep under-eye tone steadier. | L243: Cold slows blood flow under the eyes, so the bluish tint looks darker. For dry skin with dark circles, a gentle brightening serum and good sleep help the most; warmth and rest ease the look. | M243: Cold slows blood flow under the eyes, so the bluish tint looks darker. Cold air narrows the tiny blood vessels under your eyes and slows drainage, so pooled blood shows through the thin skin as a darker, bluish shadow. It often eases once you warm up. In Indian context: Most noticeable on cold North Indian and hill-station mornings. A gentle brightening serum and good sleep help the most; warmth and rest ease the look. Gentle daily habits matter more here than any single product. | N243: Brighten | O243: CH, CN | P243: Dec–Feb mornings
... A276: T-EXTR-SEN-DCIR-035 | B276: Extreme Heat | C276: >42°C | D276: Sensitive | E276: Dark Circles (Periorbital) | F276: 1 | G276: Low | H276: INFERRED | I276: 2 cites · 0 PMID · 0 book · 1 India-relevant | J276: see evidence base (cold periorbital vasoconstriction) | K276: Heatwave conditions are dehydrating your body and skin. Sun protection and rest keep under-eye tone steadier. | L276: Cold slows blood flow under the eyes, so the bluish tint looks darker. For sensitive skin with dark circles, a gentle brightening serum and good sleep help the most; warmth and rest ease the look. | M276: Cold slows blood flow under the eyes, so the bluish tint looks darker. Cold air narrows the tiny blood vessels under your eyes and slows drainage, so pooled blood shows through the thin skin as a darker, bluish shadow. It often eases once you warm up. In Indian context: Most noticeable on cold North Indian and hill-station mornings. A gentle brightening serum and good sleep help the most; warmth and rest ease the look. Gentle daily habits matter more here than any single product. | N276: Brighten | O276: CH, CN | P276: Dec–Feb mornings

Sheet 5. AQI Cells
A1: Scenario ID | B1: Band | C1: Range | D1: Skin Type | E1: Concern | F1: Risk | G1: Risk Level | H1: Confidence | I1: Evidence Summary | J1: PMID Anchors | K1: L0 Compact (≤20w) | L1: L1 Personalised (≤40w) | M1: L2 Explainer (60–90w) | N1: Action Cluster | O1: Applicable Zones | P1: Indian Cities/Season
A2: A-GOOD-NOR-DRYN-001 | B2: Good | C2: 0–50 | D2: Normal | E2: Dryness | F2: 0 | G2: Negligible | H2: MODERATE | I2: 1 cites · 0 PMID · 1 book · 0 India-relevant | J2: Skin Barrier, p.385 | K2: Air is clean today. Maintain your usual moisturising routine. | L2: Air is clean today. Your skin faces no extra pressure from this factor today. Routine day. | M2: Air is clean today. Clean air = barrier recovery window. Hydration and repair work better now. In Indian context: Hill stations, the southwest coast monsoon. Environmental pressure is low today — a good day to be consistent with your basics. Sunscreen still matters regardless of weather; visible light triggers pigment year-round. | N2: Maintain | O2: CH, TN | P2: Hill stations, coastal Kerala, Goa monsoon
A3: A-GOOD-NOR-ECZE-002 | B3: Good | C3: 0–50 | D3: Normal | E3: Eczema | F3: 0 | G3: Negligible | H3: MODERATE | I3: 1 cites · 0 PMID · 1 book · 1 India-relevant | J3: Skin Stress Response Pathways:, p.345 | K3: Air is clean today. Maintain your usual gentle routine. | L3: Air is clean today. Your skin faces no extra pressure from this factor today. Routine day. | M3: Air is clean today. Lowest pollutant-driven flare pressure. Use this window to rebuild. In Indian context: Hill stations, the southwest coast monsoon. Environmental pressure is low today — a good day to be consistent with your basics. Sunscreen still matters regardless of weather; visible light triggers pigment year-round. | N3: Maintain | O3: CH, TN | P3: Hill stations, coastal Kerala, Goa monsoon
A4: A-GOOD-NOR-OILY-003 | B4: Good | C4: 0–50 | D4: Normal | E4: Oily Skin | F4: 0 | G4: Negligible | H4: INFERRED | I4: 0 cites · 0 PMID · 0 book · 0 India-relevant | J4: see evidence base | K4: Air is clean today. Maintain your usual routine for oily skin. | L4: Air is clean today. Your skin faces no extra pressure from this factor today. Routine day. | M4: Air is clean today. No pollution film on your skin. Pores breathe. In Indian context: Hill stations, the southwest coast monsoon. Environmental pressure is low today — a good day to be consistent with your basics. Sunscreen still matters regardless of weather; visible light triggers pigment year-round. | N4: Maintain | O4: CH, TN | P4: Hill stations, coastal Kerala, Goa monsoon
A5: A-GOOD-NOR-ACNE-004 | B5: Good | C5: 0–50 | D5: Normal | E5: Acne | F5: 0 | G5: Negligible | H5: MODERATE | I5: 3 cites · 0 PMID · 3 book · 2 India-relevant | J5: Skin Stress Response Pathways:, p.347 | Skin Stress Response Pathways:, p.345 | K5: Air is clean today. Take good care of your acne-prone pores. | L5: Air is clean today. Your skin faces no extra pressure from this factor today. Routine day. | M5: Air is clean today. Pollution-driven inflammation is off the table. Treatments work cleanly. In Indian context: Hill stations, the southwest coast monsoon. Environmental pressure is low today — a good day to be consistent with your basics. Sunscreen still matters regardless of weather; visible light triggers pigment year-round. | N5: Maintain | O5: CH, TN | P5: Hill stations, coastal Kerala, Goa monsoon
A6: A-GOOD-NOR-UNEV-005 | B6: Good | C6: 0–50 | D6: Normal | E6: Uneven Skin Tone / Tan | F6: 0 | G6: Negligible | H6: MODERATE | I6: 1 cites · 0 PMID · 1 book · 1 India-relevant | J6: Skin Stress Response Pathways:, p.347 | K6: Air is clean today. Keep up your daily sun protection. | L6: Air is clean today. Your skin faces no extra pressure from this factor today. Routine day. | M6: Air is clean today. No particulate-driven pigment stimulation. Tan can fade naturally. In Indian context: Hill stations, the southwest coast monsoon. Environmental pressure is low today — a good day to be consistent with your basics. Sunscreen still matters regardless of weather; visible light triggers pigment year-round. | N6: Maintain | O6: CH, TN | P6: Hill stations, coastal Kerala, Goa monsoon
A7: A-GOOD-NOR-MELA-006 | B7: Good | C7: 0–50 | D7: Normal | E7: Melasma | F7: 0 | G7: Negligible | H7: INFERRED | I7: 0 cites · 0 PMID · 0 book · 0 India-relevant | J7: see evidence base | K7: Air is clean today. Keep up your daily sun protection. | L7: Air is clean today. Your skin faces no extra pressure from this factor today. Routine day. | M7: Air is clean today. A rare clean window. Pigment-targeting actives have the best shot now. In Indian context: Hill stations, the southwest coast monsoon. Environmental pressure is low today — a good day to be consistent with your basics. Sunscreen still matters regardless of weather; visible light triggers pigment year-round. | N7: Maintain | O7: CH, TN | P7: Hill stations, coastal Kerala, Goa monsoon
A8: A-GOOD-DRY-DRYN-007 | B8: Good | C8: 0–50 | D8: Dry | E8: Dryness | F8: 0 | G8: Negligible | H8: MODERATE | I8: 1 cites · 0 PMID · 1 book · 0 India-relevant | J8: Skin Barrier, p.385 | K8: Air is clean today. Maintain your usual moisturising routine. | L8: Air is clean today. Your dry skin faces no extra pressure from this factor today. Routine day. | M8: Air is clean today. Clean air = barrier recovery window. Hydration and repair work better now. In Indian context: Hill stations, the southwest coast monsoon. Environmental pressure is low today — a good day to be consistent with your basics. Sunscreen still matters regardless of weather; visible light triggers pigment year-round. | N8: Maintain | O8: CH, TN | P8: Hill stations, coastal Kerala, Goa monsoon
A9: A-GOOD-DRY-ECZE-008 | B9: Good | C9: 0–50 | D9: Dry | E9: Eczema | F9: 0 | G9: Negligible | H9: MODERATE | I9: 1 cites · 0 PMID · 1 book · 1 India-relevant | J9: Skin Stress Response Pathways:, p.345 | K9: Air is clean today. Maintain your usual gentle routine. | L9: Air is clean today. Your dry skin faces no extra pressure from this factor today. Routine day. | M9: Air is clean today. Lowest pollutant-driven flare pressure. Use this window to rebuild. In Indian context: Hill stations, the southwest coast monsoon. Environmental pressure is low today — a good day to be consistent with your basics. Sunscreen still matters regardless of weather; visible light triggers pigment year-round. | N9: Maintain | O9: CH, TN | P9: Hill stations, coastal Kerala, Goa monsoon
A10: A-GOOD-DRY-OILY-009 | B10: Good | C10: 0–50 | D10: Dry | E10: Oily Skin | F10: 0 | G10: Negligible | H10: INFERRED | I10: 0 cites · 0 PMID · 0 book · 0 India-relevant | J10: see evidence base | K10: Air is clean today. Maintain your usual routine for oily skin. | L10: Air is clean today. Your dry skin faces no extra pressure from this factor today. Routine day. | M10: Air is clean today. No pollution film on your skin. Pores breathe. In Indian context: Hill stations, the southwest coast monsoon. Environmental pressure is low today — a good day to be consistent with your basics. Sunscreen still matters regardless of weather; visible light triggers pigment year-round. | N10: Maintain | O10: CH, TN | P10: Hill stations, coastal Kerala, Goa monsoon
A11: A-GOOD-DRY-ACNE-010 | B11: Good | C11: 0–50 | D11: Dry | E11: Acne | F11: 0 | G11: Negligible | H11: MODERATE | I11: 3 cites · 0 PMID · 3 book · 2 India-relevant | J11: Skin Stress Response Pathways:, p.347 | Skin Stress Response Pathways:, p.345 | K11: Air is clean today. Take good care of your acne-prone pores. | L11: Air is clean today. Your dry skin faces no extra pressure from this factor today. Routine day. | M11: Air is clean today. Pollution-driven inflammation is off the table. Treatments work cleanly. In Indian context: Hill stations, the southwest coast monsoon. Environmental pressure is low today — a good day to be consistent with your basics. Sunscreen still matters regardless of weather; visible light triggers pigment year-round. | N11: Maintain | O11: CH, TN | P11: Hill stations, coastal Kerala, Goa monsoon
A12: A-GOOD-DRY-UNEV-011 | B12: Good | C12: 0–50 | D12: Dry | E12: Uneven Skin Tone / Tan | F12: 0 | G12: Negligible | H12: MODERATE | I12: 1 cites · 0 PMID · 1 book · 1 India-relevant | J12: Skin Stress Response Pathways:, p.347 | K12: Air is clean today. Keep up your daily sun protection. | L12: Air is clean today. Your dry skin faces no extra pressure from this factor today. Routine day. | M12: Air is clean today. No particulate-driven pigment stimulation. Tan can fade naturally. In Indian context: Hill stations, the southwest coast monsoon. Environmental pressure is low today — a good day to be consistent with your basics. Sunscreen still matters regardless of weather; visible light triggers pigment year-round. | N12: Maintain | O12: CH, TN | P12: Hill stations, coastal Kerala, Goa monsoon
A13: A-GOOD-DRY-MELA-012 | B13: Good | C13: 0–50 | D13: Dry | E13: Melasma | F13: 0 | G13: Negligible | H13: INFERRED | I13: 0 cites · 0 PMID · 0 book · 0 India-relevant | J13: see evidence base | K13: Air is clean today. Keep up your daily sun protection. | L13: Air is clean today. Your dry skin faces no extra pressure from this factor today. Routine day. | M13: Air is clean today. A rare clean window. Pigment-targeting actives have the best shot now. In Indian context: Hill stations, the southwest coast monsoon. Environmental pressure is low today — a good day to be consistent with your basics. Sunscreen still matters regardless of weather; visible light triggers pigment year-round. | N13: Maintain | O13: CH, TN | P13: Hill stations, coastal Kerala, Goa monsoon
... A306: A-SEVE-SEN-HAIR-030 | B306: Severe | C306: >400 | D306: Sensitive | E306: Hair & Scalp (Shedding) | F306: 4 | G306: Severe | H306: INFERRED | I306: 5 cites · 0 PMID · 5 book · 8 India-relevant | J306: see evidence base (pollution + scalp/hair) | K306: Hazardous air — pollution overload on skin and body. Rinse the scalp clean after sweat or grime. | L306: City grime settles on the scalp and can leave it irritated. For sensitive skin with hair and scalp concerns, rinsing the scalp clean after a polluted commute keeps roots comfortable. | M306: City grime settles on the scalp and can leave it irritated. Fine pollution particles settle on the scalp just like on facial skin, where they can clog and irritate the roots. A regular gentle cleanse after high-pollution days keeps the scalp calmer, which supports healthier hair. In Indian context: Most relevant in high-pollution metro months. If commute or outdoor time today is long, rinsing the scalp clean after a polluted commute keeps roots comfortable. A simple, consistent cleanse is the main habit here. | N306: Cleanse | O306: HD, EI | P306: Oct–Jan smog months

Sheet 6. UV Cells
A1: Scenario ID | B1: Band | C1: Range | D1: Skin Type | E1: Concern | F1: Risk | G1: Risk Level | H1: Confidence | I1: Evidence Summary | J1: PMID Anchors | K1: L0 Compact (≤20w) | L1: L1 Personalised (≤40w) | M1: L2 Explainer (60–90w) | N1: Action Cluster | O1: Applicable Zones | P1: Indian Cities/Season
A2: U-LOW-NOR-DRYN-001 | B2: Low | C2: 0–2 | D2: Normal | E2: Dryness | F2: 0 | G2: Negligible | H2: MODERATE | I2: 4 cites · 4 PMID · 0 book · 0 India-relevant | J2: see evidence base | K2: UV is mild today. Maintain your usual moisturising routine. | L2: UV is mild today. Your skin faces no extra pressure from this factor today. Routine day. | M2: UV is mild today. Minimal UV stress on your barrier today. In Indian context: Monsoon overcast days; winter mornings/evenings. Environmental pressure is low today — a good day to be consistent with your basics. Sunscreen still matters regardless of weather; visible light triggers pigment year-round. | N2: Maintain | O2: multiple | P2: Monsoon overcast days; winter mornings/evenings
A3: U-LOW-NOR-ECZE-002 | B3: Low | C3: 0–2 | D3: Normal | E3: Eczema | F3: 0 | G3: Negligible | H3: INFERRED | I3: 0 cites · 0 PMID · 0 book · 0 India-relevant | J3: see evidence base | K3: UV is mild today. Maintain your usual gentle routine. | L3: UV is mild today. Your skin faces no extra pressure from this factor today. Routine day. | M3: UV is mild today. Brief mid-day sun can be calming for some — avoid extremes. In Indian context: Monsoon overcast days; winter mornings/evenings. Environmental pressure is low today — a good day to be consistent with your basics. Sunscreen still matters regardless of weather; visible light triggers pigment year-round. | N3: Maintain | O3: multiple | P3: Monsoon overcast days; winter mornings/evenings
A4: U-LOW-NOR-OILY-003 | B4: Low | C4: 0–2 | D4: Normal | E4: Oily Skin | F4: 0 | G4: Negligible | H4: MODERATE | I4: 4 cites · 2 PMID · 2 book · 0 India-relevant | J4: Skin Stress Response Pathways:, p.33 | Skin Barrier, p.388 | K4: UV is mild today. Maintain your usual routine for oily skin. | L4: UV is mild today. Your skin faces no extra pressure from this factor today. Routine day. | M4: UV is mild today. No UV-driven thickening or skin oil changes today. In Indian context: Monsoon overcast days; winter mornings/evenings. Environmental pressure is low today — a good day to be consistent with your basics. Sunscreen still matters regardless of weather; visible light triggers pigment year-round. | N4: Maintain | O4: multiple | P4: Monsoon overcast days; winter mornings/evenings
A5: U-LOW-NOR-ACNE-004 | B5: Low | C5: 0–2 | D5: Normal | E5: Acne | F5: 0 | G5: Negligible | H5: MODERATE | I5: 4 cites · 4 PMID · 0 book · 0 India-relevant | J5: see evidence base | K5: UV is mild today. Take good care of your acne-prone pores. | L5: UV is mild today. Your skin faces no extra pressure from this factor today. Routine day. | M5: UV is mild today. No UV-induced post-acne marks today. Safe healing window for active lesions. In Indian context: Monsoon overcast days; winter mornings/evenings. Environmental pressure is low today — a good day to be consistent with your basics. Sunscreen still matters regardless of weather; visible light triggers pigment year-round. | N5: Maintain | O5: multiple | P5: Monsoon overcast days; winter mornings/evenings
A6: U-LOW-NOR-UNEV-005 | B6: Low | C6: 0–2 | D6: Normal | E6: Uneven Skin Tone / Tan | F6: 0 | G6: Negligible | H6: MODERATE | I6: 13 cites · 13 PMID · 0 book · 0 India-relevant | J6: see evidence base | K6: UV is mild today. Keep up your daily sun protection. | L6: UV is mild today. Your skin faces no extra pressure from this factor today. Sun shield up. | M6: UV is mild today. Lowest pigment production pressure. Fade actives have their best shot now. In Indian context: Monsoon overcast days; winter mornings/evenings. A broad-spectrum sunscreen reapplied every two hours is the highest-value step today. For pigment concerns, look for added iron oxides which also block visible light. | N6: Shield | O6: multiple | P6: Monsoon overcast days; winter mornings/evenings
A7: U-LOW-NOR-MELA-006 | B7: Low | C7: 0–2 | D7: Normal | E7: Melasma | F7: 1 | G7: Low | H7: MODERATE | I7: 2 cites · 2 PMID · 0 book · 0 India-relevant | J7: see evidence base | K7: Sun's easy today — a quiet day for your melasma. Keep your usual SPF on. | L7: For your skin, low UV means little is stirring the pigment right now — but melasma has a long memory. Staying consistent with your morning sunscreen today is what quietly stops the slow creep, even when nothing looks like it's happening. | M7: Why bother on a dull day? Melasma's pigment cells never fully switch off — even indoor and cloudy-day light keeps them mildly active, which is why daily SPF is treated as non-negotiable, not weather-dependent. | N7: Shield | O7: multiple | P7: Monsoon overcast days; winter mornings/evenings
A8: U-LOW-DRY-DRYN-007 | B8: Low | C8: 0–2 | D8: Dry | E8: Dryness | F8: 0 | G8: Negligible | H8: MODERATE | I8: 4 cites · 4 PMID · 0 book · 0 India-relevant | J8: see evidence base | K8: UV is mild today. Maintain your usual moisturising routine. | L8: UV is mild today. Your dry skin faces no extra pressure from this factor today. Routine day. | M8: UV is mild today. Minimal UV stress on your barrier today. In Indian context: Monsoon overcast days; winter mornings/evenings. Environmental pressure is low today — a good day to be consistent with your basics. Sunscreen still matters regardless of weather; visible light triggers pigment year-round. | N8: Maintain | O8: multiple | P8: Monsoon overcast days; winter mornings/evenings
A9: U-LOW-DRY-ECZE-008 | B9: Low | C9: 0–2 | D9: Dry | E9: Eczema | F9: 0 | G9: Negligible | H9: INFERRED | I9: 0 cites · 0 PMID · 0 book · 0 India-relevant | J9: see evidence base | K9: UV is mild today. Maintain your usual gentle routine. | L9: UV is mild today. Your dry skin faces no extra pressure from this factor today. Routine day. | M9: UV is mild today. Brief mid-day sun can be calming for some — avoid extremes. In Indian context: Monsoon overcast days; winter mornings/evenings. Environmental pressure is low today — a good day to be consistent with your basics. Sunscreen still matters regardless of weather; visible light triggers pigment year-round. | N9: Maintain | O9: multiple | P9: Monsoon overcast days; winter mornings/evenings
A10: U-LOW-DRY-OILY-009 | B10: Low | C10: 0–2 | D10: Dry | E10: Oily Skin | F10: 0 | G10: Negligible | H10: MODERATE | I10: 4 cites · 2 PMID · 2 book · 0 India-relevant | J10: Skin Stress Response Pathways:, p.33 | Skin Barrier, p.388 | K10: UV is mild today. Maintain your usual routine for oily skin. | L10: UV is mild today. Your dry skin faces no extra pressure from this factor today. Routine day. | M10: UV is mild today. No UV-driven thickening or skin oil changes today. In Indian context: Monsoon overcast days; winter mornings/evenings. Environmental pressure is low today — a good day to be consistent with your basics. Sunscreen still matters regardless of weather; visible light triggers pigment year-round. | N10: Maintain | O10: multiple | P10: Monsoon overcast days; winter mornings/evenings
A11: U-LOW-DRY-ACNE-010 | B11: Low | C11: 0–2 | D11: Dry | E11: Acne | F11: 0 | G11: Negligible | H11: MODERATE | I11: 4 cites · 4 PMID · 0 book · 0 India-relevant | J11: see evidence base | K11: UV is mild today. Take good care of your acne-prone pores. | L11: UV is mild today. Your dry skin faces no extra pressure from this factor today. Routine day. | M11: UV is mild today. No UV-induced post-acne marks today. Safe healing window for active lesions. In Indian context: Monsoon overcast days; winter mornings/evenings. Environmental pressure is low today — a good day to be consistent with your basics. Sunscreen still matters regardless of weather; visible light triggers pigment year-round. | N11: Maintain | O11: multiple | P11: Monsoon overcast days; winter mornings/evenings
A12: U-LOW-DRY-UNEV-011 | B12: Low | C12: 0–2 | D12: Dry | E12: Uneven Skin Tone / Tan | F12: 0 | G12: Negligible | H12: MODERATE | I12: 13 cites · 13 PMID · 0 book · 0 India-relevant | J12: see evidence base | K12: UV is mild today. Keep up your daily sun protection. | L12: UV is mild today. Your dry skin faces no extra pressure from this factor today. Sun shield up. | M12: UV is mild today. Lowest pigment production pressure. Fade actives have their best shot now. In Indian context: Monsoon overcast days; winter mornings/evenings. A broad-spectrum sunscreen reapplied every two hours is the highest-value step today. For pigment concerns, look for added iron oxides which also block visible light. | N12: Shield | O12: multiple | P12: Monsoon overcast days; winter mornings/evenings
A13: U-LOW-DRY-MELA-012 | B13: Low | C13: 0–2 | D13: Dry | E13: Melasma | F13: 1 | G13: Low | H13: MODERATE | I13: 2 cites · 2 PMID · 0 book · 0 India-relevant | J13: see evidence base | K13: Sun's easy today — a quiet day for your melasma. Keep your usual SPF on. | L13: For your dry skin, low UV means little is stirring the pigment right now — but melasma has a long memory. Staying consistent with your morning sunscreen today is what quietly stops the slow creep, even when nothing looks like it's happening. | M13: Why bother on a dull day? Melasma's pigment cells never fully switch off — even indoor and cloudy-day light keeps them mildly active, which is why daily SPF is treated as non-negotiable, not weather-dependent. | N13: Shield | O13: multiple | P13: Monsoon overcast days; winter mornings/evenings
... A291: U-EXTR-SEN-HAIR-025 | B291: Extreme | C291: 11+ | D291: Sensitive | E291: Hair & Scalp (Shedding) | F291: 5 | G291: Critical | H291: MODERATE | I291: 8 cites · 1 PMID · 8 book · 8 India-relevant | J291: see evidence base (scalp UV; part-line exposure) | K291: UV is at danger levels — limit time outside. Cover the scalp and part line in strong sun. | L291: For sensitive skin with hair and scalp concerns, a hat or covering the part line on long sun days protects the scalp; hair shielded from sun stays in better shape. | M291: Strong sun reaches your scalp along the part line and hair edges. The skin on your scalp gets the same sun damage as your face, especially along the part line and any thinning areas. Over time this adds oxidative stress to the hair roots, so covering up on long outdoor days helps protect both scalp and hair. If outdoor time today is long, a hat or covering the part line on long sun days protects the scalp; hair shielded from sun stays in better shape. Protecting the area early is the biggest help. | N291: Shield | O291: multiple | P291: Mar–Jun peak sun

Sheet 7. Humidity Cells
A1: Scenario ID | B1: Band | C1: Range | D1: Skin Type | E1: Concern | F1: Risk | G1: Risk Level | H1: Confidence | I1: Evidence Summary | J1: PMID Anchors | K1: L0 Compact (≤20w) | L1: L1 Personalised (≤40w) | M1: L2 Explainer (60–90w) | N1: Action Cluster | O1: Applicable Zones | P1: Indian Cities/Season
A2: H-CRIT-NOR-DRYN-001 | B2: Critical Low | C2: <10% | D2: Normal | E2: Dryness | F2: 5 | G2: Critical | H2: HIGH | I2: 71 cites · 50 PMID · 17 book · 16 India-relevant | J2: PMID:12406336 | PMID:9804350 | PMID:20209486 | K2: Air is bone-dry — it pulls moisture from skin fast. Lock in moisture to protect your skin now. | L2: Air is bone-dry — it pulls moisture from skin fast. For your skin with dryness, this is as tough as it gets for your skin. Layer a water-binding humectant (like glycerin) on damp skin, then seal with an emollient. Apply within three minutes of any wash. | M2: Air is bone-dry — it pulls moisture from skin fast. Air below 10% pulls water from your skin at maximum rate. Stratum corneum water drops below 5%. In Indian context: desert-region summer; heated indoor air winter. Build moisture from the inside out: water-binding humectants (like glycerin) on damp skin, sealed with an emollient layer that locks moisture in. Apply within three minutes of any wash before water evaporates. A bedroom humidifier helps overnight. | N2: Hydrate | O2: HD | P2: Desert Rajasthan summer; heated indoor air winter
A3: H-CRIT-NOR-ECZE-002 | B3: Critical Low | C3: <10% | D3: Normal | E3: Eczema | F3: 5 | G3: Critical | H3: HIGH | I3: 26 cites · 15 PMID · 10 book · 13 India-relevant | J3: PMID:23334343 | PMID:26449379 | PMID:29273721 | K3: Air is bone-dry — it pulls moisture from skin fast. Soothe and protect eczema-prone skin now. | L3: Air is bone-dry — it pulls moisture from skin fast. For your skin with eczema, this is as tough as it gets for your skin. Layer a water-binding humectant (like glycerin) on damp skin, then seal with an emollient. Apply within three minutes of any wash. | M3: Air is bone-dry — it pulls moisture from skin fast. Severe barrier insult — flares near-certain. A humidifier becomes a clinical aid. In Indian context: desert-region summer; heated indoor air winter. Build moisture from the inside out: water-binding humectants (like glycerin) on damp skin, sealed with an emollient layer that locks moisture in. Apply within three minutes of any wash before water evaporates. A bedroom humidifier helps overnight. | N3: Hydrate | O3: HD | P3: Desert Rajasthan summer; heated indoor air winter
A4: H-CRIT-NOR-OILY-003 | B4: Critical Low | C4: <10% | D4: Normal | E4: Oily Skin | F4: 0 | G4: Negligible | H4: HIGH | I4: 4 cites · 3 PMID · 1 book · 4 India-relevant | J4: PMID:29273721 | Cosmetic Dermatology for Skin , p.p. 106 | K4: Air is bone-dry — it pulls moisture from skin fast. Maintain your usual routine for oily skin. | L4: Air is bone-dry — it pulls moisture from skin fast. Your skin faces no extra pressure from this factor today. Light layers only. | M4: Air is bone-dry — it pulls moisture from skin fast. Skin compensates with rebound oil. Dehydrated-oily paradox at extreme. In Indian context: desert-region summer; heated indoor air winter. Light, non-greasy products work best. Cleanse twice if you've been outdoors — once to lift sunscreen and surface oil, once to clean. Keep heavier sealing creams off the T-zone (forehead, nose and chin) today; they trap oil. | N4: Balance | O4: HD | P4: Desert Rajasthan summer; heated indoor air winter
A5: H-CRIT-NOR-ACNE-004 | B5: Critical Low | C5: <10% | D5: Normal | E5: Acne | F5: 1 | G5: Low | H5: HIGH | I5: 12 cites · 11 PMID · 1 book · 10 India-relevant | J5: PMID:23334343 | PMID:38033568 | PMID:30238598 | K5: Air is bone-dry — it pulls moisture from skin fast. Take good care of your acne-prone pores. | L5: Air is bone-dry — it pulls moisture from skin fast. Your skin with acne feels this as a manageable environmental hit. Light layers only. | M5: Air is bone-dry — it pulls moisture from skin fast. Rebound oil from dehydration can trigger clogged pores even in non-oily types. In Indian context: desert-region summer; heated indoor air winter. Light, non-greasy products work best. Cleanse twice if you've been outdoors — once to lift sunscreen and surface oil, once to clean. Keep heavier sealing creams off the T-zone (forehead, nose and chin) today; they trap oil. | N5: Balance | O5: HD | P5: Desert Rajasthan summer; heated indoor air winter
A6: H-CRIT-NOR-UNEV-005 | B6: Critical Low | C6: <10% | D6: Normal | E6: Uneven Skin Tone / Tan | F6: 1 | G6: Low | H6: HIGH | I6: 18 cites · 12 PMID · 6 book · 10 India-relevant | J6: PMID:20209486 | PMID:31617869 | PMID:22077137 | K6: Air is bone-dry — it pulls moisture from skin fast. Daily sun protection keeps tone even. | L6: Air is bone-dry — it pulls moisture from skin fast. Your skin with uneven skin tone / tan feels this as a manageable environmental hit. Hydrate hard. | M6: Air is bone-dry — it pulls moisture from skin fast. Barrier breach amplifies the damage from every other stressor. In Indian context: desert-region summer; heated indoor air winter. Build moisture from the inside out: water-binding humectants (like glycerin) on damp skin, sealed with an emollient layer that locks moisture in. Apply within three minutes of any wash before water evaporates. A bedroom humidifier helps overnight. | N6: Hydrate | O6: HD | P6: Desert Rajasthan summer; heated indoor air winter
A7: H-CRIT-NOR-MELA-006 | B7: Critical Low | C7: <10% | D7: Normal | E7: Melasma | F7: 1 | G7: Low | H7: HIGH | I7: 5 cites · 5 PMID · 0 book · 1 India-relevant | J7: PMID:20209486 | PMID:22077137 | K7: Air is bone-dry — it pulls moisture from skin fast. Daily sun protection keeps melasma calm. | L7: Air is bone-dry — it pulls moisture from skin fast. Your skin with melasma feels this as a manageable environmental hit. Hydrate hard. | M7: Air is bone-dry — it pulls moisture from skin fast. Compromised barrier amplifies impact of UV and heat indirectly. In Indian context: desert-region summer; heated indoor air winter. Build moisture from the inside out: water-binding humectants (like glycerin) on damp skin, sealed with an emollient layer that locks moisture in. Apply within three minutes of any wash before water evaporates. A bedroom humidifier helps overnight. | N7: Hydrate | O7: HD | P7: Desert Rajasthan summer; heated indoor air winter
A8: H-CRIT-DRY-DRYN-007 | B8: Critical Low | C8: <10% | D8: Dry | E8: Dryness | F8: 5 | G8: Critical | H8: HIGH | I8: 111 cites · 53 PMID · 36 book · 37 India-relevant | J8: PMID:31544070 | PMID:102946 | PMID:12406336 | K8: Air is bone-dry — it pulls moisture from skin fast. Lock in moisture to protect your skin now. | L8: Air is bone-dry — it pulls moisture from skin fast. For your dry skin with dryness, this is as tough as it gets for your skin. Layer a water-binding humectant (like glycerin) on damp skin, then seal with an emollient. Apply within three minutes of any wash. | M8: Air is bone-dry — it pulls moisture from skin fast. Air below 10% pulls water from your skin at maximum rate. Stratum corneum water drops below 5%. In Indian context: desert-region summer; heated indoor air winter. Build moisture from the inside out: water-binding humectants (like glycerin) on damp skin, sealed with an emollient layer that locks moisture in. Apply within three minutes of any wash before water evaporates. A bedroom humidifier helps overnight. | N8: Hydrate | O8: HD | P8: Desert Rajasthan summer; heated indoor air winter
A9: H-CRIT-DRY-ECZE-008 | B9: Critical Low | C9: <10% | D9: Dry | E9: Eczema | F9: 5 | G9: Critical | H9: HIGH | I9: 48 cites · 19 PMID · 26 book · 29 India-relevant | J9: PMID:23334343 | PMID:26449379 | PMID:29273721 | K9: Air is bone-dry — it pulls moisture from skin fast. Soothe and protect eczema-prone skin now. | L9: Air is bone-dry — it pulls moisture from skin fast. For your dry skin with eczema, this is as tough as it gets for your skin. Layer a water-binding humectant (like glycerin) on damp skin, then seal with an emollient. Apply within three minutes of any wash. | M9: Air is bone-dry — it pulls moisture from skin fast. Severe barrier insult — flares near-certain. A humidifier becomes a clinical aid. In Indian context: desert-region summer; heated indoor air winter. Build moisture from the inside out: water-binding humectants (like glycerin) on damp skin, sealed with an emollient layer that locks moisture in. Apply within three minutes of any wash before water evaporates. A bedroom humidifier helps overnight. | N9: Hydrate | O9: HD | P9: Desert Rajasthan summer; heated indoor air winter
A10: H-CRIT-DRY-OILY-009 | B10: Critical Low | C10: <10% | D10: Dry | E10: Oily Skin | F10: 1 | G10: Low | H10: HIGH | I10: 12 cites · 3 PMID · 5 book · 10 India-relevant | J10: PMID:31544070 | PMID:29273721 | 10.1007/s00403-018-1860-6 | K10: Air is bone-dry — it pulls moisture from skin fast. Take good care of your oily skin. | L10: Air is bone-dry — it pulls moisture from skin fast. Your dry skin with oily skin feels this as a manageable environmental hit. Light layers only. | M10: Air is bone-dry — it pulls moisture from skin fast. Skin compensates with rebound oil. Dehydrated-oily paradox at extreme. In Indian context: desert-region summer; heated indoor air winter. Light, non-greasy products work best. Cleanse twice if you've been outdoors — once to lift sunscreen and surface oil, once to clean. Keep heavier sealing creams off the T-zone (forehead, nose and chin) today; they trap oil. | N10: Balance | O10: HD | P10: Desert Rajasthan summer; heated indoor air winter
A11: H-CRIT-DRY-ACNE-010 | B11: Critical Low | C11: <10% | D11: Dry | E11: Acne | F11: 2 | G11: Moderate | H11: HIGH | I11: 12 cites · 11 PMID · 1 book · 10 India-relevant | J11: PMID:23334343 | PMID:38033568 | PMID:30238598 | K11: Air is bone-dry — it pulls moisture from skin fast. Keep pores clean to prevent breakouts. | L11: Air is bone-dry — it pulls moisture from skin fast. Your dry skin with acne feels this as a moderate environmental hit. Light layers only. | M11: Air is bone-dry — it pulls moisture from skin fast. Rebound oil from dehydration can trigger clogged pores even in non-oily types. In Indian context: desert-region summer; heated indoor air winter. Light, non-greasy products work best. Cleanse twice if you've been outdoors — once to lift sunscreen and surface oil, once to clean. Keep heavier sealing creams off the T-zone (forehead, nose and chin) today; they trap oil. | N11: Balance | O11: HD | P11: Desert Rajasthan summer; heated indoor air winter
A12: H-CRIT-DRY-UNEV-011 | B12: Critical Low | C12: <10% | D12: Dry | E12: Uneven Skin Tone / Tan | F12: 2 | G12: Moderate | H12: HIGH | I12: 24 cites · 12 PMID · 9 book · 12 India-relevant | J12: PMID:102946 | PMID:20209486 | PMID:31617869 | K12: Air is bone-dry — it pulls moisture from skin fast. Protect from sun to keep tone even. | L12: Air is bone-dry — it pulls moisture from skin fast. Your dry skin with uneven skin tone / tan feels this as a moderate environmental hit. Hydrate hard. | M12: Air is bone-dry — it pulls moisture from skin fast. Barrier breach amplifies the damage from every other stressor. In Indian context: desert-region summer; heated indoor air winter. Build moisture from the inside out: water-binding humectants (like glycerin) on damp skin, sealed with an emollient layer that locks moisture in. Apply within three minutes of any wash before water evaporates. A bedroom humidifier helps overnight. | N12: Hydrate | O12: HD | P12: Desert Rajasthan summer; heated indoor air winter
A13: H-CRIT-DRY-MELA-012 | B13: Critical Low | C13: <10% | D13: Dry | E13: Melasma | F13: 2 | G13: Moderate | H13: HIGH | I13: 5 cites · 5 PMID · 0 book · 1 India-relevant | J13: PMID:20209486 | PMID:22077137 | K13: Air is bone-dry — it pulls moisture from skin fast. Protect melasma patches from sun today. | L13: Air is bone-dry — it pulls moisture from skin fast. Your dry skin with melasma feels this as a moderate environmental hit. Hydrate hard. | M13: Air is bone-dry — it pulls moisture from skin fast. Compromised barrier amplifies impact of UV and heat indirectly. In Indian context: desert-region summer; heated indoor air winter. Build moisture from the inside out: water-binding humectants (like glycerin) on damp skin, sealed with an emollient layer that locks moisture in. Apply within three minutes of any wash before water evaporates. A bedroom humidifier helps overnight. | N13: Hydrate | O13: HD | P13: Desert Rajasthan summer; heated indoor air winter
... A226: H-EXT-SEN-FUNG | B226: Extreme | C226: >90% | D226: Sensitive | E226: Fungal Infection (Sweat & Folds) | F226: 4 | G226: Severe | H226: HIGH | I226: 18 cites · 4 PMID · 13 book · 18 India-relevant | J226: 10.62347/ELKP5340 | 10.1111/myc.13511 | 10.11622/smedj.2020068 | K226: Air is saturated — pores stay damp and clogged. Keep folds dry and cool to stop fungus. | L226: Saturated air — peak fungal risk in every skin fold and damp area. For sensitive skin with fungal flare-ups, keeping folds clean and dry, breathable cotton and a gentle clarifying wash help most. A gentle wash avoids over-stripping. | M226: Saturated air — peak fungal risk in every skin fold and damp area. When air is this damp, sweat lingers on skin and feeds common skin yeast and ringworm-type fungi — common in the Indian monsoon as itchy patches, flaky scalp, or scaly spots on the chest and back. In Indian context: Coastal peak monsoon; pre-storm conditions. If you're sweating in humid weather, keeping folds clean and dry, breathable cotton clothing and a gentle clarifying wash help most. Drying off after sweating and not sharing towels keep flare-ups down. | N226: Balance | O226: HH, TN | P226: Coastal peak monsoon; pre-storm conditions
A227: H-HIGH-NOR-HEAT | B227: High | C227: 61–79% | D227: Normal | E227: Heat Rash (Prickly Heat) | F227: 3 | G227: High | H227: INFERRED | I227: 7 cites · 0 PMID · 7 book · 7 India-relevant | K227: Air is humid — sweat doesn't dry easily. Stay cool and dry to prevent heat rash. | L227: Humid air stops sweat evaporating — trapped sweat triggers prickly heat. For normal skin with prickly heat, keeping skin cool and dry, loose cotton and a light moisturiser help. | M227: Humid air stops sweat evaporating — trapped sweat triggers prickly heat. When the air is humid, sweat can't evaporate, so it stays trapped and blocks sweat ducts — the direct cause of prickly heat and itch. In Indian context: Monsoon arrival; coastal cities year-round. If you're hot and sweaty, keeping skin cool and dry, loose cotton and a light non-greasy moisturiser help. Air flow and a cool rinse settle the rash quickly. | N227: Calm | O227: HD, HH, CN, TP, CH, TN | P227: Monsoon arrival; coastal cities year-round
A228: H-HIGH-DRY-HEAT | B228: High | C228: 61–79% | D228: Dry | E228: Heat Rash (Prickly Heat) | F228: 3 | G228: High | H228: INFERRED | I228: 7 cites · 0 PMID · 7 book · 7 India-relevant | K228: Air is humid — sweat doesn't dry easily. Stay cool and dry to prevent heat rash. | L228: Humid air stops sweat evaporating — trapped sweat triggers prickly heat. For dry skin with prickly heat, keeping skin cool and dry, loose cotton and a light moisturiser help. Choose light, not heavy, creams. | M228: Humid air stops sweat evaporating — trapped sweat triggers prickly heat. When the air is humid, sweat can't evaporate, so it stays trapped and blocks sweat ducts — the direct cause of prickly heat and itch. In Indian context: Monsoon arrival; coastal cities year-round. If you're hot and sweaty, keeping skin cool and dry, loose cotton and a light non-greasy moisturiser help. Air flow and a cool rinse settle the rash quickly. | N228: Calm | O228: HD, HH, CN, TP, CH, TN | P228: Monsoon arrival; coastal cities year-round
A229: H-HIGH-OIL-HEAT | B229: High | C229: 61–79% | D229: Oily | E229: Heat Rash (Prickly Heat) | F229: 3 | G229: High | H229: INFERRED | I229: 7 cites · 0 PMID · 7 book · 7 India-relevant | K229: Air is humid — sweat doesn't dry easily. Stay cool and dry to prevent heat rash. | L229: Humid air stops sweat evaporating — trapped sweat triggers prickly heat. For oily skin with prickly heat, keeping skin cool and dry, loose cotton and a light moisturiser help. A light gel won't clog ducts. | M229: Humid air stops sweat evaporating — trapped sweat triggers prickly heat. When the air is humid, sweat can't evaporate, so it stays trapped and blocks sweat ducts — the direct cause of prickly heat and itch. In Indian context: Monsoon arrival; coastal cities year-round. If you're hot and sweaty, keeping skin cool and dry, loose cotton and a light non-greasy moisturiser help. Air flow and a cool rinse settle the rash quickly. | N229: Calm | O229: HD, HH, CN, TP, CH, TN | P229: Monsoon arrival; coastal cities year-round
A230: H-HIGH-COM-HEAT | B230: High | C230: 61–79% | D230: Combination | E230: Heat Rash (Prickly Heat) | F230: 3 | G230: High | H230: INFERRED | I230: 7 cites · 0 PMID · 7 book · 7 India-relevant | K230: Air is humid — sweat doesn't dry easily. Stay cool and dry to prevent heat rash. | L230: Humid air stops sweat evaporating — trapped sweat triggers prickly heat. For combination skin with prickly heat, keeping skin cool and dry, loose cotton and a light moisturiser help. Keep all zones light. | M230: Humid air stops sweat evaporating — trapped sweat triggers prickly heat. When the air is humid, sweat can't evaporate, so it stays trapped and blocks sweat ducts — the direct cause of prickly heat and itch. In Indian context: Monsoon arrival; coastal cities year-round. If you're hot and sweaty, keeping skin cool and dry, loose cotton and a light non-greasy moisturiser help. Air flow and a cool rinse settle the rash quickly. | N230: Calm | O230: HD, HH, CN, TP, CH, TN | P230: Monsoon arrival; coastal cities year-round
A231: H-HIGH-SEN-HEAT | B231: High | C231: 61–79% | D231: Sensitive | E231: Heat Rash (Prickly Heat) | F231: 3 | G231: High | H231: INFERRED | I231: 7 cites · 0 PMID · 7 book · 7 India-relevant | K231: Air is humid — sweat doesn't dry easily. Stay cool and dry to prevent heat rash. | L231: Humid air stops sweat evaporating — trapped sweat triggers prickly heat. For sensitive skin with prickly heat, keeping skin cool and dry, loose cotton and a light moisturiser help. Sensitive skin stings — prioritise cooling. | M231: Humid air stops sweat evaporating — trapped sweat triggers prickly heat. When the air is humid, sweat can't evaporate, so it stays trapped and blocks sweat ducts — the direct cause of prickly heat and itch. In Indian context: Monsoon arrival; coastal cities year-round. If you're hot and sweaty, keeping skin cool and dry, loose cotton and a light non-greasy moisturiser help. Air flow and a cool rinse settle the rash quickly. | N231: Calm | O231: HD, HH, CN, TP, CH, TN | P231: Monsoon arrival; coastal cities year-round
A232: H-VHI-NOR-HEAT | B232: Very High | C232: 80–89% | D232: Normal | E232: Heat Rash (Prickly Heat) | F232: 4 | G232: Severe | H232: INFERRED | I232: 7 cites · 0 PMID · 7 book · 7 India-relevant | K232: Very humid air — sweat and oil sit on the skin. Cool down and stay dry to stop rash. | L232: Very humid — sweat can't dry, so heat rash and itch spike. For normal skin with prickly heat, keeping skin cool and dry, loose cotton and a light moisturiser help. | M232: Very humid — sweat can't dry, so heat rash and itch spike. When the air is humid, sweat can't evaporate, so it stays trapped and blocks sweat ducts — the direct cause of prickly heat and itch. In Indian context: warm, humid coastal areas monsoon (Jun–Sep). If you're hot and sweaty, keeping skin cool and dry, loose cotton and a light non-greasy moisturiser help. Air flow and a cool rinse settle the rash quickly. | N232: Calm | O232: HH, CN, TN | P232: Mumbai/Chennai/Kolkata monsoon (Jun–Sep)
A233: H-VHI-DRY-HEAT | B233: Very High | C233: 80–89% | D233: Dry | E233: Heat Rash (Prickly Heat) | F233: 4 | G233: Severe | H233: INFERRED | I233: 7 cites · 0 PMID · 7 book · 7 India-relevant | K233: Very humid air — sweat and oil sit on the skin. Cool down and stay dry to stop rash. | L233: Very humid — sweat can't dry, so heat rash and itch spike. For dry skin with prickly heat, keeping skin cool and dry, loose cotton and a light moisturiser help. Choose light, not heavy, creams. | M233: Very humid — sweat can't dry, so heat rash and itch spike. When the air is humid, sweat can't evaporate, so it stays trapped and blocks sweat ducts — the direct cause of prickly heat and itch. In Indian context: warm, humid coastal areas monsoon (Jun–Sep). If you're hot and sweaty, keeping skin cool and dry, loose cotton and a light non-greasy moisturiser help. Air flow and a cool rinse settle the rash quickly. | N233: Calm | O233: HH, CN, TN | P233: Mumbai/Chennai/Kolkata monsoon (Jun–Sep)
A234: H-VHI-OIL-HEAT | B234: Very High | C234: 80–89% | D234: Oily | E234: Heat Rash (Prickly Heat) | F234: 4 | G234: Severe | H234: INFERRED | I234: 7 cites · 0 PMID · 7 book · 7 India-relevant | K234: Very humid air — sweat and oil sit on the skin. Cool down and stay dry to stop rash. | L234: Very humid — sweat can't dry, so heat rash and itch spike. For oily skin with prickly heat, keeping skin cool and dry, loose cotton and a light moisturiser help. A light gel won't clog ducts. | M234: Very humid — sweat can't dry, so heat rash and itch spike. When the air is humid, sweat can't evaporate, so it stays trapped and blocks sweat ducts — the direct cause of prickly heat and itch. In Indian context: warm, humid coastal areas monsoon (Jun–Sep). If you're hot and sweaty, keeping skin cool and dry, loose cotton and a light non-greasy moisturiser help. Air flow and a cool rinse settle the rash quickly. | N234: Calm | O234: HH, CN, TN | P234: Mumbai/Chennai/Kolkata monsoon (Jun–Sep)
A235: H-VHI-COM-HEAT | B235: Very High | C235: 80–89% | D235: Combination | E235: Heat Rash (Prickly Heat) | F235: 4 | G235: Severe | H235: INFERRED | I235: 7 cites · 0 PMID · 7 book · 7 India-relevant | K235: Very humid air — sweat and oil sit on the skin. Cool down and stay dry to stop rash. | L235: Very humid — sweat can't dry, so heat rash and itch spike. For combination skin with prickly heat, keeping skin cool and dry, loose cotton and a light moisturiser help. Keep all zones light. | M235: Very humid — sweat can't dry, so heat rash and itch spike. When the air is humid, sweat can't evaporate, so it stays trapped and blocks sweat ducts — the direct cause of prickly heat and itch. In Indian context: warm, humid coastal areas monsoon (Jun–Sep). If you're hot and sweaty, keeping skin cool and dry, loose cotton and a light non-greasy moisturiser help. Air flow and a cool rinse settle the rash quickly. | N235: Calm | O235: HH, CN, TN | P235: Mumbai/Chennai/Kolkata monsoon (Jun–Sep)
A236: H-VHI-SEN-HEAT | B236: Very High | C236: 80–89% | D236: Sensitive | E236: Heat Rash (Prickly Heat) | F236: 4 | G236: Severe | H236: INFERRED | I236: 7 cites · 0 PMID · 7 book · 7 India-relevant | K236: Very humid air — sweat and oil sit on the skin. Cool down and stay dry to stop rash. | L236: Very humid — sweat can't dry, so heat rash and itch spike. For sensitive skin with prickly heat, keeping skin cool and dry, loose cotton and a light moisturiser help. Sensitive skin stings — prioritise cooling. | M236: Very humid — sweat can't dry, so heat rash and itch spike. When the air is humid, sweat can't evaporate, so it stays trapped and blocks sweat ducts — the direct cause of prickly heat and itch. In Indian context: warm, humid coastal areas monsoon (Jun–Sep). If you're hot and sweaty, keeping skin cool and dry, loose cotton and a light non-greasy moisturiser help. Air flow and a cool rinse settle the rash quickly. | N236: Calm | O236: HH, CN, TN | P236: Mumbai/Chennai/Kolkata monsoon (Jun–Sep)
A237: H-CRIT-NOR-HAIR-001 | B237: Critical Low | C237: <10% | D237: Normal | E237: Hair & Scalp (Shedding) | F237: 1 | G237: Low | H237: INFERRED | I237: 8 cites · 0 PMID · 8 book · 10 India-relevant | J237: see evidence base (sweat, scalp, monsoon) | K237: Air is bone-dry — it pulls moisture from skin fast. Rinse the scalp clean after sweat or grime. | L237: Sweat and damp air keep the scalp moist, which can irritate roots. For normal skin with hair and scalp concerns, a regular gentle scalp cleanse in sweaty, humid weather keeps roots fresh and comfortable. | M237: Sweat and damp air keep the scalp moist, which can irritate roots. In humid, sweaty weather the scalp stays damp for long stretches, which softens the skin and lets sweat salts and yeast build up around the roots. Keeping the scalp clean and dry between washes keeps it comfortable through monsoon. In Indian context: Monsoon and coastal humidity keep the scalp damp for months. A regular gentle scalp cleanse in sweaty, humid weather keeps roots fresh and comfortable. A simple, consistent cleanse is the main habit here. | N237: Cleanse | O237: CS, EI, NE | P237: Jun–Sep monsoon
A238: H-CRIT-DRY-HAIR-002 | B238: Critical Low | C238: <10% | D238: Dry | E238: Hair & Scalp (Shedding) | F238: 1 | G238: Low | H238: INFERRED | I238: 8 cites · 0 PMID · 8 book · 10 India-relevant | J238: see evidence base (sweat, scalp, monsoon) | K238: Air is bone-dry — it pulls moisture from skin fast. Rinse the scalp clean after sweat or grime. | L238: Sweat and damp air keep the scalp moist, which can irritate roots. For dry skin with hair and scalp concerns, a regular gentle scalp cleanse in sweaty, humid weather keeps roots fresh and comfortable. | M238: Sweat and damp air keep the scalp moist, which can irritate roots. In humid, sweaty weather the scalp stays damp for long stretches, which softens the skin and lets sweat salts and yeast build up around the roots. Keeping the scalp clean and dry between washes keeps it comfortable through monsoon. In Indian context: Monsoon and coastal humidity keep the scalp damp for months. A regular gentle scalp cleanse in sweaty, humid weather keeps roots fresh and comfortable. A simple, consistent cleanse is the main habit here. | N238: Cleanse | O238: CS, EI, NE | P238: Jun–Sep monsoon
A239: H-CRIT-OIL-HAIR-003 | B239: Critical Low | C239: <10% | D239: Oily | E239: Hair & Scalp (Shedding) | F239: 1 | G239: Low | H239: INFERRED | I239: 8 cites · 0 PMID · 8 book · 10 India-relevant | J239: see evidence base (sweat, scalp, monsoon) | K239: Air is bone-dry — it pulls moisture from skin fast. Rinse the scalp clean after sweat or grime. | L239: Sweat and damp air keep the scalp moist, which can irritate roots. For oily skin with hair and scalp concerns, a regular gentle scalp cleanse in sweaty, humid weather keeps roots fresh and comfortable. | M239: Sweat and damp air keep the scalp moist, which can irritate roots. In humid, sweaty weather the scalp stays damp for long stretches, which softens the skin and lets sweat salts and yeast build up around the roots. Keeping the scalp clean and dry between washes keeps it comfortable through monsoon. In Indian context: Monsoon and coastal humidity keep the scalp damp for months. A regular gentle scalp cleanse in sweaty, humid weather keeps roots fresh and comfortable. A simple, consistent cleanse is the main habit here. | N239: Cleanse | O239: CS, EI, NE | P239: Jun–Sep monsoon
A240: H-CRIT-COM-HAIR-004 | B240: Critical Low | C240: <10% | D240: Combination | E240: Hair & Scalp (Shedding) | F240: 1 | G240: Low | H240: INFERRED | I240: 8 cites · 0 PMID · 8 book · 10 India-relevant | J240: see evidence base (sweat, scalp, monsoon) | K240: Air is bone-dry — it pulls moisture from skin fast. Rinse the scalp clean after sweat or grime. | L240: Sweat and damp air keep the scalp moist, which can irritate roots. For combination skin with hair and scalp concerns, a regular gentle scalp cleanse in sweaty, humid weather keeps roots fresh and comfortable. | M240: Sweat and damp air keep the scalp moist, which can irritate roots. In humid, sweaty weather the scalp stays damp for long stretches, which softens the skin and lets sweat salts and yeast build up around the roots. Keeping the scalp clean and dry between washes keeps it comfortable through monsoon. In Indian context: Monsoon and coastal humidity keep the scalp damp for months. A regular gentle scalp cleanse in sweaty, humid weather keeps roots fresh and comfortable. A simple, consistent cleanse is the main habit here. | N240: Cleanse | O240: CS, EI, NE | P240: Jun–Sep monsoon
A241: H-CRIT-SEN-HAIR-005 | B241: Critical Low | C241: <10% | D241: Sensitive | E241: Hair & Scalp (Shedding) | F241: 1 | G241: Low | H241: INFERRED | I241: 8 cites · 0 PMID · 8 book · 10 India-relevant | J241: see evidence base (sweat, scalp, monsoon) | K241: Air is bone-dry — it pulls moisture from skin fast. Rinse the scalp clean after sweat or grime. | L241: Sweat and damp air keep the scalp moist, which can irritate roots. For sensitive skin with hair and scalp concerns, a regular gentle scalp cleanse in sweaty, humid weather keeps roots fresh and comfortable. | M241: Sweat and damp air keep the scalp moist, which can irritate roots. In humid, sweaty weather the scalp stays damp for long stretches, which softens the skin and lets sweat salts and yeast build up around the roots. Keeping the scalp clean and dry between washes keeps it comfortable through monsoon. In Indian context: Monsoon and coastal humidity keep the scalp damp for months. A regular gentle scalp cleanse in sweaty, humid weather keeps roots fresh and comfortable. A simple, consistent cleanse is the main habit here. | N241: Cleanse | O241: CS, EI, NE | P241: Jun–Sep monsoon
A242: H-VERY-NOR-HAIR-006 | B242: Very Low | C242: 10–19% | D242: Normal | E242: Hair & Scalp (Shedding) | F242: 1 | G242: Low | H242: INFERRED | I242: 8 cites · 0 PMID · 8 book · 10 India-relevant | J242: see evidence base (sweat, scalp, monsoon) | K242: Very dry air — skin loses water 2-3× faster than usual. Rinse the scalp clean after sweat or grime. | L242: Sweat and damp air keep the scalp moist, which can irritate roots. For normal skin with hair and scalp concerns, a regular gentle scalp cleanse in sweaty, humid weather keeps roots fresh and comfortable. | M242: Sweat and damp air keep the scalp moist, which can irritate roots. In humid, sweaty weather the scalp stays damp for long stretches, which softens the skin and lets sweat salts and yeast build up around the roots. Keeping the scalp clean and dry between washes keeps it comfortable through monsoon. In Indian context: Monsoon and coastal humidity keep the scalp damp for months. A regular gentle scalp cleanse in sweaty, humid weather keeps roots fresh and comfortable. A simple, consistent cleanse is the main habit here. | N242: Cleanse | O242: CS, EI, NE | P242: Jun–Sep monsoon
A243: H-VERY-DRY-HAIR-007 | B243: Very Low | C243: 10–19% | D243: Dry | E243: Hair & Scalp (Shedding) | F243: 1 | G243: Low | H243: INFERRED | I243: 8 cites · 0 PMID · 8 book · 10 India-relevant | J243: see evidence base (sweat, scalp, monsoon) | K243: Very dry air — skin loses water 2-3× faster than usual. Rinse the scalp clean after sweat or grime. | L243: Sweat and damp air keep the scalp moist, which can irritate roots. For dry skin with hair and scalp concerns, a regular gentle scalp cleanse in sweaty, humid weather keeps roots fresh and comfortable. | M243: Sweat and damp air keep the scalp moist, which can irritate roots. In humid, sweaty weather the scalp stays damp for long stretches, which softens the skin and lets sweat salts and yeast build up around the roots. Keeping the scalp clean and dry between washes keeps it comfortable through monsoon. In Indian context: Monsoon and coastal humidity keep the scalp damp for months. A regular gentle scalp cleanse in sweaty, humid weather keeps roots fresh and comfortable. A simple, consistent cleanse is the main habit here. | N243: Cleanse | O243: CS, EI, NE | P243: Jun–Sep monsoon
A244: H-VERY-OIL-HAIR-008 | B244: Very Low | C244: 10–19% | D244: Oily | E244: Hair & Scalp (Shedding) | F244: 1 | G244: Low | H244: INFERRED | I244: 8 cites · 0 PMID · 8 book · 10 India-relevant | J244: see evidence base (sweat, scalp, monsoon) | K244: Very dry air — skin loses water 2-3× faster than usual. Rinse the scalp clean after sweat or grime. | L244: Sweat and damp air keep the scalp moist, which can irritate roots. For oily skin with hair and scalp concerns, a regular gentle scalp cleanse in sweaty, humid weather keeps roots fresh and comfortable. | M244: Sweat and damp air keep the scalp moist, which can irritate roots. In humid, sweaty weather the scalp stays damp for long stretches, which softens the skin and lets sweat salts and yeast build up around the roots. Keeping the scalp clean and dry between washes keeps it comfortable through monsoon. In Indian context: Monsoon and coastal humidity keep the scalp damp for months. A regular gentle scalp cleanse in sweaty, humid weather keeps roots fresh and comfortable. A simple, consistent cleanse is the main habit here. | N244: Cleanse | O244: CS, EI, NE | P244: Jun–Sep monsoon
A245: H-VERY-COM-HAIR-009 | B245: Very Low | C245: 10–19% | D245: Combination | E245: Hair & Scalp (Shedding) | F245: 1 | G245: Low | H245: INFERRED | I245: 8 cites · 0 PMID · 8 book · 10 India-relevant | J245: see evidence base (sweat, scalp, monsoon) | K245: Very dry air — skin loses water 2-3× faster than usual. Rinse the scalp clean after sweat or grime. | L245: Sweat and damp air keep the scalp moist, which can irritate roots. For combination skin with hair and scalp concerns, a regular gentle scalp cleanse in sweaty, humid weather keeps roots fresh and comfortable. | M245: Sweat and damp air keep the scalp moist, which can irritate roots. In humid, sweaty weather the scalp stays damp for long stretches, which softens the skin and lets sweat salts and yeast build up around the roots. Keeping the scalp clean and dry between washes keeps it comfortable through monsoon. In Indian context: Monsoon and coastal humidity keep the scalp damp for months. A regular gentle scalp cleanse in sweaty, humid weather keeps roots fresh and comfortable. A simple, consistent cleanse is the main habit here. | N245: Cleanse | O245: CS, EI, NE | P245: Jun–Sep monsoon
A246: H-VERY-SEN-HAIR-010 | B246: Very Low | C246: 10–19% | D246: Sensitive | E246: Hair & Scalp (Shedding) | F246: 1 | G246: Low | H246: INFERRED | I246: 8 cites · 0 PMID · 8 book · 10 India-relevant | J246: see evidence base (sweat, scalp, monsoon) | K246: Very dry air — skin loses water 2-3× faster than usual. Rinse the scalp clean after sweat or grime. | L246: Sweat and damp air keep the scalp moist, which can irritate roots. For sensitive skin with hair and scalp concerns, a regular gentle scalp cleanse in sweaty, humid weather keeps roots fresh and comfortable. | M246: Sweat and damp air keep the scalp moist, which can irritate roots. In humid, sweaty weather the scalp stays damp for long stretches, which softens the skin and lets sweat salts and yeast build up around the roots. Keeping the scalp clean and dry between washes keeps it comfortable through monsoon. In Indian context: Monsoon and coastal humidity keep the scalp damp for months. A regular gentle scalp cleanse in sweaty, humid weather keeps roots fresh and comfortable. A simple, consistent cleanse is the main habit here. | N246: Cleanse | O246: CS, EI, NE | P246: Jun–Sep monsoon
A247: H-LOW-NOR-HAIR-011 | B247: Low | C247: 20–29% | D247: Normal | E247: Hair & Scalp (Shedding) | F247: 1 | G247: Low | H247: INFERRED | I247: 8 cites · 0 PMID · 8 book · 10 India-relevant | J247: see evidence base (sweat, scalp, monsoon) | K247: Air is on the drier side — barrier needs support. Rinse the scalp clean after sweat or grime. | L247: Sweat and damp air keep the scalp moist, which can irritate roots. For normal skin with hair and scalp concerns, a regular gentle scalp cleanse in sweaty, humid weather keeps roots fresh and comfortable. | M247: Sweat and damp air keep the scalp moist, which can irritate roots. In humid, sweaty weather the scalp stays damp for long stretches, which softens the skin and lets sweat salts and yeast build up around the roots. Keeping the scalp clean and dry between washes keeps it comfortable through monsoon. In Indian context: Monsoon and coastal humidity keep the scalp damp for months. A regular gentle scalp cleanse in sweaty, humid weather keeps roots fresh and comfortable. A simple, consistent cleanse is the main habit here. | N247: Cleanse | O247: CS, EI, NE | P247: Jun–Sep monsoon
A248: H-LOW-DRY-HAIR-012 | B248: Low | C248: 20–29% | D248: Dry | E248: Hair & Scalp (Shedding) | F248: 1 | G248: Low | H248: INFERRED | I248: 8 cites · 0 PMID · 8 book · 10 India-relevant | J248: see evidence base (sweat, scalp, monsoon) | K248: Air is on the drier side — barrier needs support. Rinse the scalp clean after sweat or grime. | L248: Sweat and damp air keep the scalp moist, which can irritate roots. For dry skin with hair and scalp concerns, a regular gentle scalp cleanse in sweaty, humid weather keeps roots fresh and comfortable. | M248: Sweat and damp air keep the scalp moist, which can irritate roots. In humid, sweaty weather the scalp stays damp for long stretches, which softens the skin and lets sweat salts and yeast build up around the roots. Keeping the scalp clean and dry between washes keeps it comfortable through monsoon. In Indian context: Monsoon and coastal humidity keep the scalp damp for months. A regular gentle scalp cleanse in sweaty, humid weather keeps roots fresh and comfortable. A simple, consistent cleanse is the main habit here. | N248: Cleanse | O248: CS, EI, NE | P248: Jun–Sep monsoon
... A271: H-EXTR-SEN-HAIR-035 | B271: Extreme | C271: >90% | D271: Sensitive | E271: Hair & Scalp (Shedding) | F271: 4 | G271: Severe | H271: INFERRED | I271: 8 cites · 0 PMID · 8 book · 10 India-relevant | J271: see evidence base (sweat, scalp, monsoon) | K271: Air is saturated — pores stay damp and clogged. Rinse the scalp clean after sweat or grime. | L271: Sweat and damp air keep the scalp moist, which can irritate roots. For sensitive skin with hair and scalp concerns, a regular gentle scalp cleanse in sweaty, humid weather keeps roots fresh and comfortable. | M271: Sweat and damp air keep the scalp moist, which can irritate roots. In humid, sweaty weather the scalp stays damp for long stretches, which softens the skin and lets sweat salts and yeast build up around the roots. Keeping the scalp clean and dry between washes keeps it comfortable through monsoon. In Indian context: Monsoon and coastal humidity keep the scalp damp for months. A regular gentle scalp cleanse in sweaty, humid weather keeps roots fresh and comfortable. A simple, consistent cleanse is the main habit here. | N271: Cleanse | O271: CS, EI, NE | P271: Jun–Sep monsoon

Sheet 8. Compound Scenarios Index
A1: ID | B1: Name | C1: Temp Band | D1: UV Band | E1: AQI Band | F1: RH Band | G1: Dominant Drivers | H1: Zones | I1: Seasons | J1: Mechanism | K1: Cities Example
A2: C01 | B2: Pre-Monsoon Sun & Heat | C2: hot | D2: very_high | E2: moderate | F2: low | G2: UV, Temperature, Humidity | H2: CN, HD, TP | I2: Apr–Jun | J2: Three drivers combine: intense UV burns proteins, heat doubles oil and sweat, dry air pulls moisture out. | K2: the north plains and plateau (Apr–May)
A3: C02 | B3: Heatwave Crisis | C3: extreme_heat | D3: extreme | E3: moderate | F3: very_low | G3: Temperature, UV, Humidity | H3: CN, HD | I3: May–Jun | J3: Heatwave conditions — body and skin dehydrating; UV burns possible in minutes; barrier proteins denaturing. | K3: the hot interior regions heatwave days
A4: C03 | B4: Dry-Heat Desert Day | C4: hot | D4: very_high | E4: moderate | F4: critical_low | G4: Humidity, Temperature, UV | H4: HD | I4: Apr–Jun | J4: Bone-dry desert air strips moisture while heat and UV pile on. Barrier is fighting on three fronts. | K4: the desert regions (Apr–Jun)
A5: C04 | B5: Beach Day UV | C5: hot | D5: very_high | E5: satisfactory | F5: very_high | G5: UV, Temperature, Humidity | H5: HH | I5: Mar–May, Oct–Nov | J5: Water and sand reflect 25–50% more UV. Heat plus humidity locks oil on the surface. | K5: the western and southern coasts beach days
A6: C05 | B6: Hot-Humid Coastal Summer | C6: hot | D6: high | E6: moderate | F6: very_high | G6: Humidity, Temperature | H6: HH | I6: Apr–May | J6: Heat doubles oil, humidity keeps sweat from evaporating. Pores stay occluded most of the day. | K6: warm, humid coastal areas (Apr–May)
A7: C06 | B7: Monsoon Acne Trifecta | C7: warm | D7: moderate | E7: poor | F7: very_high | G7: Humidity, AQI, Temperature | H7: HH, CN | I7: Jul–Sep | J7: Heat, humidity, and pollution combine. Sweat and oil cannot evaporate, particles settle into pores, and pollution drives inflammation. | K7: warm, humid coastal areas monsoon
A8: C07 | B8: Coastal Monsoon Standard | C8: warm | D8: moderate | E8: satisfactory | F8: very_high | G8: Humidity | H8: HH | I8: Jul–Sep | J8: Heavy humid air keeps sweat on skin and traps oil. Fungal risk in folds rises. | K8: Coastal monsoon weeks across India
A9: C08 | B9: Tropical NE Saturated | C9: warm | D9: moderate | E9: good | F9: extreme | G9: Humidity | H9: TN | I9: Jun–Sep | J9: Air at saturation. Sweat won't evaporate. Pores and folds stay blocked. | K9: the humid Northeast monsoon
A10: C09 | B10: Pre-Monsoon Humidity Surge | C10: hot | D10: high | E10: moderate | F10: high | G10: Humidity, Temperature, UV | H10: HH, CN | I10: Jun (early) | J10: Humidity surges before rains arrive. Heat is still high. Sweat-oil-UV trifecta peaks. | K10: major metros early Jun
A11: C10 | B11: North-Plains Winter Smog | C11: cold | D11: moderate | E11: very_poor | F11: very_low | G11: AQI, Humidity, Temperature | H11: CN | I11: Nov–Jan | J11: Inversion traps pollution; dry cold air cracks the barrier; pollution then seeps through. Worst combination for many concerns. | K11: the north plains in winter
A12: C11 | B12: Post-Diwali AQI Spike | C12: cool | D12: moderate | E12: severe | F12: low | G12: AQI | H12: CN, TP | I12: Oct–Nov (Diwali week) | J12: Severe overnight AQI spike from firecrackers + inversion. Acute particulate-driven barrier and pigment insult. | K12: Most North/Central India Diwali week
... A22: C21 | B22: Indoor AC Office Hours | C22: cool | D22: low | E22: satisfactory | F22: low | G22: Humidity, Temperature | H22: any | I22: year-round (office and indoor workers) | J22: Eight or more hours of AC-conditioned air at 20–35% humidity steadily pulls water from skin. Chronic dehydration accumulates even though no single hour feels harsh. | K22: All metro office workers; IT corridors; long-haul flights

Sheet 9. Compound Cell Library
A1: Compound ID | B1: Scenario Name | C1: Skin Type | D1: Concern | E1: Compound Risk | F1: Risk Level | G1: Confidence (Compound) | H1: Evidence Summary | I1: L0 Compact | J1: L1 Personalised | K1: L2 Explainer | L1: Action Cluster | M1: Zones | N1: Seasons | O1: Indian Cities
A2: C01-NOR-DRYN-0001 | B2: Pre-Monsoon Sun & Heat | C2: Normal | D2: Dryness | E2: 3 | F2: High | G2: MODERATE | H2: Temperature: 44 cites · 26 PMID · 8 book · 11 India-relevant | UV: 28 cites · 4 PMID · 22 book · 7 India-relevant | Humidity: 93 cites · 50 PMID · 31 book · 31 India-relevant | AQI: 18 cites · 2 PMID · 10 book · 14 India-relevant | I2: Pre-Monsoon Sun & Heat. Moisturise often to protect your skin. | J2: Pre-Monsoon Sun & Heat: Three drivers combine: intense UV burns proteins, heat doubles oil and sweat, dry air pulls moisture out. For normal, dryness-prone skin, these conditions add real environmental load together. | K2: Pre-Monsoon Sun & Heat. Three drivers combine: intense UV burns proteins, heat doubles oil and sweat, dry air pulls moisture out. For normal, dryness-prone skin, the dominant drivers are UV + Temperature + Humidity. Typical in: Apr–Jun across CN, HD, TP zones. A broad-spectrum sunscreen, reapplied every two hours, is the single biggest lever today. | L2: Shield | M2: CN, HD, TP | N2: Apr–Jun | O2: Delhi, Jaipur, Nagpur, Pune (Apr–May)
A3: C01-NOR-ECZE-0002 | B3: Pre-Monsoon Sun & Heat | C3: Normal | D3: Eczema | E3: 3 | F3: High | G3: MODERATE | H3: Temperature: 7 cites · 2 PMID · 1 book · 0 India-relevant | UV: 5 cites · 0 PMID · 5 book · 3 India-relevant | Humidity: 30 cites · 15 PMID · 12 book · 15 India-relevant | AQI: 9 cites · 0 PMID · 3 book · 4 India-relevant | I3: Pre-Monsoon Sun & Heat. Soothe eczema-prone skin to avoid flare-ups. | J3: Pre-Monsoon Sun & Heat: Three drivers combine: intense UV burns proteins, heat doubles oil and sweat, dry air pulls moisture out. For normal, eczema-prone skin, these conditions add real environmental load together. | K3: Pre-Monsoon Sun & Heat. Three drivers combine: intense UV burns proteins, heat doubles oil and sweat, dry air pulls moisture out. For normal, eczema-prone skin, the dominant drivers are UV + Temperature + Humidity. Typical in: Apr–Jun across CN, HD, TP zones. A broad-spectrum sunscreen, reapplied every two hours, is the single biggest lever today. | L3: Shield | M3: CN, HD, TP | N3: Apr–Jun | O3: Delhi, Jaipur, Nagpur, Pune (Apr–May)
A4: C01-NOR-OILY-0003 | B4: Pre-Monsoon Sun & Heat | C4: Normal | D4: Oily Skin | E4: 4 | F4: Severe | G4: MODERATE | H4: Temperature: 18 cites · 8 PMID · 1 book · 4 India-relevant | UV: 16 cites · 2 PMID · 14 book · 8 India-relevant | Humidity: 4 cites · 3 PMID · 1 book · 4 India-relevant | AQI: 6 cites · 2 PMID · 4 book · 4 India-relevant | I4: Pre-Monsoon Sun & Heat. Stay on top of oil today. | J4: Pre-Monsoon Sun & Heat: Three drivers combine: intense UV burns proteins, heat doubles oil and sweat, dry air pulls moisture out. For normal, oil-prone skin, the combination is severe — visible effects likely within hours. | K4: Pre-Monsoon Sun & Heat. Three drivers combine: intense UV burns proteins, heat doubles oil and sweat, dry air pulls moisture out. For normal, oil-prone skin, the dominant drivers are UV + Temperature + Humidity. Typical in: Apr–Jun across CN, HD, TP zones. A broad-spectrum sunscreen, reapplied every two hours, is the single biggest lever today. | L4: Shield | M4: CN, HD, TP | N4: Apr–Jun | O4: Delhi, Jaipur, Nagpur, Pune (Apr–May)
A5: C01-NOR-ACNE-0004 | B5: Pre-Monsoon Sun & Heat | C5: Normal | D5: Acne | E5: 4 | F5: Severe | G5: MODERATE | H5: Temperature: 20 cites · 14 PMID · 1 book · 13 India-relevant | UV: 22 cites · 4 PMID · 17 book · 18 India-relevant | Humidity: 13 cites · 11 PMID · 1 book · 11 India-relevant | AQI: 6 cites · 0 PMID · 5 book · 3 India-relevant | I5: Pre-Monsoon Sun & Heat. Protect acne-prone pores from breakouts today. | J5: Pre-Monsoon Sun & Heat: Three drivers combine: intense UV burns proteins, heat doubles oil and sweat, dry air pulls moisture out. For normal, acne-prone skin, the combination is severe — visible effects likely within hours. | K5: Pre-Monsoon Sun & Heat. Three drivers combine: intense UV burns proteins, heat doubles oil and sweat, dry air pulls moisture out. For normal, acne-prone skin, the dominant drivers are UV + Temperature + Humidity. Typical in: Apr–Jun across CN, HD, TP zones. A broad-spectrum sunscreen, reapplied every two hours, is the single biggest lever today. | L5: Shield | M5: CN, HD, TP | N5: Apr–Jun | O5: Delhi, Jaipur, Nagpur, Pune (Apr–May)
A6: C01-NOR-UNEV-0005 | B6: Pre-Monsoon Sun & Heat | C6: Normal | D6: Uneven Skin Tone / Tan | E6: 4 | F6: Severe | G6: MODERATE | H6: Temperature: 41 cites · 27 PMID · 6 book · 17 India-relevant | UV: 195 cites · 13 PMID · 149 book · 133 India-relevant | Humidity: 21 cites · 12 PMID · 7 book · 12 India-relevant | AQI: 36 cites · 0 PMID · 17 book · 23 India-relevant | I6: Pre-Monsoon Sun & Heat. Shield skin from sun to limit tanning. | J6: Pre-Monsoon Sun & Heat: Three drivers combine: intense UV burns proteins, heat doubles oil and sweat, dry air pulls moisture out. For normal, pigment-sensitive skin, the combination is severe — visible effects likely within hours. | K6: Pre-Monsoon Sun & Heat. Three drivers combine: intense UV burns proteins, heat doubles oil and sweat, dry air pulls moisture out. For normal, pigment-sensitive skin, the dominant drivers are UV + Temperature + Humidity. Typical in: Apr–Jun across CN, HD, TP zones. A broad-spectrum sunscreen, reapplied every two hours, is the single biggest lever today. | L6: Shield | M6: CN, HD, TP | N6: Apr–Jun | O6: Delhi, Jaipur, Nagpur, Pune (Apr–May)
A7: C01-NOR-MELA-0006 | B7: Pre-Monsoon Sun & Heat | C7: Normal | D7: Melasma | E7: 5 | F7: Critical | G7: MODERATE | H7: Temperature: 3 cites · 0 PMID · 3 book · 1 India-relevant | UV: 77 cites · 2 PMID · 49 book · 44 India-relevant | Humidity: 5 cites · 5 PMID · 0 book · 1 India-relevant | AQI: 2 cites · 0 PMID · 1 book · 2 India-relevant | I7: Pre-Monsoon Sun & Heat. Shield melasma patches from sun now. | J7: Pre-Monsoon Sun & Heat: Three drivers combine: intense UV burns proteins, heat doubles oil and sweat, dry air pulls moisture out. For normal, melasma-affected skin, these conditions hit hardest together — assume severe impact today. | K7: Pre-Monsoon Sun & Heat. Three drivers combine: intense UV burns proteins, heat doubles oil and sweat, dry air pulls moisture out. For normal, melasma-affected skin, the dominant drivers are UV + Temperature + Humidity. Typical in: Apr–Jun across CN, HD, TP zones. A broad-spectrum sunscreen, reapplied every two hours, is the single biggest lever today. | L7: Shield | M7: CN, HD, TP | N7: Apr–Jun | O7: Delhi, Jaipur, Nagpur, Pune (Apr–May)
A8: C01-DRY-DRYN-0007 | B8: Pre-Monsoon Sun & Heat | C8: Dry | D8: Dryness | E8: 5 | F8: Critical | G8: MODERATE | H8: Temperature: 49 cites · 26 PMID · 12 book · 15 India-relevant | UV: 30 cites · 4 PMID · 24 book · 9 India-relevant | Humidity: 133 cites · 53 PMID · 50 book · 52 India-relevant | AQI: 30 cites · 1 PMID · 22 book · 25 India-relevant | I8: Pre-Monsoon Sun & Heat. Lock in moisture to protect your skin now. | J8: Pre-Monsoon Sun & Heat: Three drivers combine: intense UV burns proteins, heat doubles oil and sweat, dry air pulls moisture out. For your dry, dryness-prone skin, these conditions hit hardest together — assume severe impact today. | K8: Pre-Monsoon Sun & Heat. Three drivers combine: intense UV burns proteins, heat doubles oil and sweat, dry air pulls moisture out. For your dry, dryness-prone skin, the dominant drivers are UV + Temperature + Humidity. Typical in: Apr–Jun across CN, HD, TP zones. A broad-spectrum sunscreen, reapplied every two hours, is the single biggest lever today. | L8: Shield | M8: CN, HD, TP | N8: Apr–Jun | O8: Delhi, Jaipur, Nagpur, Pune (Apr–May)
A9: C01-DRY-ECZE-0008 | B9: Pre-Monsoon Sun & Heat | C9: Dry | D9: Eczema | E9: 5 | F9: Critical | G9: MODERATE | H9: Temperature: 13 cites · 2 PMID · 7 book · 6 India-relevant | UV: 10 cites · 0 PMID · 10 book · 8 India-relevant | Humidity: 52 cites · 19 PMID · 28 book · 31 India-relevant | AQI: 20 cites · 1 PMID · 13 book · 14 India-relevant | I9: Pre-Monsoon Sun & Heat. Soothe and protect eczema-prone skin now. | J9: Pre-Monsoon Sun & Heat: Three drivers combine: intense UV burns proteins, heat doubles oil and sweat, dry air pulls moisture out. For dry, eczema-prone skin, these conditions hit hardest together — assume severe impact today. | K9: Pre-Monsoon Sun & Heat. Three drivers combine: intense UV burns proteins, heat doubles oil and sweat, dry air pulls moisture out. For dry, eczema-prone skin, the dominant drivers are UV + Temperature + Humidity. Typical in: Apr–Jun across CN, HD, TP zones. A broad-spectrum sunscreen, reapplied every two hours, is the single biggest lever today. | L9: Shield | M9: CN, HD, TP | N9: Apr–Jun | O9: Delhi, Jaipur, Nagpur, Pune (Apr–May)
A10: C01-DRY-OILY-0009 | B10: Pre-Monsoon Sun & Heat | C10: Dry | D10: Oily Skin | E10: 4 | F10: Severe | G10: MODERATE | H10: Temperature: 19 cites · 8 PMID · 2 book · 4 India-relevant | UV: 16 cites · 2 PMID · 14 book · 8 India-relevant | Humidity: 12 cites · 3 PMID · 5 book · 10 India-relevant | AQI: 4 cites · 0 PMID · 4 book · 2 India-relevant | I10: Pre-Monsoon Sun & Heat. Stay on top of oil today. | J10: Pre-Monsoon Sun & Heat: Three drivers combine: intense UV burns proteins, heat doubles oil and sweat, dry air pulls moisture out. For dry, oil-prone skin, the combination is severe — visible effects likely within hours. | K10: Pre-Monsoon Sun & Heat. Three drivers combine: intense UV burns proteins, heat doubles oil and sweat, dry air pulls moisture out. For dry, oil-prone skin, the dominant drivers are UV + Temperature + Humidity. Typical in: Apr–Jun across CN, HD, TP zones. A broad-spectrum sunscreen, reapplied every two hours, is the single biggest lever today. | L10: Shield | M10: CN, HD, TP | N10: Apr–Jun | O10: Delhi, Jaipur, Nagpur, Pune (Apr–May)
A11: C01-DRY-ACNE-0010 | B11: Pre-Monsoon Sun & Heat | C11: Dry | D11: Acne | E11: 5 | F11: Critical | G11: MODERATE | H11: Temperature: 20 cites · 14 PMID · 1 book · 13 India-relevant | UV: 22 cites · 4 PMID · 17 book · 18 India-relevant | Humidity: 13 cites · 11 PMID · 1 book · 11 India-relevant | AQI: 6 cites · 0 PMID · 5 book · 3 India-relevant | I11: Pre-Monsoon Sun & Heat. Protect acne-prone pores from breakouts now. | J11: Pre-Monsoon Sun & Heat: Three drivers combine: intense UV burns proteins, heat doubles oil and sweat, dry air pulls moisture out. For dry, acne-prone skin, these conditions hit hardest together — assume severe impact today. | K11: Pre-Monsoon Sun & Heat. Three drivers combine: intense UV burns proteins, heat doubles oil and sweat, dry air pulls moisture out. For dry, acne-prone skin, the dominant drivers are UV + Temperature + Humidity. Typical in: Apr–Jun across CN, HD, TP zones. A broad-spectrum sunscreen, reapplied every two hours, is the single biggest lever today. | L11: Shield | M11: CN, HD, TP | N11: Apr–Jun | O11: Delhi, Jaipur, Nagpur, Pune (Apr–May)
A12: C01-DRY-UNEV-0011 | B12: Pre-Monsoon Sun & Heat | C12: Dry | D12: Uneven Skin Tone / Tan | E12: 5 | F12: Critical | G12: MODERATE | H12: Temperature: 44 cites · 27 PMID · 8 book · 20 India-relevant | UV: 196 cites · 13 PMID · 150 book · 134 India-relevant | Humidity: 27 cites · 12 PMID · 10 book · 14 India-relevant | AQI: 38 cites · 0 PMID · 19 book · 25 India-relevant | I12: Pre-Monsoon Sun & Heat. Shield skin from sun to prevent tanning. | J12: Pre-Monsoon Sun & Heat: Three drivers combine: intense UV burns proteins, heat doubles oil and sweat, dry air pulls moisture out. For dry, pigment-sensitive skin, these conditions hit hardest together — assume severe impact today. | K12: Pre-Monsoon Sun & Heat. Three drivers combine: intense UV burns proteins, heat doubles oil and sweat, dry air pulls moisture out. For dry, pigment-sensitive skin, the dominant drivers are UV + Temperature + Humidity. Typical in: Apr–Jun across CN, HD, TP zones. A broad-spectrum sunscreen, reapplied every two hours, is the single biggest lever today. | L12: Shield | M12: CN, HD, TP | N12: Apr–Jun | O12: Delhi, Jaipur, Nagpur, Pune (Apr–May)
A13: C01-DRY-MELA-0012 | B13: Pre-Monsoon Sun & Heat | C13: Dry | D13: Melasma | E13: 5 | F13: Critical | G13: MODERATE | H13: Temperature: 3 cites · 0 PMID · 3 book · 1 India-relevant | UV: 77 cites · 2 PMID · 49 book · 44 India-relevant | Humidity: 5 cites · 5 PMID · 0 book · 1 India-relevant | AQI: 2 cites · 0 PMID · 1 book · 2 India-relevant | I13: Pre-Monsoon Sun & Heat. Shield melasma patches from sun now. | J13: Pre-Monsoon Sun & Heat: Three drivers combine: intense UV burns proteins, heat doubles oil and sweat, dry air pulls moisture out. For dry, melasma-affected skin, these conditions hit hardest together — assume severe impact today. | K13: Pre-Monsoon Sun & Heat. Three drivers combine: intense UV burns proteins, heat doubles oil and sweat, dry air pulls moisture out. For dry, melasma-affected skin, the dominant drivers are UV + Temperature + Humidity. Typical in: Apr–Jun across CN, HD, TP zones. A broad-spectrum sunscreen, reapplied every two hours, is the single biggest lever today. | L13: Shield | M13: CN, HD, TP | N13: Apr–Jun | O13: Delhi, Jaipur, Nagpur, Pune (Apr–May)
... A941: C19-SEN-HAIR | B941: Snow-Reflected UV | C941: Sensitive | D941: Hair & Scalp (Shedding) | E941: 4 | F941: Severe | G941: INFERRED | H941: Compound · scalp UV + sweat + pollution evidence · India-relevant | I941: Snow-Reflected UV. Cover the scalp in strong sun; rinse it clean after grime. | J941: In Snow-Reflected UV, very strong sun adds to hair and scalp concerns. For sensitive skin with hair and scalp concerns, covering the scalp and part line in strong sun protects it; hair shielded from sun stays in better shape. | K941: In Snow-Reflected UV, very strong sun works on hair and scalp concerns. The scalp takes the same sun, sweat and pollution as facial skin, especially along the part line, which stresses the roots over time. In Indian context: the Himalayan belt winter (Dec–Mar). If outdoor time today is long, covering the scalp and part line in strong sun protects it; hair shielded from sun stays in better shape. A simple, consistent cleanse is the main habit here. | L941: Cleanse | M941: CH | N941: Dec–Mar | O941: Kashmir, Himachal, Uttarakhand winter

Sheet 10. Master Library
A1: Scenario ID | B1: Factor | C1: Band | D1: Range | E1: Band Key | F1: Skin Type | G1: Concern | H1: Risk | I1: Risk Level | J1: Confidence | K1: Evidence Summary | L1: PMID Anchors | M1: L0 Compact | N1: L1 Personalised | O1: L2 Explainer | P1: Action Cluster | Q1: Zones | R1: Indian Cities/Season
A2: T-EXTR-NOR-DRYN-001 | B2: Temperature | C2: Extreme Cold | D2: <5°C | E2: extreme_cold | F2: Normal | G2: Dryness | H2: 5 | I2: Critical | J2: HIGH | K2: 39 cites · 26 PMID · 8 book · 7 India-relevant | L2: PMID:37953512 | PMID:35053992 | PMID:31029804 | M2: Sub-zero air holds almost no moisture. Lock in moisture to protect your skin now. | N2: Sub-zero air holds almost no moisture. For your skin with dryness, this is as tough as it gets for your skin. Layer a water-binding humectant (like glycerin) on damp skin, then seal with an emollient. Apply within three minutes of any wash. | O2: Sub-zero air holds almost no moisture. Air this cold holds almost no water — your skin is losing moisture every second it's exposed. In Indian context: the Himalayan belt (Dec–Jan); -ve impact in mountain belt. Build moisture from the inside out: water-binding humectants (like glycerin) on damp skin, sealed with an emollient layer that locks moisture in. Apply within three minutes of any wash before water evaporates. A bedroom humidifier helps overnight. | P2: Hydrate | Q2: CH | R2: Kashmir, Himachal (Dec–Jan); -ve impact in mountain belt
A3: T-EXTR-NOR-ECZE-002 | B3: Temperature | C3: Extreme Cold | D3: <5°C | E3: extreme_cold | F3: Normal | G3: Eczema | H3: 5 | I3: Critical | J3: MODERATE | K3: 7 cites · 2 PMID · 1 book · 0 India-relevant | L3: PMID:37336870 | PMID:21426384 | 10.1016/j.anai.2023.08.007 | M3: Sub-zero air holds almost no moisture. Soothe and protect eczema-prone skin now. | N3: Sub-zero air holds almost no moisture. For your skin with eczema, this is as tough as it gets for your skin. Layer a water-binding humectant (like glycerin) on damp skin, then seal with an emollient. Apply within three minutes of any wash. | O3: Sub-zero air holds almost no moisture. Cold this severe collapses your skin's natural moisture-binders. Flares are nearly automatic without intervention. In Indian context: the Himalayan belt (Dec–Jan); -ve impact in mountain belt. Build moisture from the inside out: water-binding humectants (like glycerin) on damp skin, sealed with an emollient layer that locks moisture in. Apply within three minutes of any wash before water evaporates. A bedroom humidifier helps overnight. | P3: Hydrate | Q3: CH | R3: Kashmir, Himachal (Dec–Jan); -ve impact in mountain belt
A4: T-EXTR-NOR-OILY-003 | B4: Temperature | C4: Extreme Cold | D4: <5°C | E4: extreme_cold | F4: Normal | G4: Oily Skin | H4: 0 | I4: Negligible | J4: MODERATE | K4: 12 cites · 8 PMID · 0 book · 0 India-relevant | L4: PMID:11096379 | PMID:27333493 | PMID:19467097 | M4: Sub-zero air holds almost no moisture. Maintain your usual routine for oily skin. | N4: Sub-zero air holds almost no moisture. Your skin faces no extra pressure from this factor today. Hydrate hard. | O4: Sub-zero air holds almost no moisture. Oil flow slows in sub-zero air. You may feel matte, but the barrier underneath needs more care, not less. In Indian context: the Himalayan belt (Dec–Jan); -ve impact in mountain belt. Build moisture from the inside out: water-binding humectants (like glycerin) on damp skin, sealed with an emollient layer that locks moisture in. Apply within three minutes of any wash before water evaporates. A bedroom humidifier helps overnight. | P4: Hydrate | Q4: CH | R4: Kashmir, Himachal (Dec–Jan); -ve impact in mountain belt
A5: T-EXTR-NOR-ACNE-004 | B5: Temperature | C5: Extreme Cold | D5: <5°C | E5: extreme_cold | F5: Normal | G5: Acne | H5: 1 | I5: Low | J5: HIGH | K5: 14 cites · 14 PMID · 0 book · 9 India-relevant | L5: PMID:37336870 | PMID:30238598 | PMID:12227481 | M5: Sub-zero air holds almost no moisture. Take good care of your acne-prone pores. | N5: Sub-zero air holds almost no moisture. Your skin with acne feels this as a manageable environmental hit. Hydrate hard. | O5: Sub-zero air holds almost no moisture. Bacteria slow down, but heated indoor air strips skin — barrier cracks can still drive breakouts. In Indian context: the Himalayan belt (Dec–Jan); -ve impact in mountain belt. Build moisture from the inside out: water-binding humectants (like glycerin) on damp skin, sealed with an emollient layer that locks moisture in. Apply within three minutes of any wash before water evaporates. A bedroom humidifier helps overnight. | P5: Hydrate | Q5: CH | R5: Kashmir, Himachal (Dec–Jan); -ve impact in mountain belt
A6: T-EXTR-NOR-UNEV-005 | B6: Temperature | C6: Extreme Cold | D6: <5°C | E6: extreme_cold | F6: Normal | G6: Uneven Skin Tone / Tan | H6: 1 | I6: Low | J6: HIGH | K6: 39 cites · 27 PMID · 5 book · 15 India-relevant | L6: PMID:14764172 | PMID:22374181 | PMID:37855862 | M6: Sub-zero air holds almost no moisture. Daily sun protection keeps tone even. | N6: Sub-zero air holds almost no moisture. Your skin with uneven skin tone / tan feels this as a manageable environmental hit. Routine day. | O6: Sub-zero air holds almost no moisture. Cold itself doesn't darken skin, but snow and ice can reflect up to 80% of UV onto your face. In Indian context: the Himalayan belt (Dec–Jan); -ve impact in mountain belt. Environmental pressure is low today — a good day to be consistent with your basics. Sunscreen still matters regardless of weather; visible light triggers pigment year-round. | P6: Maintain | Q6: CH | R6: Kashmir, Himachal (Dec–Jan); -ve impact in mountain belt
A7: T-EXTR-NOR-MELA-006 | B7: Temperature | C7: Extreme Cold | D7: <5°C | E7: extreme_cold | F7: Normal | G7: Melasma | H7: 1 | I7: Low | J7: MODERATE | K7: 3 cites · 0 PMID · 3 book · 1 India-relevant | L7: Melasma and Vitiligo in Brown , p.p13 | Melasma and Vitiligo in Brown , p.p349 | M7: Sub-zero air holds almost no moisture. Daily sun protection keeps melasma calm. | N7: Sub-zero air holds almost no moisture. Your skin with melasma feels this as a manageable environmental hit. Routine day. | O7: Sub-zero air holds almost no moisture. Cold air narrows surface blood vessels — skin looks evener, but heat-cold cycles can trigger pigment surges. In Indian context: the Himalayan belt (Dec–Jan); -ve impact in mountain belt. Environmental pressure is low today — a good day to be consistent with your basics. Sunscreen still matters regardless of weather; visible light triggers pigment year-round. | P7: Maintain | Q7: CH | R7: Kashmir, Himachal (Dec–Jan); -ve impact in mountain belt
A8: T-EXTR-DRY-DRYN-007 | B8: Temperature | C8: Extreme Cold | D8: <5°C | E8: extreme_cold | F8: Dry | G8: Dryness | H8: 5 | I8: Critical | J8: HIGH | K8: 44 cites · 26 PMID · 12 book · 11 India-relevant | L8: PMID:37953512 | PMID:35053992 | PMID:31029804 | M8: Sub-zero air holds almost no moisture. Lock in moisture to protect your skin now. | N8: Sub-zero air holds almost no moisture. For your dry skin with dryness, this is as tough as it gets for your skin. Layer a water-binding humectant (like glycerin) on damp skin, then seal with an emollient. Apply within three minutes of any wash. | O8: Sub-zero air holds almost no moisture. Air this cold holds almost no water — your skin is losing moisture every second it's exposed. In Indian context: the Himalayan belt (Dec–Jan); -ve impact in mountain belt. Build moisture from the inside out: water-binding humectants (like glycerin) on damp skin, sealed with an emollient layer that locks moisture in. Apply within three minutes of any wash before water evaporates. A bedroom humidifier helps overnight. | P8: Hydrate | Q8: CH | R8: Kashmir, Himachal (Dec–Jan); -ve impact in mountain belt
A9: T-EXTR-DRY-ECZE-008 | B9: Temperature | C9: Extreme Cold | D9: <5°C | E9: extreme_cold | F9: Dry | G9: Eczema | H9: 5 | I9: Critical | J9: MODERATE | K9: 12 cites · 2 PMID · 6 book · 5 India-relevant | L9: PMID:37336870 | PMID:21426384 | 10.1016/j.anai.2023.08.007 | M9: Sub-zero air holds almost no moisture. Soothe and protect eczema-prone skin now. | N9: Sub-zero air holds almost no moisture. For your dry skin with eczema, this is as tough as it gets for your skin. Layer a water-binding humectant (like glycerin) on damp skin, then seal with an emollient. Apply within three minutes of any wash. | O9: Sub-zero air holds almost no moisture. Cold this severe collapses your skin's natural moisture-binders. Flares are nearly automatic without intervention. In Indian context: the Himalayan belt (Dec–Jan); -ve impact in mountain belt. Build moisture from the inside out: water-binding humectants (like glycerin) on damp skin, sealed with an emollient layer that locks moisture in. Apply within three minutes of any wash before water evaporates. A bedroom humidifier helps overnight. | P9: Hydrate | Q9: CH | R9: Kashmir, Himachal (Dec–Jan); -ve impact in mountain belt
A10: T-EXTR-DRY-OILY-009 | B10: Temperature | C10: Extreme Cold | D10: <5°C | E10: extreme_cold | F10: Dry | G10: Oily Skin | H10: 1 | I10: Low | J10: MODERATE | K10: 13 cites · 8 PMID · 1 book · 0 India-relevant | L10: PMID:11096379 | PMID:27333493 | PMID:19467097 | M10: Sub-zero air holds almost no moisture. Take good care of your oily skin. | N10: Sub-zero air holds almost no moisture. Your dry skin with oily skin feels this as a manageable environmental hit. Hydrate hard. | O10: Sub-zero air holds almost no moisture. Oil flow slows in sub-zero air. You may feel matte, but the barrier underneath needs more care, not less. In Indian context: the Himalayan belt (Dec–Jan); -ve impact in mountain belt. Build moisture from the inside out: water-binding humectants (like glycerin) on damp skin, sealed with an emollient layer that locks moisture in. Apply within three minutes of any wash before water evaporates. A bedroom humidifier helps overnight. | P10: Hydrate | Q10: CH | R10: Kashmir, Himachal (Dec–Jan); -ve impact in mountain belt
A11: T-EXTR-DRY-ACNE-010 | B11: Temperature | C11: Extreme Cold | D11: <5°C | E11: extreme_cold | F11: Dry | G11: Acne | H11: 2 | I11: Moderate | J11: HIGH | K11: 14 cites · 14 PMID · 0 book · 9 India-relevant | L11: PMID:37336870 | PMID:30238598 | PMID:12227481 | M11: Sub-zero air holds almost no moisture. Keep pores clean to prevent breakouts. | N11: Sub-zero air holds almost no moisture. Your dry skin with acne feels this as a moderate environmental hit. Hydrate hard. | O11: Sub-zero air holds almost no moisture. Bacteria slow down, but heated indoor air strips skin — barrier cracks can still drive breakouts. In Indian context: the Himalayan belt (Dec–Jan); -ve impact in mountain belt. Build moisture from the inside out: water-binding humectants (like glycerin) on damp skin, sealed with an emollient layer that locks moisture in. Apply within three minutes of any wash before water evaporates. A bedroom humidifier helps overnight. | P11: Hydrate | Q11: CH | R11: Kashmir, Himachal (Dec–Jan); -ve impact in mountain belt
A12: T-EXTR-DRY-UNEV-011 | B12: Temperature | C12: Extreme Cold | D12: <5°C | E12: extreme_cold | F12: Dry | G12: Uneven Skin Tone / Tan | H12: 2 | I12: Moderate | J12: HIGH | K12: 42 cites · 27 PMID · 7 book · 18 India-relevant | L12: PMID:14764172 | PMID:22374181 | PMID:37855862 | M12: Sub-zero air holds almost no moisture. Protect from sun to keep tone even. | N12: Sub-zero air holds almost no moisture. Your dry skin with uneven skin tone / tan feels this as a moderate environmental hit. Routine day. | O12: Sub-zero air holds almost no moisture. Cold itself doesn't darken skin, but snow and ice can reflect up to 80% of UV onto your face. In Indian context: the Himalayan belt (Dec–Jan); -ve impact in mountain belt. Environmental pressure is low today — a good day to be consistent with your basics. Sunscreen still matters regardless of weather; visible light triggers pigment year-round. | P12: Maintain | Q12: CH | R12: Kashmir, Himachal (Dec–Jan); -ve impact in mountain belt
A13: T-EXTR-DRY-MELA-012 | B13: Temperature | C13: Extreme Cold | D13: <5°C | E13: extreme_cold | F13: Dry | G13: Melasma | H13: 2 | I13: Moderate | J13: MODERATE | K13: 3 cites · 0 PMID · 3 book · 1 India-relevant | L13: Melasma and Vitiligo in Brown , p.p13 | Melasma and Vitiligo in Brown , p.p349 | M13: Sub-zero air holds almost no moisture. Protect melasma patches from sun today. | N13: Sub-zero air holds almost no moisture. Your dry skin with melasma feels this as a moderate environmental hit. Routine day. | O13: Sub-zero air holds almost no moisture. Cold air narrows surface blood vessels — skin looks evener, but heat-cold cycles can trigger pigment surges. In Indian context: the Himalayan belt (Dec–Jan); -ve impact in mountain belt. Environmental pressure is low today — a good day to be consistent with your basics. Sunscreen still matters regardless of weather; visible light triggers pigment year-round. | P13: Maintain | Q13: CH | R13: Kashmir, Himachal (Dec–Jan); -ve impact in mountain belt
... A816: H-EXT-SEN-FUNG | B816: Humidity | C816: Extreme | D816: >90% | E816: extreme | F816: Sensitive | G816: Fungal Infection (Sweat & Folds) | H816: 4 | I816: Severe | J816: HIGH | K816: 18 cites · 4 PMID · 13 book · 18 India-relevant | L816: 10.62347/ELKP5340 | 10.1111/myc.13511 | 10.11622/smedj.2020068 | M816: Air is saturated — pores stay damp and clogged. Keep folds dry and cool to stop fungus. | N816: Saturated air — peak fungal risk in every skin fold and damp area. For sensitive skin with fungal flare-ups, keeping folds clean and dry, breathable cotton and a gentle clarifying wash help most. A gentle wash avoids over-stripping. | O816: Saturated air — peak fungal risk in every skin fold and damp area. When air is this damp, sweat lingers on skin and feeds common skin yeast and ringworm-type fungi — common in the Indian monsoon as itchy patches, flaky scalp, or scaly spots on the chest and back. In Indian context: Coastal peak monsoon; pre-storm conditions. If you're sweating in humid weather, keeping folds clean and dry, breathable cotton clothing and a gentle clarifying wash help most. Drying off after sweating and not sharing towels keep flare-ups down. | P816: Balance | Q816: HH, TN | R816: Coastal peak monsoon; pre-storm conditions
A817: T-WARM-NOR-FUNG | B817: Temperature | C817: Warm | D817: 28–34°C | E817: warm | F817: Normal | G817: Fungal Infection (Sweat & Folds) | H817: 2 | I817: Moderate | J817: INFERRED | K817: 9 cites · 0 PMID · 8 book · 7 India-relevant | M817: Warm air starts to bump up oil production. Keep skin folds dry to avoid fungus. | N817: Warm, sweaty folds create the damp setting fungus prefers. For normal skin with fungal flare-ups, breathable cotton, staying dry and a gentle clarifying wash help. | O817: Warm, sweaty folds create the damp setting fungus prefers. Heat plus sweat trapped in folds creates the warm, damp setting fungus prefers, raising the risk of ringworm and yeast flare-ups. In Indian context: Most of India (Mar–Apr, Sep–Oct). If your day involves heat and sweat, breathable cotton, staying dry and a gentle clarifying wash help. Changing out of damp clothes quickly makes a real difference. | P817: Balance | Q817: HD, HH, CN, TP, CH, TN | R817: Most of India (Mar–Apr, Sep–Oct)
